Workbook

Sheet BILAN GENERAL
A1: BILAN GENERAL DE TABLEAU MARGE BENEFICIAIRE
B2: 2019 | C2: 2020 | D2: 2021 | E2: 2022 | F2: 2023 | G2: 2024 | H2: PROJECTED 2025
A3: JANV | B3: 4054748 | C3: 2708658 | D3: 2016935 | E3: 2670520 | F3: 8001529
A4: FEV | B4: 2506986 | C4: 3722151 | D4: 1172280 | E4: 2550569 | F4: 8899888
A5: MARS | B5: 3088124 | C5: 2227332 | D5: 1461243 | E5: 5112299 | F5: 7286920
A6: AVRIL | B6: 3765436 | D6: 1964055 | E6: 3749790 | F6: 6165018
A7: MAI | B7: 4087698 | D7: 1421985 | E7: 8134015 | F7: 10221695
A8: JUIN | B8: 2847899 | D8: 2235817 | E8: 6914727 | F8: 11631907
A9: JUIL | B9: 2562496 | D9: 2392760 | E9: 8444336 | F9: 10756417
A10: AOUT | B10: 3038847 | C10: 1087250 | D10: 4431247 | E10: 8414693 | F10: 10365520
A11: SEPT | B11: 3738723 | C11: 709370 | D11: 2952131 | E11: 12182359 | F11: 10640419
A12: OCT | B12: 5144842 | C12: 988155 | D12: 2545712 | E12: 10620735 | F12: 17199623
A13: NOV | B13: 2456022 | C13: 1097157 | D13: 3959852 | E13: 7686701 | F13: 13774945
A14: DEC | B14: 3078458 | C14: 1115342 | D14: 3099835 | E14: 3483357 | F14: 9705932
A15: TOTAL | B15: =SUM(B3:B14) | C15: =SUM(C3:C14) | D15: =SUM(D3:D14) | E15: =SUM(E3:E14) | F15: =SUM(F3:F14)
A17: left 13,816,262 to BEP with 2019 MARGE DE BENEFICIAIRE | C17: left 990,340 to BEP with 2020

Sheet JANVIER
A1: DATE | B1: CIES | C1: TRAVEL DATE | D1: PARCOURS | E1: N FACTURE | F1: ENTREPRISE | G1: NOMS/PRENOMS | H1: APPORTEUR | I1: TARIF HT | J1: TC | K1: TM | L1: FS | M1: LIEU ACHAT | N1: NUMERO DU BILLET | O1: NBRE SGTS | P1: AVANCE 01 | Q1: AVANCE 02 | R1: RGLT | S1: SOLDE | T1: DATE RGLT | U1: MODE RGLT | V1: OBS
A2: 45665 | B2: AF | C2: 17FEB-02MAR | D2: DLA-NTE-DLA | E2: 00008/01/2025 | F2: ADSNET | G2: KENFACK GUEFO EPSE JIOTSA EDWIGE | H2: DG | J2: 725950 | K2: 660020 | L2: =J2-K2 | M2: GOLITE | N2: ETKT 0575827796850 | O2: 4 | R2: 725950 | S2: =J2-P2-R2 | T2: 45763 | U2: BANQUE | V2: CHQ 2988599
A3: 45671 | B3: QC | C3: 16JAN. | D3: DLA-NSI-DLA | E3: 00018/01/2025 | F3: ATLANTIQUE | G3: RAOUL CHARLEMAGNE RAYMOND YAPO | H3: DG | I3: 36840 | J3: 124940 | K3: 106740 | L3: =J3-K3 | M3: KUI | N3: ETKT 0400300037012 | R3: 124940 | S3: =J3-P3-R3 | T3: 45734 | U3: BANQUE | V3: CHQ 2342450
A4: 45679 | B4: SN | C4: 03FEB-09FEB | D4: DLA-CDG-DLA | E4: 00051/01/2025 | F4: ATLANTIQUE | G4: FOTADZONG TCHIO THEOPHILE | H4: DG | J4: 2245950 | K4: 1925420 | L4: =J4-K4 | M4: NDC | N4: ETKT 0829049042116 | R4: 2245950 | S4: =J4-P4-R4 | T4: 45734 | U4: BANQUE | V4: CHQ 2342450
A5: 45681 | E5: 00057/01/2025 | F5: ATLANTIQUE | G5: FOTADZONG TCHIO THEOPHILE | H5: DG | J5: 56000 | K5: 32000 | L5: =J5-K5 | O5: VISA MAROC | R5: 56000 | S5: =J5-P5-R5 | T5: 45734 | U5: BANQUE | V5: CHQ 2342450
A6: 45687 | E6: 00080/01/2025 | F6: ATLANTIQUE | G6: FOTADZONG TCHIO THEOPHILE | J6: 946900 | O6: HERGEMENT | R6: 946900 | S6: =J6-P6-R6 | T6: 45734 | U6: BANQUE | V6: CHQ 2342450
A7: 45676 | B7: J7 | C7: 20JAN. | D7: SSG-DLA | E7: 00037/01/2025 | F7: BANGE BANK | G7: OBIANG NCHAMA JOSE MIGUEL | H7: DG | J7: 149950 | K7: 118700 | L7: =J7-K7 | M7: J7 | N7: ETKT 27722616419 | R7: 148152 | S7: =J7-P7-R7 | T7: 45695 | U7: V/R
A8: 45677 | B8: QC | C8: 21JAN-22JAN | D8: NSI-DLA-NSI | E8: 00040/01/2025 | F8: BANGE BANK | G8: MVONDO ASSAM BONAVENTURE | H8: DG | J8: 165950 | K8: 146140 | L8: =J8-K8 | M8: KIU | N8: ETKT 0400300037014 | R8: 164691 | S8: =J8-P8-R8 | T8: 45695 | U8: V/R
A9: 45680 | B9: C8 | C9: 26JAN-29JAN | D9: DLA-SSG-DLA | E9: 00053/01/2025 | F9: BANGE BANK | G9: BIYANG OBIANG ELSA ANTONIA | H9: DG | J9: 309093 | K9: 256093 | L9: =J9-K9 | M9: C8 | N9: ETKT 49850000310507 | R9: 306093 | S9: =J9-P9-R9 | T9: 45862 | U9: V/R
A10: 45680 | B10: C8 | C10: 26JAN-29JAN | D10: DLA-SSG-DLA | E10: 00053/01/2025 | F10: BANGE BANK | G10: NVE BIYANG CELEDONIO | H10: DG | J10: 26857 | K10: 16857 | L10: =J10-K10 | M10: C8 | N10: ETKT 49850 000310508 | R10: 26857 | S10: =J10-P10-R10 | T10: 45862 | U10: V/R
A11: 45686 | B11: C8 | C11: 31JAN. | D11: SSG-DLA | E11: 00081/01/2025 | F11: BANGE BANK | G11: BIYANG OBIANG ELSA ANTONIA | H11: DG | J11: 73900 | K11: 58000 | L11: =J11-K11 | M11: C8 | N11: ETKT 49850000312295 | O11: EXCHANGE | R11: 73001 | S11: =J11-P11-R11 | T11: 45695 | U11: V/R
A12: 45686 | B12: C8 | C12: 31JAN. | D12: SSG-DLA | E12: 00081/01/2025 | F12: BANGE BANK | G12: NVE BIYANG CELEDONIO | H12: DG | J12: 0 | K12: 0 | L12: =J12-K12 | M12: C8 | N12: ETKT 49850000312295 | O12: EXCHANGE | S12: =J12-P12-R12
A13: 45681 | E13: 00060/01/2025 | F13: CABINET DENTAIRE G2 | G13: GAMGNE GUIADEM CATHERINE MARCELLE | H13: DG | J13: 60000 | K13: 46000 | L13: =J13-K13 | O13: VISA | R13: 60000 | S13: =J13-P13-Q13-R13 | T13: 45676 | U13: CAISSE
A14: 45681 | B14: SN | C14: 31JAN-05FEB | D14: DLA-CDG-DLA | E14: 00065/01/2025 | F14: CABINET DENTAIRE G2 | G14: GAMGNE GUIADEM CATHERINE MARCELLE | H14: DG | J14: 2090000 | K14: 1925420 | L14: =J14-K14 | M14: NDC | N14: ETKT 0829049042122 | R14: 2090000 | S14: =J14-P14-Q14-R14 | T14: 45676 | U14: CAISSE
A15: 45684 | B15: SN | C15: 17APR. | D15: DLA-CDG | E15: 00071/01/2025 | F15: CABINET DENTAIRE G2 | G15: GAMGNE GUIADEM CATHERINE MARCELLE | H15: DG | J15: 189000 | K15: 164000 | L15: =J15-K15 | M15: SN | N15: ETKT 0823038968286 | R15: 189000 | S15: =J15-P15-Q15-R15 | T15: 45676 | U15: CAISSE
A16: 45666 | B16: KP | C16: 23JAN. | D16: NIM-DLA | E16: 00012/01/2025 | F16: CABTE | G16: ABDOULAYE ALIO MAHAMAN LAWAN | H16: DG | I16: 222000 | J16: 498600 | K16: 445280 | L16: =J16-K16 | M16: GOLITE | N16: ETKT 032587796855 | O16: 2 | R16: 498900 | S16: =J16-P16-R16 | T16: 45667 | U16: BANQUE | V16: CHQ 8484219
A17: 45673 | B17: SN | C17: 18MAR-02APR | D17: DLA-MEM-DLA | E17: 00025/01/2025 | F17: CABTE | G17: DJEUGAP EPSE NTSAGUIM FERNANDE ALIENCE | H17: DG | I17: 663800 | J17: 1168900 | K17: 1049782 | L17: =J17-K17 | M17: GOLITE | N17: ETKT 0825827796871-872 | O17: 6 | R17: 1168900 | S17: =J17-P17-R17 | T17: 45688 | U17: BANQUE | V17: CHQ 3023335
A18: 45665 | B18: QC | C18: 20JAN-23JAN | D18: DLA-NGE-DLA | E18: 00010/01/2025 | F18: CANAL+ | G18: NA IMMA AMADOU HAMIDOU | H18: DG | I18: 59340 | J18: 153640 | K18: 131640 | L18: =J18-K18 | M18: KIU | N18: ETKT 0400300037011 | R18: 153640 | S18: =J18-P18-R18 | T18: 45779 | U18: V/R
A19: 45667 | B19: ET | C19: 14JAN-04FEB | D19: DLA-BGF-DLA | E19: 00014/01/2025 | F19: CANAL+ | G19: BOUJEKE TCHEKOULONG WILLIAM | H19: DG | I19: 225100 | J19: 523900 | K19: 455947 | L19: =J19-K19 | M19: GOLITE | N19: ETKT 4595827796857 | O19: 2 | R19: 523900 | S19: =J19-P19-R19 | T19: 45779 | U19: V/R
A20: 45680 | B20: SN | C20: 09FEB-15FEB | D20: DLA-DSS-DLA | E20: 00055/01/2025 | F20: CANAL+ | G20: YOUBISSI TOWO EPSE ZEINSE F JUSTINE DIANE | H20: DG | J20: 681920 | K20: 620488 | L20: =J20-K20 | M20: GOLITE | N20: ETKT 0325827796893 | O20: 4 | R20: 681920 | S20: =J20-P20-R20 | T20: 45754 | U20: V/R
A21: 45681 | B21: QC | C21: 27JAN-27JAN | D21: DLA-NSI-DLA | E21: 00064/01/2025 | F21: CANAL+ | G21: GNABE KOUKOU MAWOUSSE | H21: DG | J21: 121740 | K21: 94340 | L21: =J21-K21 | M21: KIU | N21: ETKT 0400300037017 | S21: =J21-P21-R21
A22: 45681 | B22: QC | C22: 27JAN-27JAN | D22: DLA-NSI-DLA | E22: 00064/01/2025 | F22: CANAL+ | G22: YOUATOU PENE FABRICE | H22: DG | J22: 121740 | K22: 94340 | L22: =J22-K22 | M22: KIU | N22: ETKT 0400300037018 | S22: =J22-P22-R22
A23: 45688 | B23: WB | C23: 31JAN. | D23: BGF-DLA | E23: 00093/01/2025 | F23: CANAL+ | G23: BOUJEKE TCHEKOULONG WILLIAM | H23: DG | J23: 111950 | K23: 63000 | L23: =J23-K23 | M23: GOLITE | N23: ETKT 4595827796913 | O23: EXCHANGE | R23: 111950 | S23: =J23-P23-R23 | T23: 45754 | U23: V/R
A24: 45688 | B24: QC | C24: 02FEB-08FEB | D24: DLA-NSI-DLA | E24: 00093/01/2025 | F24: CANAL+ | G24: BOUJEKE TCHEKOULONG WILLIAM | H24: DG | I24: 33640 | J24: 119540 | K24: 86540 | L24: =J24-K24 | M24: KIU | N24: ETKT 0400300037019 | R24: 119540 | S24: =J24-P24-R24 | T24: 45754 | U24: V/R
A25: 45688 | B25: QC | C25: 02FEB. | D25: DLA-BFX | E25: 00092/01/2025 | F25: CANAL+ | G25: MAKOUGAM BRIGITTE | H25: DG | I25: 17370 | J25: 71500 | K25: 49150 | L25: =J25-K25 | M25: KIU | N25: ETKT 0400300037020 | R25: 71500 | S25: =J25-P25-R25 | T25: 45754 | U25: V/R
A26: 45688 | B26: QC | C26: 06FEB-09FEB | D26: DLA-NSI-DLA | E26: 00092/01/2025 | F26: CANAL+ | G26: MAKOUGAM BRIGITTE | H26: DG | I26: 33640 | J26: 117900 | K26: 86500 | L26: =J26-K26 | M26: KIU | N26: ETKT 0400300037021 | R26: 117900 | S26: =J26-P26-R26 | T26: 45754 | U26: V/R
A27: 45660 | B27: J7 | C27: 04JAN. | D27: BSG -DLA | E27: 00004/01/2025 | F27: DAF BANGE BANK | G27: NVE MODJO JUSTINO NGUERE | H27: DG | J27: 223900 | K27: 173900 | L27: =J27-K27 | M27: J7 | N27: ETKT 27722420665 | P27: 0 | R27: 570870 | S27: 0 | T27: 45670 | U27: CAISSE | V27: 19JAN. | W27: +237 6 98 40 54 70
A28: 45660 | B28: J7 | C28: 04JAN. | D28: BSG -DLA | E28: 00004/01/2025 | F28: DAF BANGE BANK | G28: MOHAMADOU AISSA | H28: DG | J28: 271800 | K28: 231200 | L28: =J28-K28 | M28: J7 | N28: ETKT 27722420681 | V28: 19JAN. | W28: +237 6 98 40 54 71
A29: 45660 | B29: QC | C29: 05JAN. | D29: DLA-NSI | E29: 00004/01/2025 | F29: DAF BANGE BANK | G29: NVE MODJO JUSTINO NGUERE | H29: DG | J29: 75170 | K29: 60170 | L29: =J29-K29 | M29: KIU | N29: ETKT 0400300037010 | V29: 19JAN. | W29: +237 6 98 40 54 72
A30: 45681 | B30: C8 | C30: 26JAN-29JAN | D30: DLA-SSG-DLA | E30: 00068/01/20250 | F30: DAF BANGE BANK | G30: ADIDJA TALATOU | H30: DG | J30: 256000 | K30: 256000 | L30: =J30-K30 | M30: C8 | N30: ETKT 49850000310899 | R30: 256000 | S30: =J30-P30-R30 | T30: 45726 | U30: OM
A31: 45686 | B31: C8 | C31: 31JAN. | D31: SSG-DLA | E31: 00083/01/2025 | F31: DAF BANGE BANK | G31: ADIDJA TALATOU | H31: DG | J31: 68000 | K31: 53000 | L31: =J31-K31 | M31: C8 | N31: ETKT 49850000312293 | O31: EXCHANGE | R31: 68000 | S31: =J31-P31-R31
A32: 45681 | B32: AF | C32: 13FEB-02MAR | D32: DLA-CDG-DLA | E32: 00063/01/2025 | F32: HARVEST | G32: KAMGAING MARC | H32: DG | J32: 2411900 | K32: 2266500 | L32: =J32-K32 | M32: BLUEBERRY | N32: ETKT 0572306439131 | R32: 2411900 | S32: =J32-P32-R32 | T32: 45702 | U32: V/R
A33: 45678 | F33: HORUS | G33: ONANA CYRILLE BERTRAND | H33: DG | J33: 275000 | K33: 200000 | L33: =J33-K33 | O33: VISA | R33: 275000 | S33: =J33-P33-R33 | T33: 45692 | U33: V/R
A34: 45686 | B34: EK | C34: 07FEB-10FEB | D34: CDG-DXB-CDG | E34: 00082/01/2025 | F34: HORUS | G34: ONANA CYRILLE BERTRAND | H34: DG | J34: 5897900 | K34: 5477250 | L34: =J34-K34 | M34: BLUEBERRY | N34: ETKT 1762113933918 | P34: 4441025 | R34: 1456875 | S34: =J34-P34-R34 | T34: 45715 | U34: V/R
A35: 45688 | B35: ET | C35: 07FEV-10FEB | D35: DLA-DXB-DLA | E35: 00085/01/2025 | F35: HORUS | G35: WAFO MAURICE | H35: DG | I35: 170000 | J35: 2488920 | K35: 2241020 | L35: =J35-K35 | M35: GOLLITE | N35: ETKT 0715827796914 | O35: 4 | P35: 746580 | R35: 1742340 | S35: =J35-P35-R35 | T35: 45737 | U35: V/R
A36: 45673 | B36: AT | C36: 20JAN-05MAR | D36: CMN-DLA-CMN | E36: 00023/01/2025 | F36: KALFRELEC | G36: NICORA GUY CARLO ALPHONSE | H36: DG | I36: 534500 | J36: 857950 | K36: 769675 | L36: =J36-K36 | M36: AT | N36: ETKT 0145827796875 | O36: 2 | S36: =J36-P36-R36
A37: 45682 | B37: HF | C37: 28JAN-31JAN | D37: DLA-ABJ-DLA | E37: 00070/01/2025 | F37: KETCH | G37: BETCHEM NARCISSE | H37: DG | I37: 140600 | J37: 505800 | K37: 481684 | L37: =J37-K37 | M37: GOLITE | N37: ETKT 4835827796897 | O37: 2 | P37: 300000 | R37: 831600 | S37: =J37+J38+J39+J40-P37-R37 | T37: 45692 | U37: V/R
A38: 45682 | B38: HF | C38: 28JAN-31JAN | D38: DLA-ABJ-DLA | E38: 00070/01/2025 | F38: KETCH | G38: NGOUEN, EMMANUEL | H38: DG | I38: 140600 | J38: 505800 | K38: 481684 | L38: =J38-K38 | M38: GOLITE | N38: ETKT 4835827796898 | O38: 2
A39: 45684 | B39: HF | C39: 29JAN-31JAN | D39: DLA-ABJ-DLA | E39: 00070/01/2025 | F39: KETCH | G39: BETCHEM NARCISSE | H39: DG | J39: 60000 | K39: 30000 | L39: =J39-K39 | M39: GOLITE | N39: ETKT 4835827796900 | O39: EXCHANGE
A40: 45684 | B40: HF | C40: 29JAN-31JAN | D40: DLA-ABJ-DLA | E40: 00070/01/2025 | F40: KETCH | G40: NGOUEN, EMMANUEL | H40: DG | J40: 60000 | K40: 30000 | L40: =J40-K40 | M40: GOLITE | N40: ETKT 4835827796901 | O40: EXCHANGE
A41: 45672 | B41: KP | C41: 16JAN. | D41: BLQ-NSI | E41: 00020/01/2025 | F41: KUEDA | G41: KUEDA HARMAND BERTRAND | H41: MRS HEUNA | I41: 423300 | J41: 113800 | K41: 83500 | L41: =J41-K41 | M41: GOLITE | N41: ETKT 2355827796866 | O41: EXCHANGE | R41: 113800 | S41: =J41-P41-R41 | T41: 45673 | U41: CAISSE | V41: SOLDE
A42: 45664 | B42: ET | C42: 20JAN-05FEB | D42: DLA-DEL-DLA | E42: 00009/01/2025 | F42: Mme AZEMO | G42: DONFACK EPSE AZEMO CHANTALE | H42: DG | I42: 248800 | J42: 615820 | K42: 578356 | L42: =J42-K42 | M42: GOLITE | N42: ETKT 0715827796849 | O42: 4 | P42: 0 | R42: 615820 | S42: =J42-P42-R42 | T42: 45664 | U42: CAISSE | V42: 15JAN.
A43: 45686 | B43: TK | C43: 20FEB-07MAR | D43: DLA-CDG-DLA | E43: 00084/01/2025 | F43: MR TCHOUMBA | G43: TCHOUMBA EPSE NGANTCHUI BERLINE | H43: MME HEUNA | I43: 122300 | J43: 526800 | K43: 491451 | L43: =J43-K43 | M43: GOLITE | N43: ETKT 2355827796909 | O43: 4 | R43: 526800 | S43: =J43-P43-R43 | T43: 45687 | U43: CAISSE
A44: 45679 | B44: HF | C44: 27JAN. | D44: DLA-DSS | E44: 00047/01/2025 | F44: MR AZEMKOUO | G44: AZEMKOUO MARTIN | H44: DG | J44: 484920 | K44: 409452 | L44: =J44-K44 | M44: GOLITE | N44: ETKT 4835827796889 | O44: 2 | R44: 484920 | S44: =J44-Q44-P44-R44 | T44: 45681 | U44: BANQUE | V44: CHQ
A45: 45679 | B45: KP | C45: 04FEB. | D45: DSS-DLA | E45: 00047/01/2025 | F45: MR AZEMKOUO | G45: AZEMKOUO MARTIN | H45: DG | J45: 439920 | K45: 320648 | L45: =J45-K45 | M45: GOLITE | N45: ETKT 4835827796890 | O45: 2 | R45: 439920 | S45: =J45-Q45-P45-R45 | T45: 45681 | U45: BANQUE | V45: CHQ
A46: 45663 | B46: AT | C46: 04FEB. | D46: NSI-LHR | E46: 00007/01/2025 | F46: MR BELINGA | G46: BELINGA EBAH ARIANE EMERAUDE DAPHNEE | H46: DG | J46: 72600 | K46: 38218 | L46: =J46-K46 | M46: GOLITE | N46: ETKT 1475827796848 | O46: EXCHANGE | R46: 72568 | S46: =J46-P46-R46 | T46: 45663 | U46: OM
A47: 45672 | B47: QC | C47: 26JAN-31JAN | D47: NSI-NDJ-NSI | E47: 00019/01/2025 | F47: SMC | G47: YEMELONG YEMETA CAROLE VIRGINIE | H47: DG | I47: 245 805 | J47: 498905 | K47: 483305 | L47: =J47-K47 | M47: KUI | N47: ETKT 040030007013 | R47: 498905 | S47: =J47-P47-R47 | T47: 45706 | V47: 45687
A48: 45685 | B48: QC | C48: 16FEV-23FEB | D48: NSI-NDJ-NSI | E48: 00019A/01/2025 | F48: MR HOT | G48: YEMELONG YEMETA CAROLE VIRGINIE | H48: DG | J48: 0 | K48: 0 | L48: =J48-K48 | M48: QC | N48: ETKT 040030007013 | O48: EXCHANGE | S48: =J48-P48-R48
A49: 42028 | B49: HF | C49: 29JAN-31JAN | D49: NSI-ABJ-NSI | E49: 00062/01/2025 | F49: MR IBOUMBOU | G49: IBOUMBOU RAOUL RODOLPHE | H49: MR ROMEO | I49: 138600 | J49: 498900 | K49: 479804 | L49: =J49-K49 | M49: GOLITE | N49: ETKT 4835827796895 | O49: 2 | R49: 498900 | S49: =J49-P49-R49 | T49: 45685 | U49: CAISSE
A50: 45672 | B50: KP | C50: 28JAN-30JAN | D50: DLA-LFW-DLA | E50: 01232/01/2025 | F50: MR KAGOU | G50: GAMGNE GUIADEM CATHERINE MARCELLE | H50: DG | I50: 155400 | J50: 89500 | K50: 33800 | L50: =J50-K50 | M50: GOLITE | N50: ETKT 0325827796869 | O50: EXCHANGE | R50: 89500 | S50: =J50-P50-R50 | T50: 45792 | U50: CAISSE | V50: 45687
A51: 45672 | B51: KP | C51: 28JAN-30JAN | D51: DLA-LFW-DLA | E51: 1232/01/2025 | F51: MR KAGOU | G51: ELANGA SOPPI EPSE EBOA GISELE | H51: DG | I51: 139700 | J51: 89500 | K51: 33800 | L51: =J51-K51 | M51: GOLITE | N51: ETKT 0325827796868 | O51: EXCHANGE | R51: 89500 | S51: =J51-P51-R51 | T51: 45792 | U51: CAISSE | V51: 45687
A52: 45665 | B52: TK | C52: 13JAN. | D52: DLA-BRE | E52: 00011/01/2025 | F52: MR KOAGNE | G52: KOAGNE TCHOUABEH ANGE VANELLE | H52: MME HEUNA | I52: 549300 | J52: 805000 | K52: 768720 | L52: =J52-K52 | M52: GOLITE | N52: ETKT 2355827796851 | O52: 2 | R52: 805000 | S52: =J52-P52-R52 | T52: 45670 | U52: CAISSE
A53: 45673 | B53: AH | C53: 03FEB-20FEB | D53: DLA-CDG-DLA | E53: 00027/01/2025 | F53: MR KONDA | G53: KONDA BOUJEKA PATRICK STEVE | H53: MR STEPHANE | I53: 109200 | J53: 470000 | K53: 399520 | L53: =J53-K53 | M53: GOLITE | N53: ETKT 1245827796870 | O53: 4 | R53: 470000 | S53: =J53-P53-R53 | T53: 45671 | U53: CAISSE | V53: SOLDE
A54: 45659 | B54: AF | C54: 05JAN-02SEP | D54: DLA-CDG-DLA | E54: 00001/01/2025 | F54: MR LENTEU | G54: LENTEU GIULIA ASHLEY | H54: DG | I54: 685500 | J54: 1177620 | K54: 987420 | L54: =J54-K54 | M54: GOLITE | N54: ETKT 0575827796844 | O54: 2 | P54: 1177500 | S54: =J54-P54-R54 | T54: 45672 | U54: CAISSE | V54: 18JAN. | W54: 699998337
A55: 45675 | B55: AT | C55: 22JAN-27JAN | D55: TUN-NSI-TUN | E55: 00033/01/2025 | F55: MR MASMOUDI | G55: MASMOUDI TAIEB | H55: MR ROMEO | I55: 234500 | J55: 568900 | K55: 555773 | L55: =J55-K55 | M55: GOLITE | N55: ETKT 1475827796878 | O55: 4 | R55: 568900 | S55: 0 | T55: 45678 | U55: CAISSE
A56: 45668 | B56: WB | C56: 13JAN-20JAN | D56: DLA-BZV-DLA | E56: 00016/01/2025 | F56: MR MASSOMA PERSO BANGE BANK | G56: EDO DIMOUNGUE DAROUCHKA ORPHELIA | H56: DG | I56: 73500 | J56: 559900 | K56: 514737 | L56: =J56-K56 | M56: GOLITE | N56: ETKT 4595827796860 | O56: 2 | P56: 296500 | S56: =J56-P56-R56 | T56: 45673 | U56: CAISSE | V56: 45677
A57: 45668 | B57: WB | C57: 13JAN-13FEB | D57: DLA-BZV-DLA | E57: 00016/01/2025 | F57: MR MASSOMA PERSO BANGE BANK | G57: NZINGGOULA EPSE MASSOMA DENISE FERNANDE | H57: DG | I57: 73500 | J57: 585900 | K57: 514737 | L57: =J57-K57 | M57: GOLITE | N57: ETKT 4595827796861 | O57: 2 | S57: =J57-P57-R57 | V57: 45677
A58: 45681 | B58: ET | C58: 03FEB. | D58: NSI-CDG | E58: 00061/01/2025 | F58: MR NGOTTA | G58: NGOTTA MBANG FRANCIS ANDY | H58: DG | I58: 138900 | J58: 379950 | K58: 328753 | L58: =J58-K58 | M58: GOLITE | N58: ETKT 0715827796894 | O58: 2 | P58: 377000 | S58: =J58-P58-R58 | T58: 45681 | U58: OM
A59: 45659 | B59: AF | C59: 04JAN-28FEB | D59: DLA-CDG-DLA | E59: 00003/01/2025 | F59: MR ONANA | G59: TIANI VESSAH OLIVIA BIBIANA TCHANGAIN | H59: DG | J59: 3588900 | K59: 2832373 | L59: =J59-K59 | M59: BLUEBERRY | N59: ETKT 0572306439023 | O59: 0 | R59: 3588900 | S59: =J59-P59-R59 | T59: 45727 | U59: CAISSE | V59: 18JAN. | W59: +237 6 93 00 52 59
A60: 45681 | B60: QC | C60: 25JAN. | D60: DLA-NSI | E60: 00054/01/2025 | F60: MR ONANA | G60: NNANGA BEKONO | H60: DG | J60: 29900 | K60: 22400 | L60: =J60-K60 | M60: QC | N60: ETKT 0400200505780 | O60: EXCHANGE | R60: 29900 | S60: =J60-P60-R60 | T60: 45730 | U60: CAISSE
A61: 45659 | B61: AF | C61: 08JAN. | D61: IAD-DLA | E61: 00002/01/2025 | F61: MR OUSMAN | G61: OUSMAN BABILA KEVIN | H61: MME GLADYS | I61: 276000 | J61: 588600 | K61: 538600 | L61: =J61-K61 | M61: GOLITE | N61: ETKT 0575827796845 | O61: 2 | P61: 505000 | R61: 83600 | S61: =J61-P61-R61 | U61: CAISSE | W61: +237 52071351
A62: 45687 | B62: WB | C62: 03FEB-12FEB | D62: DLA-BZV-DLA | E62: 00087/01/2025 | F62: MR SOLLE | G62: SOLLE GEREMIE | H62: MM HEUNA | I62: 0 | J62: 0 | K62: 0 | L62: 0 | M62: GOLITE | N62: ETKT 4595827796910 | O62: 2 | R62: 0 | S62: =J62-P62-R62
A63: 45682 | B63: SN | C63: 01FEB-01JUL | D63: CDG-DLA-CDG | E63: 00067/01/2025 | F63: MR TCHATUE | G63: SONE EKOLO XAVIER YANNICK | H63: DG | J63: 497920 | K63: 447120 | L63: =J63-K63 | M63: NDC | N63: ETKT 0829049042123 | P63: 350000 | Q63: 500000 | R63: 548000 | S63: 0 | T63: 16/01/2025 28/01/2025 28/02/2025 | U63: CAISSE
A64: 45682 | B64: SN | C64: 01FEB-01JUL | D64: CDG-DLA-CDG | E64: 00067/01/2025 | F64: MR TCHATUE | G64: SONE EKOLO WELISANE XAVIER | H64: DG | J64: 449820 | K64: 399220 | L64: =J64-K64 | M64: NDC | N64: ETKT 0829049042124
A65: 45682 | B65: SN | C65: 01FEB-01JUL | D65: CDG-DLA-CDG | E65: 00067/01/2025 | F65: MR TCHATUE | G65: SONE EKOLO MALEA JULIENNE | H65: DG | J65: 449820 | K65: 399220 | L65: =J65-K65 | M65: NDC | N65: ETKT 0829049042125
A66: 45663 | B66: ET | C66: 10JAN. | D66: NSI-MGQ | E66: 00006/01/2025 | F66: MR TEGUIMDJE | G66: TEGUIMDJE MBONDI EPSE KENNE CHRIS | H66: DG | J66: 115400 | K66: 95400 | L66: =J66-K66 | M66: ET | N66: ETKT 0712149956593 | O66: EXCHANGE | R66: 115400 | S66: =J66-P66-R66
A67: 45672 | B67: AF | C67: 06FEB-26FEB | D67: DLA-PARDLA | E67: 00021/01/2025 | F67: MR TEUFACK | G67: TEUFACK PASCAL | H67: DG | I67: 387200 | J67: 850950 | K67: 696120 | L67: =J67-K67 | M67: GOLITE | N67: ETKT 0575827796865 | O67: 2 | P67: 500000 | R67: 350950 | S67: =J67-P67-R67 | T67: 17/01/2025 30/01/2025 | U67: BANQUE
A68: 45674 | B68: ET | C68: 08FEB-14FEB | D68: DLA-DXB-DLA | E68: 00030/01/2025 | F68: MRS AFIAVI | G68: DALMEIDA EPSE MINYEBELE AFIAVI | H68: DG | I68: 157800 | J68: 498920 | K68: 442786 | L68: =J68-K68 | M68: GOLITE | N68: ETKT 0715827796876 | R68: 498920 | S68: =J68-P68-R68 | T68: 45674 | U68: CAISSE
A69: 45677 | B69: HF | C69: 23JAN-26JAN | D69: DLA-DSS-DLA | E69: 00041/01/2025 | F69: MRS AMBASSA | G69: AMBASSA NNOMO ADELAIDE | H69: MME HEUNA | J69: 452000 | K69: 421120 | L69: =J69-K69 | M69: AMADEUS | N69: ETKT 4833578235372 | R69: 452000 | S69: =J69-P69-R69 | T69: 45678 | U69: CAISSE
A70: 45679 | B70: SN | C70: 14FEB-17FEB | D70: DLA-CDG-DLA | F70: MRS ANGELE | G70: ANGELE BERLINE NDONGMO NGANA EPSE KANA | H70: DG | J70: -4803 | K70: 4803 | L70: -4803 | M70: NDC | N70: ETKT 0829049042117 | P70: -4803 | S70: =J70-P70-R70
A71: 45675 | B71: ET | C71: 25FEB-12MAR | D71: DLA-DEL-DLA | E71: 00035/01/2025 | F71: MRS AZEMO | G71: DONFACK EPSE AZEMO CHANTALE | H71: DG | J71: 98500 | K71: 71200 | L71: =J71-K71 | M71: GOLITE | N71: ETKT 0715827796880 | O71: EXCHANGE | P71: 0 | R71: 98500 | S71: =J71-P71-R71 | T71: 45677 | U71: OM
A72: 45677 | B72: HF | C72: 23JAN-26JAN | D72: DLA-DSS-DLA | E72: 00043/01/2025 | F72: MRS BEBE | G72: BEBE ERNESTINE | H72: MME HEUNA | J72: 452000 | K72: 421120 | L72: =J72-K72 | M72: AMADEUS | N72: ETKT 4833578235373 | R72: 452000 | S72: =J72-P72-R72 | T72: 45678 | U72: CAISSE
A73: 45675 | B73: SN | C73: 19JAN. | D73: CDG-DLA | E73: 00034/01/2025 | F73: MRS ELANGA | G73: ELANGA SOPPI EPSE EBOA GISELE | H73: DG | J73: 92300 | K73: 78800 | L73: =J73-K73 | M73: NDC | N73: ETKT 0821806317723 | O73: EMD | R73: 92300 | S73: =J73-P73-R73 | T73: 45688 | U73: CAISSE
A74: 45676 | B74: ET | C74: 05APR-13APR | D74: DLA-DXB-DLA | E74: 00036/01/2025 | F74: MRS ELANGA | G74: ELANGA SOPPI EPSE EBOA GISELE | H74: DG | I74: 157800 | J74: 497500 | K74: 443686 | L74: =J74-K74 | M74: GOLITE | N74: ETKT 0715827796886 | O74: 4 | R74: 497500 | S74: =J74-P74-R74 | T74: 45688 | U74: CAISSE
A75: 45676 | B75: ET | C75: 05APR-13APR | D75: DLA-DXB-DLA | E75: 00036/01/2025 | F75: MRS ELANGA | G75: BOLANGA MOUDO JACQUELINE | H75: DG | I75: 157800 | J75: 497500 | K75: 443686 | L75: =J75-K75 | M75: GOLITE | N75: ETKT 0715827796885 | O75: 4 | R75: 497500 | S75: =J75-P75-R75 | T75: 45688 | U75: CAISSE
A76: 45676 | B76: ET | C76: 05APR-13APR | D76: DLA-DXB-DLA | E76: 00036/01/2025 | F76: MRS ELANGA | G76: EBOA ELANGA YANN ARTHUR | H76: DG | I76: 118400 | J76: 468520 | K76: 405495 | L76: =J76-K76 | M76: GOLITE | N76: ETKT 0715827796883 | O76: 4 | R76: 468520 | S76: =J76-P76-R76 | T76: 45688 | U76: CAISSE
A77: 45676 | B77: ET | C77: 05APR-13APR | D77: DLA-DXB-DLA | E77: 00036/01/2025 | F77: MRS ELANGA | G77: EBOA MATHEO WILFRIED | H77: DG | I77: 118400 | J77: 468520 | K77: 405495 | L77: =J77-K77 | M77: GOLITE | N77: ETKT 0715827796884 | O77: 4 | R77: 468520 | S77: =J77-P77-R77 | T77: 45688 | U77: CAISSE
A78: 45681 | E78: 00059/01/2025 | F78: MRS ELANGA | G78: ELANGA SOPPI EPSE EBOA GISELE | H78: DG | J78: 60000 | K78: 46000 | L78: =J78-K78 | O78: VISA | R78: 60000 | S78: =J78-P78-R78 | T78: 45688 | U78: CAISSE
A79: 45678 | B79: QC | C79: 27JAN-27JAN | D79: DLA-NSI-DLA | E79: 00046/01/2025 | F79: MRS ELANGA | G79: ELANGA SOPPI EPSE EBOA GISELE | H79: DG | J79: 109950 | K79: 86540 | L79: =J79-K79 | M79: KIU | N79: ETKT 0400300037016 | R79: 109950 | S79: =J79-P79-R79 | T79: 45688 | U79: CAISSE
A80: 45673 | B80: J7 | C80: 31JAN-05FEB | D80: DLA-LBV-DLA | E80: 00026/01/2025 | F80: MRS EUPHRASIE | G80: NZEUTCHO DJIEDOM EPSE NKOUMNGOCK EUPHASIE | H80: DG | J80: 265950 | K80: 239200 | L80: =J80-K80 | M80: J7 | N80: ETKT 27722585553 | P80: 0 | R80: 266440 | S80: =J80-P80-R80 | T80: 45673 | U80: OM | V80: SOLDE
A81: 45679 | B81: SN | C81: 08FEB-21FEB | D81: CDG-DLA-CDG | E81: 00049/01/2025 | F81: MRS EYOUM | G81: EYOUM CAMELIA MYLANE | H81: DG | J81: 839950 | K81: 719950 | L81: =J81-K81 | M81: NDC | N81: ETKT 0829049042120 | P81: 280000 | Q81: 503200 | R81: 56750 | S81: =J81-P81-Q81-R81 | T81: 31/01/2025 12/02/2025 | U81: CAISSE | V81: SOLDE | W81: 280000 | X81: 503200 | Y81: 56712
A82: 45667 | B82: ET | C82: 12JAN-20JAN | D82: DLA-DXB-DLA | E82: 00015/01/2025 | F82: MRS FRANCA | G82: FRANCA SOSSO DIKOUME EMILIE AURORE | H82: DG | J82: -26568 | K82: 476168 | L82: -26568 | M82: GOLITE | N82: ETKT 0715827796856 | O82: PERTE | S82: =J82-P82-R82 | V82: VISA N EST ¨PAS SRTI
A83: 45670 | B83: ET | C83: 14JAN-20JAN | D83: DLA-DXB-DLA | E83: 00017/01/2025 | F83: MRS FRANCA | G83: BINTOU POUENGUE SOUMAI | H83: DG | I83: 338800 | J83: 688920 | K83: 617956 | L83: =J83-K83 | M83: GOLITE | N83: ETKT 0715827796862 | O83: 4 | R83: 688920 | S83: =J83-P83-R83 | T83: 45670 | U83: CAISSE | V83: SOLDE
A84: 45675 | B84: ET | C84: 20JAN. | D84: DXB-DLA | E84: 00032/01/2025 | F84: MRS FRANCA | G84: BINTOU POUENGUE SOUMAI | H84: DG | J84: 149950 | K84: 110627 | L84: =J84-K84 | M84: GOLITE | N84: ETKT 0715827796881 | O84: EXCHANGE | P84: - | R84: 149950 | S84: =J84-R84 | T84: 45667 | U84: OM
A85: 45676 | B85: ET | C85: 20JAN. | D85: DXB-DLA | E85: 00038/01/2025 | F85: MRS FRANCA | G85: BINTOU POUENGUE SOUMAI | H85: DG | J85: 159950 | K85: 95700 | L85: =J85-K85 | M85: GOLITE | N85: ETKT 0715827796882 | O85: EXCHANGE | P85: - | R85: 159950 | S85: =J85-R85 | T85: 45667 | U85: OM
A86: 45684 | B86: HF | C86: 16FEB. | D86: ABJ-DLA | E86: 00072/01/2025 | F86: MRS JIOTSA | G86: FOLEFACK BRUNO | H86: DG | I86: 83000 | J86: 259600 | K86: 230620 | L86: =J86-K86 | M86: GOLITE | N86: ETKT 4835827796899 | O86: 1 | R86: 259600 | S86: =J86-P86-R86 | T86: 45688 | U86: CAISSE
A87: 45677 | B87: HF | C87: 23JAN-02FEB | D87: DLA-DSS-DLA | E87: 00042/01/2025 | F87: MRS MAMBOU | G87: MAMBOU ELISE | H87: MME HEUNA | J87: 452000 | K87: 421120 | L87: =J87-K87 | M87: AMADEUS | N87: ETKT 4833578235371 | R87: 452000 | S87: =J87-P87-R87 | T87: 45678 | U87: CAISSE
A88: 45680 | B88: SN | C88: 13FEB-17FEB | D88: DLA-BRU-DLA | E88: 00056/01/2025 | F88: MRS NDONGMO | G88: NDONGMO NGANA EPSE NGANA ANGELE BERLINE | H88: DG | J88: 934800 | K88: 899800 | L88: =J88-K88 | M88: NDC | N88: ETKT 0829049042121 | P88: 154800 | R88: 780000 | S88: =J88-P88-R88 | T88: 23/01/2025 24/01/2025 | U88: CAISSE
A89: 45679 | B89: SN | C89: 19APR-27APR-19MAY | D89: NSI-CDG-YUL-NSI | E89: 00050/01/2025 | F89: MRS NKONGO | G89: NKONGO NTOUBA SAMUEL | H89: MME HEUNA | J89: 869120 | K89: 819120 | L89: =J89-K89 | M89: AMADEUS | N89: ETKT 0823578236725-26 | R89: 869100 | S89: =J89-P89-R89 | T89: 45679 | U89: CAISSE
A90: 45672 | B90: AF | C90: 26JAN-08FEB | D90: DLA-YUL-DLA | E90: 00029/01/2025 | F90: MRS STEPHANIE | G90: DIAYO MASSAH STEPHANIE LAURE | H90: DG | I90: 616500 | J90: 1129000 | K90: 1084720 | L90: =J90-K90 | M90: AMADEUS | N90: ETKT 0573578233305 | P90: 1000000 | R90: 129000 | S90: =J90-P90-R90 | T90: 45687 | U90: CAISSE
A91: 45675 | B91: AT | C91: 23JAN-05FEB | D91: DLA-DXB-DLA | E91: 00028/01/2025 | F91: MRS SUZANNE | G91: WENDJA SUZANNE | H91: DG | I91: 257700 | J91: 650620 | K91: 597689 | L91: =J91-K91 | M91: GOLITE | N91: ETKT 1475827796879 | O91: 4 | P91: 246000 | Q91: 400000 | R91: 4620 | S91: =J91-Q91-P91-R91 | T91: 20/01/2025 24/01/2025 | U91: OM CAISSE
A92: 45688 | B92: AT | C92: 11FEB. | D92: CDG-DLA | E92: 00090/01/2025 | F92: MRS SUZANNE | G92: WENDJA SUZANNE | H92: DG | J92: 100950 | K92: 70400 | L92: =J92-K92 | M92: GOLITE | N92: ETKT 1475827796915 | O92: EXCHANGE | R92: 100950 | S92: 0 | T92: 45688 | U92: CAISSE
A93: 45678 | B93: TK | C93: 25FEB-06MAR | D93: CDG-DLA-CDG | E93: 00045/01/2025 | F93: MRS TCHETGNA | G93: TCHETGNA MICHELINE | H93: MME HEUNA | J93: 483600 | K93: 443620 | L93: =J93-K93 | M93: GOLITE | N93: ETKT 2355827796888 | O93: 4 | P93: 0 | R93: 483600 | S93: =J93-P93-R93 | T93: 45678 | U93: CAISSE
A94: 45672 | B94: ET | C94: 19JAN-30JAN | D94: DLA-BLR-DLA | E94: 00022/01/2025 | F94: MRS TEIFOUET | G94: TEIFOUET HELENE | H94: DG | I94: 411900 | J94: 781820 | K94: 749863 | L94: =J94-K94 | M94: GOLITE | N94: ETKT 0715827796864 | O94: 4 | R94: 781820 | S94: =J94-P94-R94 | T94: 45672 | U94: CAISSE | V94: SOLDE | X94: 45397
A95: 45685 | B95: HF | C95: 02FEB-09FEB | D95: DLA-ABJ-DLA | E95: 00077/01/2025 | F95: NEO INDUSTRIE | G95: KEMMOE TAKAMGANG /JOSEPH MR | H95: DG | I95: 140600 | J95: 539820 | K95: 481684 | L95: =J95-K95 | M95: GOLITE | N95: ETKT 4835827796905 | O95: 2 | R95: 539820 | S95: =J95-P95-R95 | T95: 45692 | U95: BANQUE | V95: chq 6277125
A96: 45685 | B96: HF | C96: 02FEB-09FEB | D96: DLA-ABJ-DLA | E96: 00078/01/2025 | F96: NEO INDUSTRIE | G96: BEUTKA NGNOUNEWOU/SERGES BERTRAND MR | H96: DG | I96: 140600 | J96: 539820 | K96: 481684 | L96: =J96-K96 | M96: GOLITE | N96: ETKT 4835827796906 | O96: 2 | R96: 539820 | S96: =J96-P96-R96 | T96: 45692 | U96: BANQUE | V96: chq 6277125
A97: 45685 | B97: HF | C97: 02FEB-09FEB | D97: DLA-ABJ-DLA | E97: 00079/01/2025 | F97: NEO INDUSTRIE | G97: NGAHANG FONGANG/JAURES LEOVANNI MR | H97: DG | I97: 140600 | J97: 539820 | K97: 481684 | L97: =J97-K97 | M97: GOLITE | N97: ETKT 4835827796907 | O97: 2 | R97: 539820 | S97: =J97-P97-R97 | T97: 45692 | U97: BANQUE | V97: chq 6277125
A98: 45677 | B98: AF | C98: 17APR-27APR | D98: FLW-CDG-LFW | E98: 00039/01/2025 | F98: RAF 24 | G98: YHAYE JENNIFER OULOASSIA | H98: DG | I98: 321800 | J98: 623900 | K98: 573900 | L98: =J98-K98 | M98: GOLITE | N98: ETKT 0575827796887 | O98: 2 | R98: 623900 | S98: =J98-P98-R98 | T98: 45716 | U98: CAISSE
A99: 45673 | B99: HF | C99: 27JAN-01FEB | D99: DLA-DSS-DLA | E99: 00024/01/2025 | F99: RWKING | G99: KEM NOUMEDEM EPOUSE AZEMKOUO FRANCOISE | H99: DG | I99: 306500 | J99: 698620 | K99: 678220 | L99: =J99-K99 | M99: GOLITE | N99: ETKT 4835827796874 | O99: 4 | R99: 698620 | S99: =J99-P99-R99 | T99: 45684 | U99: CAISSE
A100: 45673 | B100: HF | C100: 27JAN-01FEB | D100: DLA-DSS-DLA | E100: 00024/01/2025 | F100: RWKING | G100: MAGOUDJOU EPOUSE AZEMKOUO SUZANNE | H100: DG | I100: 306500 | J100: 698620 | K100: 659830 | L100: =J100-K100 | M100: GOLITE | N100: ETKT 4835827796873 | O100: 4 | P100: 600000 | R100: 98620 | S100: =J100-P100-R100 | T100: 17/01/2025 21/01/2025 | U100: CAISSE | V100: 45687
...

Sheet FEVRIER
A1: DATE | B1: CIES | C1: TRAJET | D1: PARCOURS | E1: N FACTURE | F1: ENTREPRISE | G1: NOMS/PRENOMS | H1: APPORTEUR | I1: TARIF HT | J1: TC | K1: TM | L1: FS | M1: LIEU ACHAT | N1: NUMERO DU BILLET | O1: NBRE SGTS | P1: AVANCE 01 | Q1: AVANCE 02 | R1: AVANCE 03 | S1: RGLT | T1: SOLDE | U1: DATE RGLT | V1: MODE RGLT | W1: OBS
A2: 45689 | B2: J7 | C2: 04FEB-06FEB | D2: DLA-SSG-DLA | E2: 00096/02/2025 | F2: BANGE BANK | G2: OBIANG NCHAMA JOSE MIGUEL | H2: DG | I2: 217 094 | J2: 120800 | L2: 120 800 | M2: J7 | N2: ETKT 27722785148 | S2: 120800 | T2: =J2-P2-S2 | U2: 45695 | V2: V/R
A3: 45689 | B3: J7 | C3: 06FEB. | D3: SSG-DLA | E3: 00097/02/2025 | F3: BANGE BANK | G3: EKOLO TSITSI CLEMENT JANVIER | H3: DG | I3: 108 284 | J3: 75800 | L3: 75 800 | M3: J7 | N3: ETKT 27722785114 | S3: 75800 | T3: =J3-P3-S3 | U3: 45695 | V3: V/R
A4: 45689 | B4: C8 | C4: 02FEB. | D4: DLA-SSG | E4: 00102/2/2025 | F4: BANGE BANK | G4: EKOLO TSITSI CLEMENT JANVIER | H4: DG | I4: 104 970 | J4: 80000 | K4: - | L4: 80 000 | M4: C8 | N4: ETKT 49850000313098 | S4: 80000 | T4: =J4-P4-S4 | U4: 45695 | V4: V/R
A5: 45689 | B5: KP | C5: 02FEB-04FEB | D5: NSI-SSG-NSI | E5: 00095/02/2025 | F5: BANGE BANK | G5: MVONDO ASSAM BONAVENTURE | H5: DG | I5: 770900 | J5: 180000 | K5: 0 | L5: 180 000 | M5: GOLITE | N5: ETKT 0325827796917 | S5: 180000 | T5: =J5-P5-S5 | U5: 45695 | V5: V/R
A6: 45689 | B6: HF | C6: 02FEB. | D6: ABJ-DLA | E6: 00098/02/2025 | F6: RWKING | G6: KEM NOUMEDEM EPOUSE AZEMKOUO FRANCOISE | H6: DG | J6: 99900 | K6: 71 000 | L6: 28 900 | M6: GOLITE | N6: ETKT 4835827796920 | O6: EXCHANGE | S6: 100000 | T6: =J6-P6-S6 | U6: 026/02/2025 | V6: CAISSE
A7: 45689 | B7: AT | C7: 20FEB-23FEB | D7: DLA-RAK-DLA | E7: 00100/02/2025 | F7: ATLANTIQUE | G7: FOTADZONG TCHIO THEOPHILE | H7: DG | J7: 198000 | K7: -1000 | L7: 199 000 | M7: NDC | N7: ETKT 1475827796918 | O7: EXCHANGE | S7: 198000 | T7: =J7-P7-S7 | U7: 45744 | V7: BANQUE | W7: CHQ 2342450
A8: 45689 | B8: HF | C8: 02FEB. | D8: ABJ-DLA | E8: 00098/02/2025 | F8: RWKING | G8: MAGOUDJOU EPOUSE AZEMKOUO SUZANNE | H8: DG | J8: 99900 | K8: 71000 | L8: =J8-K8 | M8: GOLITE | N8: ETKT 4835827796919 | O8: EXCHANGE | S8: 100000 | T8: =J8-P8-S8 | U8: 45714 | V8: CAISSE
A9: 45690 | B9: AF | C9: 02FEB. | D9: DLA-CDG | E9: 00101/02/2025 | F9: MR ONANA | G9: TIANI VESSAH OLIVIA BIBIANA TCHANGAIN | H9: DG | J9: -293000 | L9: =J9-K9 | M9: AF | N9: ETKT 0572324013110 | O9: EXCHANGE | T9: =J9-P9-S9 | W9: -100000 | X9: PAR BLUEBERRY
A10: 45690 | B10: AF | C10: 02FEB. | D10: DLA-CDG | E10: 00099/02/2025 | F10: MR ONANA | G10: TIANI VESSAH OLIVIA BIBIANA TCHANGAIN | H10: DG | L10: - | M10: BLUEBERRY | N10: ETKT 0572306439161 | O10: EXCHANGE | T10: =J10-P10-S10
A11: 45691 | B11: AF | C11: 03FEB-13FEB | D11: DLA-CDG-DLA | E11: 000104/02/2025 | F11: HORUS | G11: ONANA CYRILLE BERTRAND | H11: DG | J11: 250000 | K11: 210 000 | L11: 40 000 | O11: CONSIEGERIE | S11: 250000 | T11: =J11-P11-S11 | U11: 45762 | V11: BANQUE | W11: CHQ 2988599
A12: 45691 | B12: QC | C12: 04FEB-11FEB | D12: DLA-BZV-DLA | E12: 00103/02/2025 | F12: MR SOLLE | G12: SOLLE GEREMIE | H12: MME HEUNA | J12: 565800 | K12: 420 314 | L12: 145 486 | M12: KIU | N12: ETKT 0400300037023 | S12: 565800 | T12: =J12-P12-S12 | U12: 030/01/2025 | V12: CAISSE
A13: 45691 | B13: J7 | C13: 04FEB-11FEB | D13: DLA-SSG-DLA | E13: 00105/02/2025 | F13: BANGE BANK | G13: ESONO OYANA ANGELICA MONAYONG | H13: DG | I13: 217 094 | J13: 429950 | K13: 386 600 | L13: 43 350 | M13: J7 | N13: ETKT 277228074439 | S13: 427252 | T13: =J13-P13-S13 | U13: 45695 | V13: V/R
A14: 45691 | B14: QC | C14: 11FEB-15FEB | D14: DLA-LBV-DLA | E14: 00111/002/2025 | F14: ISTAMA | G14: KUTCHE TAMGHE CHEVALIER DE DIEU | H14: DG | I14: 225455 | J14: 346950 | K14: 288 155 | L14: 58 795 | M14: KIU | N14: ETKT 0400300037024 | S14: 346950 | T14: =J14-P14-S14 | U14: 45660 | V14: V/R
A15: 45691 | B15: QC | C15: 11FEB-14FEB | D15: DLA-LBV-DLA | E15: 00111/02/2025 | F15: ISTAMA | G15: NJANTA EBENEZER | H15: DG | I15: 220 845 | J15: 299900 | K15: 275 955 | L15: 23 945 | M15: KIU | N15: ETKT 0400300037022 | S15: 299900 | T15: =J15-P15-S15 | U15: 45660 | V15: V/R
A16: 45692 | B16: J7 | C16: 04FEB-06FEB | D16: DLA-SSG-DLA | E16: 0108/02/2024 | F16: BANGE BANK | G16: OBIANG NCHAMA JOSE MIGUEL | H16: DG | I16: 217094 | J16: 586600 | K16: 386600 | L16: 200000 | M16: J7 | N16: ETKT 27722785148 | S16: 583002 | T16: =J16-P16-S16
A17: 45692 | C17: 08FEB-09FEB | D17: BEAUVILLE | E17: 00109/02/2025 | F17: ATLANTIQUE | G17: FOTADZONG TCHIO THEOPHILE | H17: DG | J17: 354540 | K17: 282500 | L17: 72040 | M17: FR | N17: REF 4890315659 | O17: CONSIEGERIE | S17: 354540 | T17: =J17-P17-S17 | U17: 45744 | V17: BANQUE | W17: CHQ 2342450
A18: 45692 | B18: QC | C18: 11FEB-15FEB | D18: DLA-LBV-DLA | E18: 00111/02/2025 | F18: ISTAMA | G18: YOUAGANG GOUGUEU HARRIS STEPHANE | H18: DG | I18: 225455 | J18: 346950 | K18: 306 055 | L18: 40 895 | M18: KIU | N18: ETKT 0400200515158 | S18: 346950 | T18: =J18-P18-S18 | U18: 45660 | V18: V/R
A19: 45692 | B19: J7 | C19: 04FEB-06FEB | D19: DLA-SSG-DLA | E19: 00106/20/2025 | F19: BANGE BANK | G19: OBIANG NCHAMA JOSE MIGUEL | H19: DG | I19: 217 094 | J19: 153600 | K19: - | L19: 153 600 | M19: J7 | N19: ETKT 27722785148 | S19: 153600 | T19: =J19-P19-S19 | U19: 45695 | V19: V/R
A20: 45692 | B20: KP | C20: 05FEB-08FEB | D20: NSI-SSG-NSI | E20: 0107/02/2025 | F20: BANGE BANK | G20: MVONDO ASSAM BONAVENTURE | H20: DG | I20: 957 600 | J20: 1457955 | K20: 1 299 799 | L20: 158 156 | M20: GOLITE | N20: ETKT 0325827796921 | O20: 2 | S20: 2747264 | T20: =J20+J21+J22-P20-S20
A21: 45692 | B21: KP | C21: 05FEB-08FEB | D21: NSI-SSG-NSI | E21: 00107/02/2025 | F21: BANGE BANK | G21: EKOLO TSITSI CLEMENT JANVIER | H21: DG | I21: 298 000 | J21: 650955 | K21: 552 775 | L21: 98 180 | M21: GOLITE | N21: ETKT 0325827796923 | O21: 2
A22: 45692 | B22: KP | C22: 05FEB-08FEB | D22: NSI-SSG-NSI | E22: 00107/02/2025 | F22: BANGE BANK | G22: OBIANG NCHAMA JOSE MIGUEL | H22: DG | I22: 298 000 | J22: 650955 | K22: 552 775 | L22: 98 180 | M22: GOLITE | N22: ETKT 0325827796922 | O22: 2
A23: 45693 | B23: C8 | C23: 09FEB-12FEB | D23: DLA-SSG-DA | E23: 00112/02/2025 | F23: DAF BANGE BANK | G23: NVE MODJO JUSTINO NGUERE | H23: DG | I23: 138 870 | J23: 298800 | K23: 238000 | L23: 60800 | M23: C8 | N23: ETKT 49850000314163 | S23: 298800 | T23: =J23-P23-S23 | U23: 010/03/2025 | V23: OM
A24: 45693 | B24: C8 | C24: 09FEB-12FEB | D24: DLA-SSG-DLA | E24: 00112/02/2025 | F24: DAF BANGE BANK | G24: NGUE ANNE GUILAINE | H24: DG | I24: 138 870 | J24: 298800 | K24: 238000 | L24: 60800 | M24: C8 | N24: ETKT 49850000314164 | S24: 298800 | T24: =J24-P24-S24
A25: 45693 | B25: AT | C25: 19FEB-23FEB-26FEB | D25: DLA-DXB-RAK.CMN-LFW | E25: 00113/02/2025 | F25: SAAR | G25: KAGOU GEORGES LEOPOLD | H25: DG | I25: 1 384 600 | J25: 2109000 | K25: 1783482 | L25: 325518 | M25: GOLITE | N25: ETKT 1475827796925-926 | O25: 5 | S25: 2109000 | T25: =J25-P25-S25 | U25: 45714 | V25: BANQUE | W25: CHQ 8230438
A26: 45693 | B26: AT | C26: 20FEB-27FEB | D26: DLA-RAK-DLA | E26: 00114/02/2025 | F26: ATLANTIQUE | G26: FOTADZONG TCHIO THEOPHILE | H26: DG | J26: 198000 | K26: 800 | L26: 197200 | M26: NDC | N26: ETKT 1475827796924 | O26: EXCHANGE | T26: =J26-P26-S26
A27: 45694 | B27: TK | C27: 23FEB-27FEB | D27: DLA-RAK-DLA | E27: 00110/02/2025 | F27: ASPROM | G27: AWATIO TCHINDA ALECE FRACIOLI | H27: DG | I27: 441400 | M27: GOLITE | N27: ETKT 235582779697 | T27: =J27-P27-S27 | W27: CHEQUE
A28: 45694 | B28: J7 | C28: 07FEB- | D28: SSG-DLA | E28: 00117/02/2025 | F28: BANGE BANK | G28: MVONDO ASSAM BONAVENTURE | H28: DG | I28: 108 284 | J28: 295900 | K28: 199600 | L28: 96300 | M28: J7 | N28: ETKT 27722846733 | S28: 295900 | T28: =J28-P28-S28 | U28: 45862 | V28: V/R
A29: 45694 | B29: C8 | C29: 07FEB-16FEB | D29: DLA-SSG-DLA | E29: 00115/02/2025 | F29: BANGE BANK | G29: MARAMA MANUACHE MARIO LORENZO | H29: DG | I29: 220 770 | J29: 318900 | K29: 258000 | L29: 60900 | M29: C8 | N29: ETKT 49850000314552 | S29: 316202 | T29: =J29-P29-S29 | U29: 45742 | V29: V/R
A30: 45694 | B30: SN | C30: 05MAR-11MAR | D30: DLA-CDG-DLA | E30: 00116/02/2025 | F30: MR DJOUAKA | G30: KIFACK BOUKENG EPSE DJOUAKA FLORENCE | H30: DG | I30: 782 100 | J30: 1300800 | K30: 1108020 | L30: 192780 | M30: NDC | N30: ETKT 0829049042127 | S30: 1300800 | T30: =J30-P30-S30 | U30: 45694 | V30: V/R
A31: 45694 | B31: QC | C31: 07FEB- | D31: DLA-BFX | E31: 00118/02/2025 | F31: FOKOUA ROMEO | G31: FOKOUA KUMO ROMEO ARISTIDE | H31: DG | I31: 19 370 | J31: 86950 | K31: 55670 | L31: 31280 | M31: KIU | N31: ETKT 0400300037025 | T31: =J31-P31-S31
A32: 45694 | B32: ET | C32: 15FEB- | D32: DXB-DLA | E32: 00119/02/2025 | F32: MR WAFO | G32: WAFO MAURICE | H32: DG | J32: 112000 | K32: 73500 | L32: 38500 | M32: GOLITE | N32: ETKT 0715827796928 | O32: EXCHANGE | P32: 109750 | T32: =J32-P32-S32 | U32: 006/02/2025 | V32: OM | W32: SOLDE
A33: 45694 | B33: QC | C33: 07FEB- | D33: DLA-NSI | E33: 00120/02/2025 | F33: BANGE BANK | G33: MVONDO ASSAM BONAVENTURE | H33: DG | I33: 26 370 | J33: 114950 | K33: 99770 | L33: 15180 | M33: KIU | N33: ETKT 0400300037026 | S33: 114051 | T33: =J33-P33-S33 | U33: 45742 | V33: V/R
A34: 45695 | B34: ET | C34: 24FEB-02MAR | D34: DLA-DXB-DLA | E34: 00121/002/2025 | F34: MR KENMOGNE | G34: KENMOGNE ALAIN MODESTE | H34: DG | I34: 152 000 | J34: 489820 | K34: 439820 | L34: 50000 | M34: GOLITE | N34: ETKT 0715827796929 | O34: 4 | S34: 979650 | T34: 0 | U34: 007/02/2025 | V34: CAISSE
A35: 45695 | B35: ET | C35: 24FEB-02MAR | D35: DLA-DXB-DLA | E35: 00121/02/2025 | F35: MR KENMOGNE | G35: APALA ATONGO EPSE KENMOGNE GRACE | H35: DG | I35: 152 000 | J35: 489820 | K35: 439820 | L35: 50000 | M35: GOLITE | N35: ETKT 0715827796930 | O35: 4
A36: 45695 | B36: J7 | C36: 03MAR-06MAR | D36: DLA-LBV-DLA | E36: 00122/02/2025 | F36: HARVEST | G36: KAMGAING MARC ETIENNE | H36: DG | I36: 262 673 | J36: 648700 | K36: 578700 | L36: 70000 | M36: J7 | N36: ETKT 27722860831 | S36: 648700 | T36: =J36-P36-S36 | U36: 45722 | V36: V/R
A37: 45695 | B37: J7 | C37: 26FEB-28FEB | D37: DLA-LBV-DLA | E37: 00123/02/2025 | F37: HARVEST | G37: YE SENEH POWOH INNOCENT | H37: DG | I37: 48 978 | J37: 330900 | K37: 289500 | L37: 41400 | M37: J7 | N37: ETKT 27722860417 | S37: 330900 | T37: =J37-P37-S37 | U37: 45722 | V37: V/R
A38: 45695 | B38: J7 | C38: 26FEB-28FEB | D38: DLA-LBV-DLA | E38: 00124/02/2025 | F38: HARVEST | G38: BUNANG POUEME LIONEL FRANKY | H38: DG | I38: 48 978 | J38: 330900 | K38: 289500 | L38: 41400 | M38: J7 | N38: ETKT 27722860417 | S38: 330900 | T38: =J38-P38-S38 | U38: 45722 | V38: V/R
A39: 45695 | B39: KP | C39: 09FEB-11FEB | D39: SSG-COO-NSI | E39: 00125/02/2025 | F39: BANGE BANK | G39: OBIANG NCHAMA JOSE MIGUEL | H39: DG | I39: 270 000 | J39: 760900 | K39: 711400 | L39: 49500 | M39: GOLITE | N39: ETKT 0325827796931 | O39: 4 | S39: 758202 | T39: =J39-P39-S39 | U39: 45742 | V39: V/R
A40: 45695 | B40: SN | C40: 16MAR-15APR | D40: CDG-DLA-CDG | E40: 00127/02/2025 | F40: MR POKASSA ISTAMA | G40: CHOUAIBOU POKASSA | H40: DG | J40: 139900 | K40: 107900 | L40: 32000 | M40: NDC | N40: ETKT 0829049042128 | O40: EXCHANGE | S40: 140000 | T40: =J40-P40-S40 | U40: 45695 | V40: CAISSE
A41: 45696 | B41: HF | C41: 09FEB-10FEB | D41: DLA-ABJ-DLA | E41: 00129/02/2025 | F41: SAAR | G41: KAGOU GEORGES LEOPOLD | H41: DG | I41: 86 100 | J41: 694920 | K41: 435620 | L41: 259300 | M41: GOLITE | N41: ETKT 4835827796932 | O41: 2 | T41: =J41-P41-S41
A42: 45696 | B42: KP | C42: 27FEB-03MAR | D42: DLA-LFW-DLA | E42: 00130/02/2025 | F42: CABINET DENTAIRE G2 | G42: GAMGNE GUIADEM CATHERINE MARCELLE | H42: DG | I42: 103 700 | J42: 432800 | K42: 364120 | L42: 68680 | M42: GOLITE | N42: ETKT 0325827796934 | O42: 2 | P42: 366000 | S42: 66800 | T42: =J42-P42-S42 | U42: 45676 | V42: CAISSE
A43: 45696 | B43: ET | C43: 09FEB- | D43: KGL-DLA | E43: 00131/02/2025 | F43: MR TEFOUELE | G43: TEFOUELO NECDEM PERIAT NEIL | H43: MME HEUNA | I43: 192 200 | J43: 299900 | K43: 279200 | L43: 20700 | M43: GOLITE | N43: ETKT 0715827796935 | O43: 2 | P43: 299500 | T43: =J43-P43-S43 | U43: 011/02/2025 | V43: OM | W43: SOLDE
A44: 45696 | B44: ET | C44: 09FEB- | D44: KGL-DLA | E44: 00132/02/2025 | F44: MR BAYANG | G44: BAYANG JOB | H44: MME HEUNA | I44: 192 200 | J44: 299900 | K44: 279200 | L44: 20700 | M44: GOLITE | N44: ETKT 0715827796937 | O44: 3 | S44: 299900 | T44: =J44-P44-S44 | U44: 012/02/2025 | V44: CAISSE | W44: SOLDE
A45: 45696 | B45: NH | C45: 28JUN-12JUL | D45: BRU-NRT-BRU | E45: 00133/02/2025 | F45: SMC | G45: HOT SAMORI NGANDE | H45: DG | J45: 3230800 | K45: 3150290 | L45: 80510 | M45: BLUEBERRY | N45: ETKT 2050675025979 | S45: 3230800 | T45: =J45-P45-S45 | U45: 45701 | V45: BANQUE | W45: CHQ 8465699
A46: 45696 | B46: NH | C46: 28JUN-12JUL | D46: BRU-NRT-BRU | E46: 00133/02/2025 | F46: SMC | G46: HOT JUNIOR THIERRY | H46: DG | J46: 3230800 | K46: 3150290 | L46: 80510 | M46: BLUEBERRY | N46: ETKT 2050675025978 | S46: 3230800 | T46: =J46-P46-S46 | U46: 45701 | V46: BANQUE | W46: CHQ 8465699
A47: 45696 | B47: NH | C47: 28JUN-12JUL | D47: BRU-NRT-BRU | E47: 00133/02/2025 | F47: SMC | G47: ETOGO ASSE FREDERIQUE ESTELLE | H47: DG | J47: 3230800 | K47: 3150290 | L47: 80510 | M47: BLUEBERRY | N47: ETKT 2050675025977 | S47: 3230800 | T47: =J47-P47-S47 | U47: 45701 | V47: BANQUE | W47: CHQ 8465699
A48: 45698 | B48: TK | C48: 08MAR-08APR | D48: DLA-CDG-DLA | E48: 00134/02/2025 | F48: MR MENOUGA | G48: MENOUNGA NOMO JEAN GUIDEL | H48: DG | I48: 162 900 | J48: 672820 | K48: 539320 | L48: 133500 | M48: GOLITE | N48: ETKT 2355827796939 | O48: 4 | P48: 300000 | S48: 372820 | T48: =J48-P48-S48 | U48: 19/02/2025 04/03/2025 | V48: OM CAISSE
A49: 45699 | B49: QC | C49: 12FEB- | D49: DLA-NSI | E49: 00135/02/2025 | F49: DAF BANGE BANK | G49: NVE MODJO JUSTINO NGUERE | H49: DG | I49: 16 970 | J49: 89900 | K49: 41870 | L49: 48030 | M49: KIU | N49: ETKT 0400300037027 | S49: 89900 | T49: =J49-P49-S49 | U49: 010/03/2025 | V49: OM
A50: 45700 | B50: J7 | C50: 27FEB-01MAR | D50: DLA-LBV-DLA | E50: 00138/02/2025 | F50: HARVEST | G50: YE SENEH POWOH INNOCENT | H50: DG | J50: 15000 | L50: 15000 | M50: J7 | N50: ETKT 27722923059 | O50: EXCHANGE | S50: 15000 | T50: =J50-P50-S50 | U50: 45722 | V50: V/R
A51: 45700 | B51: J7 | C51: 27FEB-01MAR | D51: DLA-LBV-DLA | E51: 00137/02/2025 | F51: HARVEST | G51: BUNANG POUEME LIONEL FRANKY | H51: DG | J51: 15000 | L51: 15001 | M51: J7 | N51: ETKT 27722923059 | O51: EXCHANGE | S51: 15000 | T51: =J51-P51-S51 | U51: 45722 | V51: V/R
A52: 45700 | B52: AF | C52: 21FEB-29APR | D52: DLA-CDG-DLA | E52: 00139/02/2025 | F52: MRS EYOUM | G52: DONGMO TEFACK EP EYOUM LINDA | H52: DG | J52: 812900 | K52: 740000 | L52: 72900 | M52: BLUEBERRY | N52: ETKT 0572306439210 | P52: 213960 | Q52: 98720 | R52: 496220 | S52: 4000 | T52: =J52-Q52-R52-P52-S52 | U52: 27/02/2025 05/03/2025 19/03/2025 13/05/2025 | V52: OM | X52: 216 960
A53: 45700 | B53: AF | C53: 03MAY- | D53: ABJ-LHR | E53: 00136/02/2025 | F53: SMC | G53: APLPHING KOUASSI LYNDA | H53: DG | J53: 32800 | L53: 32800 | M53: GOLITE | N53: ETKT 0575827796941 | O53: EXCHANGE | S53: 32800 | T53: =J53-P53-S53 | U53: 45716 | V53: CAISSE
A54: 45700 | B54: AF | C54: 16FEB-27FEB | D54: DLA-MEX.CDG-DLA | E54: 00140/02/2025 | F54: HORUS | G54: ENAMA MARIE LAURE | H54: DG | J54: 3973900 | K54: 3693465 | L54: 280435 | M54: BLUEBERRY | N54: ETKT 0572306439211 | S54: 3973900 | T54: =J54-P54-S54 | U54: 45762 | V54: BANQUE | W54: CHQ 2988599
A55: 45701 | B55: HF | C55: 13MAR-20MAR | D55: DLA-DSS-DLA | E55: 00141/02/2025 | F55: MR KAMGA | G55: KAMGA TCHOUAFA EPSE TCHALEU ROLANDE | H55: MME HEUNA | J55: 423500 | K55: 388820 | L55: 34680 | M55: AMADEUS | N55: ETKT 4833578246895 | S55: 847000 | T55: =J55+J56-P55-S55 | U55: 45701 | V55: CAISSE | W55: SOLDE
A56: 45701 | B56: HF | C56: 13MAR-16MAR | D56: DLA-DSS-DLA | E56: 00142/02/2025 | F56: MR TCHALEU | G56: TCHALEU NGALEMO GILBERT | H56: MME HEUNA | J56: 423500 | K56: 388820 | L56: 34680 | M56: AMADEUS | N56: ETKT 4833578246894 | W56: SOLDE
A57: 45701 | B57: C8 | C57: 14FEB- | D57: DLA-SSG-DLA | E57: 00143/02/2025 | F57: DAF BANGE BANK | G57: NVE MODJO JUSTINO NGUERE | H57: DG | I57: 80 000 | J57: 232950 | K57: 151000 | L57: 81950 | M57: C8 | N57: ETKT 49850000316894 | S57: 232950 | T57: =J57-P57-S57 | U57: 45726 | V57: OM
A58: 45701 | B58: C8 | C58: 14FEB-16FEB | D58: DLA-SSG-DLA | E58: 00144/02/2025 | F58: DAF BANGE BANK | G58: NGUE ANNE GUILAINE | H58: DG | I58: 190 000 | J58: 378950 | K58: 288000 | L58: 90950 | M58: C8 | N58: ETKT 49850000316893 | P58: 54350 | Q58: 268000 | T58: =J58-Q58-R58-P58-S58 | U58: 10/03/2025 28/03/2025 | V58: OM CAISSE
A59: 45701 | B59: ET | C59: 20FEB-24FEB | D59: DLA-DXB-DLA | E59: 00145/02/2025 | F59: CABINET DENTAIRE G2 | G59: SIMO KAMDEM JEANNE CLAIRE | H59: DG | I59: 1 143 400 | J59: 1895820 | K59: 1755820 | L59: 140000 | M59: GOLITE | N59: ETKT 0715827796942 | O59: 4 | S59: 1895820 | T59: =J59-P59-S59 | U59: 45705 | V59: CAISSE
A60: 45701 | B60: KP | C60: 27FEB-02MAR | D60: DLA-LFW-DLA | E60: 00146/02/2025 | F60: ELECT INGENIERIE | G60: KAMGA STEPHANE | H60: DG | I60: 119 400 | J60: 430500 | K60: 380420 | L60: 50080 | M60: GOLITE | N60: ETKT 0325827796943 | O60: 2 | S60: 430500 | T60: =J60-P60-S60 | U60: 45827 | V60: BANQUE | W60: CHQ8040578
A61: 45702 | B61: QC | C61: 18FEB-18FEB | D61: DLA-NSI-DLA | E61: 00148/02/2025 | F61: APCAR | G61: MEDJO MEVA A EPSE NAOMIE MIRABELLE | H61: DG | I61: 33 640 | J61: 96900 | K61: 81540 | L61: 15360 | M61: KIU | N61: ETKT 0400300037031 | S61: 96900 | T61: =J61-P61-S61 | U61: 45727 | V61: BANQUE | W61: CHQ 8815107
A62: 45702 | B62: QC | C62: 18FEB-18FEB | D62: DLA-NSI-DLA | E62: 00148/02/2025 | F62: APCAR | G62: MATUENO LAURE NICAISE | H62: DG | I62: 33 640 | J62: 96900 | K62: 81540 | L62: 15360 | M62: KIU | N62: ETKT 0400300037030 | S62: 96900 | T62: =J62-P62-S62 | U62: 45727 | V62: BANQUE | W62: CHQ 8815107
A63: 45702 | B63: QC | C63: 20FEB- | D63: NSI-DLA | E63: 00156/02/2025 | F63: CANAL+ | G63: PUNTURELLO SEBASTIEN | H63: DG | I63: 19 170 | J63: 81900 | K63: 55170 | L63: 26730 | M63: KIU | N63: ETKT 040030003729 | S63: 81900 | T63: =J63-P63-S63 | U63: 45754 | V63: BANQUE
A64: 45702 | B64: QC | C64: 20FEB- | D64: NSI-DLA | E64: 00156/02/2025 | F64: CANAL+ | G64: TAMBA ZAPO PAUL ZEPHYRIN | H64: DG | I64: 19 170 | J64: 81900 | K64: 55170 | L64: 26730 | M64: KIU | N64: ETKT 040030003728 | S64: 81900 | T64: =J64-P64-S64 | U64: 45754 | V64: BANQUE
A65: 45703 | B65: QC | C65: 18FEB-18FEB | D65: DLA-NSI-DLA | E65: 00148/02/2025 | F65: APCAR | G65: MATUENO LAURE NICAISE | H65: DG | I65: - | J65: 23500 | K65: 13000 | L65: 10500 | M65: QC | N65: ETKT 0400300037030 | O65: EXCHANGE | S65: 23500 | T65: =J65-P65-S65 | U65: 45727 | V65: BANQUE | W65: CHQ 8135107
A66: 45703 | B66: AH | C66: 28FEB-13MAR | D66: DLA-MXP.CDG-DLA | E66: 00147/02/2025 | F66: MR DJAPOM | G66: DJAPOM NANA JOB STEPHANE | H66: MR STEPHANE | I66: 132 300 | J66: 418820 | K66: 418820 | L66: - | M66: GOLITE | N66: ETKT 1245827796944-945 | O66: 4 | P66: 200000 | Q66: 200000 | T66: =J66-Q66-P66-S66 | U66: 45727 | V66: CAISSE
A67: 45703 | B67: AF | C67: 17FEB-23FEB | D67: CDG-DLA.NSI-CDG | E67: 00149/02/2025 | F67: MR ONANA | G67: BIWOLE BIWOLE EDWIGE YOLANDE | H67: DG | I67: 4 859 400 | J67: 5784520 | K67: 5684520 | L67: 100000 | M67: GOLITE | N67: ETKT 0575827796946 | O67: 2 | S67: 5784520 | T67: =J67-Q67-R67-P67-S67 | U67: 45730 | V67: CAISSE
A68: 45705 | B68: C8 | C68: 19FEB- | D68: SSG-DLA | E68: 00152/02/2025 | F68: DAF BANGE BANK | G68: NVE MODJO JUSTINO NGUERE | H68: DG | I68: 129 900 | J68: 232950 | K68: 157000 | L68: 75950 | M68: C8 | N68: ETKT 49850000317788 | T68: =J68-P68-S68
A69: 45705 | B69: C8 | C69: 19FEB- | D69: SSG-DLA | E69: 00153/02/2025 | F69: DAF BANGE BANK | G69: NGUE ANNE GUILAINE | H69: DG | J69: 89950 | K69: 57500 | L69: 32450 | M69: C8 | N69: ETKT 48950000316893 | O69: EXCHANGE | T69: =J69-P69-S69
A70: 45705 | B70: TK | C70: 14APR-24APR | D70: CDG-DLA-CDG | E70: 00154/02/2025 | F70: MS NFANDA | G70: MS NFANDA CHERYL ORLANE | H70: MME HEUNA | I70: 141 100 | J70: 531500 | K70: 511520 | L70: 19980 | M70: GOLITE | N70: ETKT 2355827796947 | O70: 4 | S70: 531500 | T70: =J70-P70-S70 | U70: 45706 | V70: CAISSE | W70: SOLDE
A71: 45705 | B71: AH | C71: 18FEB-26FEB | D71: ALG-DLA-ALG | E71: 00155/002/2025 | F71: KALFRELEC | G71: BOUKHEZZAR ABDELAZIZ | H71: DG | I71: 122 900 | J71: 410950 | K71: 300920 | L71: 110030 | M71: GOLITE | N71: ETKT 1245827796948 | O71: 2 | T71: =J71-P71-S71
A72: 45705 | B72: QC | C72: 18FEB- | D72: DLA-NSI | E72: 00151/02/2025 | F72: TOASMI ASSURANCE | G72: DJAPOM NANA JOB STEPHANE | H72: MR STEPHANE | I72: 19 170 | J72: 55170 | K72: 55170 | L72: - | M72: KIU | N72: ETKT 0400300037032 | T72: =J72-P72-S72
A73: 45705 | B73: SN | C73: 18FEB- | D73: BRU-DLA | E73: 00150/02/2025 | F73: TOASMI VOYAGE | G73: TEZANOU KAFACK EPSE AZEMKOUO GEORGETTE | H73: DG | J73: 94600 | K73: 94600 | L73: - | M73: SN | N73: ETKT 0824558574471 | O73: EMD | T73: =J73-P73-S73
A74: 45706 | B74: ET | C74: 20FEB-23FEB | D74: NSI-LBV-NSI | E74: 00159/02/2025 | F74: BANGE BANK | G74: MASSOMA FRANCIA EDWINE ARNAULD | H74: DG | I74: 361 600 | J74: 690950 | K74: 640755 | L74: 50195 | M74: GOLITE | N74: ETKT 0715827796949 | O74: 2 | S74: 687352 | T74: =J74-P74-S74 | U74: 45719 | V74: V/R
A75: 45706 | B75: J7 | C75: 19FEB-23FEB | D75: DLA-LBV-DLA | E75: 00157/02/2025 | F75: BANGE BANK | G75: SELATSA KEALACK REINE AUDREY | H75: DG | I75: 188 820 | J75: 520920 | K75: 465100 | L75: 55820 | M75: J7 | N75: ETKT 277004562099 | S75: 518223 | T75: =J75-P75-S75 | U75: 45719 | V75: V/R
A76: 45706 | B76: QC | C76: 19FEB-19FEB | D76: NSI-DLA-NSI | E76: 00158/02/2025 | F76: BANGE BANK PERSO | G76: BIYANG OBIANG ELSA ANTONIA | H76: DG | I76: 38 140 | J76: 129950 | K76: 109540 | L76: 20410 | M76: KIU | N76: ETKT 0400300037033 | S76: 129150 | T76: =J76-P76-S76 | U76: 21/02/2025 26/03/2025 | V76: CAISSE V/R BB | W76: SOLDE | X76: DOUBLE PAIEMENT
A77: 45707 | B77: SN | C77: 23MAR-29MAR | D77: CDG-DLA-CDG | E77: 00163/02/2025 | F77: ISTAMA | G77: FABBRI FILIPPO | H77: DG | I77: 328 700 | J77: 684800 | K77: 589720 | L77: 95080 | M77: NDC | N77: ETKT 0829049042130 | S77: 684800 | T77: =J77-P77-S77 | U77: 45660 | V77: V/R
A78: 45707 | B78: SN | C78: 23MAR-29MAR | D78: CDG-DLA-CDG | E78: 00163/02/2025 | F78: ISTAMA | G78: DREYFUSS XAVIER DAVID | H78: DG | I78: 328 701 | J78: 684800 | K78: 589720 | L78: 95080 | M78: NDC | N78: ETKT 0829049042129 | S78: 684800 | T78: =J78-P78-S78 | U78: 45660 | V78: V/R
A79: 45707 | B79: C8 | C79: 21FEB- | D79: SSG-DLA | E79: 00161/02/2025 | F79: DAF BANGE BANK | G79: NVE MODJO JUSTINO NGUERE | H79: DG | I79: - | J79: 60000 | K79: 40000 | L79: 20000 | M79: C8 | N79: ETKT 49850000317788 | O79: EXCHANGE | T79: =J79-P79-S79
A80: 45707 | B80: J7 | C80: 19FEB-21FEB | D80: DLA-SSG-DLA | E80: 00160/02/2025 | F80: BANGE BANK | G80: ILLIASSOU MOHAMADOU ABDEL AZIZ | H80: DG | I80: 164 744 | J80: 442950 | K80: 306 000 | L80: 136 950 | M80: J7 | N80: ETKT 27723005235 | S80: 439352 | T80: =J80-P80-S80 | U80: 45742 | V80: V/R
A81: 45707 | B81: WB | C81: 17MAR-03ARP | D81: DLA-CDG-DLA | E81: 00163/02/2025 | F81: MRS NJIA EP DRAULT | G81: NJIA EP DRAULT LAURE BEATRICE | H81: MME HEUNA | I81: 150 000 | J81: 468000 | K81: 431 220 | L81: 36 780 | M81: GOLITE | N81: ETKT 4599588273650 | O81: 4 | S81: 468800 | T81: =J81-P81-S81 | U81: 45707 | V81: CAISSE | W81: SOLDE
A82: 45708 | B82: QC | C82: 20FEB- | D82: DLA-NSI | E82: 00167/02/2025 | F82: MR ONANA | G82: BIWOLE BIWOLE EDWIGE YOLANDE | H82: DG | I82: 26 370 | J82: 119900 | K82: 99 770 | L82: 20 130 | M82: KIU | N82: ETKT 0400300037034 | S82: 119900 | T82: =J82-P82-S82 | U82: 45730 | V82: CAISSE
A83: 45708 | B83: SN | C83: 19MAR-23MAR | D83: BRU-NSI-BRU | E83: 00168/02/2025 | F83: SMC | G83: BABISSAGANA EMMANUEL NOEL | H83: DG | I83: 372 600 | J83: 670950 | K83: 593 020 | L83: 77 930 | M83: NDC | N83: ETKT 0829049042131 | S83: 670950 | T83: =J83-P83-S83 | U83: 45716 | V83: CAISSE
A84: 45708 | B84: J7 | C84: 04MAR-06MAR | D84: DLA-LBV-DLA | E84: 00169/02/2025 | F84: HARVEST | G84: KAMGAING TAASSI MARC ETIENNE | H84: DG | I84: - | J84: 50000 | K84: 30 000 | L84: 20 000 | M84: J7 | N84: ETKT 2772302434 | O84: EXCHANGE | S84: 50000 | T84: =J84-P84-S84 | U84: 45757 | V84: V/R
A85: 45708 | B85: J7 | C85: 22FEB-25FEB | D85: DLA-LBV-DLA | E85: 00164/02/2025 | F85: BANGE BANK | G85: MONSUY NFONO MARIANO MONSUY | H85: DG | I85: 188 664 | J85: 520950 | K85: 465 100 | L85: 55 850 | M85: J7 | N85: ETKT 27723026956 | S85: 517352 | T85: =J85-P85-S85 | U85: 45742 | V85: V/R
A86: 45708 | B86: QC | C86: 23FEB- | D86: DLA-BFX | E86: 00165/02/2025 | F86: CANAL+ | G86: EMBOLO OYONO NINA SUZANNE | H86: DG | I86: 17 370 | J86: 66500 | K86: 44 170 | L86: 22 330 | M86: KIU | N86: ETKT 0400300037035 | S86: 66500 | T86: =J86-P86-S86 | U86: 45789 | V86: BANQUE
A87: 45708 | B87: AF | C87: 23FEB. | D87: IAD-CDG | E87: 00166/02/2025 | F87: HORUS | G87: ENAMA EPSE ONANA, MARIE LAURE | H87: DG | I87: 4 498 100 | J87: 5371300 | K87: 5 178 500 | L87: 192 800 | M87: GOLITE | N87: ETKT 0579588273651 | O87: 1 | S87: 5371300 | T87: =J87-P87-S87 | U87: 45762 | V87: BANQUE | W87: CHQ 2988599
A88: 45709 | B88: QC | C88: 24FEB-02MAR | D88: DLA-NGE.GOU-DLA | E88: 00173/02/2025 | F88: ADSNET | G88: TEKOBOU YMELE SIMON | H88: DG | I88: 70 640 | J88: 200900 | K88: 170 740 | L88: 30 160 | M88: KIU | N88: ETKT 0400300037036 | S88: 200900 | T88: =J88-P88-S88 | U88: 45763 | V88: BANQUE | W88: CHQ 2988599
A89: 45709 | B89: AT | C89: 22FEB-26FEB | D89: DLA-RAK-DLA | E89: 00174/02/2025 | F89: ASPROM | G89: AWATIO TCHINDA ALECE FRACIOLI | H89: DG | I89: 528 800 | J89: 827120 | K89: 777 120 | L89: 50 000 | M89: GOLITE | N89: ETKT 1479588273652 | O89: 4 | S89: 855920 | T89: =J89-P89-S89 | U89: 45708 | V89: BANQUE | W89: CHQ 6217354
A90: 45709 | B90: J7 | C90: 23FEB. | D90: DLA-BSG | E90: 00172/02/2025 | F90: BANGE BANK | G90: BIYANG OBIANG ELSA ANTONIA | H90: DG | J90: 374950 | K90: 274 250 | L90: 100 700 | M90: J7 | N90: ETKT 27723037661 | S90: 371352 | T90: =J90-P90-S90 | U90: 45742 | V90: V/R
A91: 45709 | B91: J7 | C91: 23FEB. | D91: DLA-BSG | E91: 00172/02/2025 | F91: BANGE BANK | G91: NVE BIYANG CELENDONIO | H91: DG | L91: - | M91: J7 | N91: ETKT 27723037661 | U91: 45742 | V91: V/R
A92: 45709 | B92: TK | C92: 16APR-16MAY | D92: DLA-IAD-DLA | E92: 00175/02/2025 | F92: MRS NGUENKAM | G92: NGUENKAM EPSE TCHOUAGA MARIE LOUISE | H92: MME HEUNA | J92: 700100 | K92: 683 120 | L92: 16 980 | M92: AMADEUS | N92: ETKT 2353578250737 | S92: 700100 | T92: =J92-P92-S92 | U92: 45709 | V92: CAISSE | W92: SOLDE
A93: 45709 | B93: J7 | C93: 23FEB. | D93: SSG-DLA | E93: 00171/02/2025 | F93: BANGE BANK | G93: ABDEL AZIZ ILIASSOU MOHAMADOU | H93: DG | J93: 60000 | K93: 30 000 | L93: 30 000 | M93: J7 | N93: ETKT 27723037208 | O93: EXCHANGE | S93: 60000 | T93: =J93-P93-S93 | U93: 45742 | V93: V/R
A94: 45709 | B94: QC | C94: 06MAR-09MAR | D94: NSI-DLA-NSI | F94: BANGE BANK | G94: JOSE MANUEL ESONO EDJANG | H94: DG | J94: 105950 | K94: 57 940 | L94: 48 010 | M94: KIU | N94: ETKT 040030003737 | S94: 105950 | T94: =J94-P94-S94 | U94: 45742 | V94: V/R
A95: 45710 | B95: ET | C95: 23FEB. | D95: NSI-SSG | E95: 00176/02/2025 | F95: BANGE BANK | G95: BIYANG OBIANG ELSA ANTONIA | H95: DG | I95: 303 300 | J95: 598950 | K95: 521 055 | L95: 77 895 | M95: GOLITE | N95: ETKT 0719588273654 | O95: 1 | S95: 692504 | T95: =J95+J96-P95-S95 | U95: 45742 | V95: V/R
A96: 45710 | B96: ET | C96: 23FEB. | D96: NSI-SSG | F96: BANGE BANK | G96: NVE BIYANG CELENDONIO | H96: DG | I96: 30 400 | J96: 98950 | K96: 67 400 | L96: 31 550 | M96: GOLITE | N96: ETKT 0719588273655 | O96: 1
A97: 45710 | B97: AT | C97: 25FEB. | D97: RAK-DLA | E97: 00179/02/2025 | F97: ATLANTIQUE | G97: FOTADZONG TCHIO THEOPHILE | H97: DG | J97: 198000 | K97: - | L97: 198 000 | M97: GOLITE | N97: ETKT 1479588273653 | O97: EXCHANGE | S97: 198000 | T97: =J97-P97-S97 | U97: 45744 | V97: BANQUE | W97: CHQ 2342450
A98: 45710 | B98: ET | C98: 24MAR-06APR | D98: DLA-DXB-DLA | E98: 00180/02/2025 | F98: MR TATIEZEU | G98: TATIEZEU GUEDIA BRUNO | H98: DG | I98: 152 000 | J98: 508900 | K98: 438 820 | L98: 70 080 | M98: GOLITE | N98: ETKT 0719588273658 | O98: 4 | S98: 1017800 | T98: =J98+J99-S98 | U98: 45713 | V98: CAISSE
A99: 45710 | B99: ET | C99: 24MAR-06APR | D99: DLA-DXB-DLA | E99: 00180/02/2025 | F99: MR TATIEZEU | G99: TSAFACK EPSE TATIEZEU ANNE CHANTAL | H99: DG | I99: 152 001 | J99: 508900 | K99: 438 820 | L99: 70 080 | M99: GOLITE | N99: ETKT 0719588273659 | O99: 4
A100: 45711 | B100: SN | C100: 15MAY-30MAY | D100: DLA-CDG-DLA | E100: 00181/02/2025 | F100: ISTAMA | G100: NJANTA EBENEZER | H100: DG | I100: 261 820 | J100: 590950 | K100: 537 120 | L100: 53 830 | M100: NDC | N100: ETKT 0829049042132 | S100: 590950 | T100: =J100-P100-S100 | U100: 45660 | V100: V/R
...

Sheet MAR
A1: DATE | B1: CIES | C1: PARCOURS | D1: TRAVEL DATE | E1: N FACTURE | F1: ENTREPRISE | G1: NOMS/PRENOMS | H1: APPORTEUR | I1: TARIF HT | J1: TC | K1: TM | L1: FS | M1: LIEU ACHAT | N1: NUMERO DU BILLET | O1: NBRE SGTS | P1: AVANCE 1 | Q1: AVANCE 2 | R1: AVANCE 03 | S1: RGLT | T1: SOLDE | U1: DATE RGL | V1: MODE RGLT | W1: OBS | X1: VR GOLITE | Y1: GOLITE | Z1: VR CAMAIR CO | AA1: CAMAIR CO | AB1: VR B2B | AC1: B2B
A2: 45717 | B2: ET | C2: DLA-MXP.CDG-DLA | D2: 02MAR-12MAR | E2: 00198/03/2025 | F2: MRS NJOFIN | G2: NJOFIN EPSE KAMGA FLORE | H2: MME HEUNA | J2: 147400 | K2: 137500 | L2: =J2-K2 | M2: GOLITE | N2: ETKT 0719588273688 - 689 | O2: EXCHANGE | S2: 147400 | T2: =J2-P2-S2 | U2: 45719 | V2: CAISSE | W2: SOLDE | AD2: 0
A3: 45717 | B3: KP | C3: NDJ-DLA-NDJ | D3: 05MAR-08MAR | E3: 00199/03/2025 | F3: HORUS | G3: DJIKOLOUM GUESSIMBAYE AIME | H3: DG | I3: 894300 | J3: 1249950 | K3: 1141805 | L3: =J3-K3 | M3: GOLITE | N3: ETKT 0329588273690 | O3: 2 | S3: 1249950 | T3: =J3-P3-S3 | U3: 45762 | V3: BANQUE | W3: CHQ 2988599
A4: 45717 | B4: KP | C4: LFW-DLA | D4: 02MAR. | E4: 00200/03/2025 | F4: SAAR | G4: KAGOU GEORGES LEOPOLD | H4: DG | I4: 584100 | J4: 695000 | K4: 685000 | L4: =J4-K4 | M4: GOLITE | N4: ETKT 0329588273691 | O4: 1 | S4: 695000 | T4: =J4-P4-S4 | U4: 45749 | V4: BANQUE | W4: CHQ 8619291
A5: 45718 | B5: AF | C5: NSI-BLQ-NSI | D5: 02MAR-03MAY | E5: 00202/03/2025 | F5: MR KUEDA | G5: KUEDA HARMAND BERTRAND | H5: MME HEUNA | J5: 879746 | K5: 849746 | L5: =J5-K5 | M5: BLUEBERRY | N5: ETKT 0572333237561 | S5: 879800 | T5: =J5-P5-S5 | U5: 45719 | V5: CAISSE | W5: SOLDE
A6: 45719 | B6: KP | C6: NDJ-DLA-NDJ | D6: 05MAR-08MAR | E6: 00204/03/2025 | F6: HORUS | G6: ABDEL RAZIK MAHAMAT IDRISS | H6: DG | I6: 606000 | J6: 953505 | K6: 853505 | L6: =J6-K6 | M6: GOLITE | N6: ETKT 0329588273692 | O6: 2 | S6: 953505 | T6: =J6-P6-S6 | U6: 45762 | V6: BANQUE | W6: CHQ 2988599
A7: 45719 | B7: HF | C7: DLA-ABJ-DLA | D7: 05MAR-07MAR | E7: 00205/03/2025 | F7: SAAR | G7: KAGOU GEORGES LEOPOLD | H7: DG | I7: 155300 | J7: 584820 | K7: 504820 | L7: =J7-K7 | M7: GOLITE | N7: ETKT 4839588273693 | O7: 2 | S7: 584820 | T7: =J7-P7-S7 | U7: 45384 | V7: BANQUE | W7: CHQ 8619290
A8: 45719 | B8: QC | C8: DLA-NSI | D8: 03MAR. | E8: 00203/03/2025 | F8: DAF BANGE BANK | G8: JUSTINO NGUERE, NVE MODJO | H8: DG | J8: 89970 | K8: 55170 | L8: =J8-K8 | M8: KIU | N8: ETKT 0400300037046 | T8: =J8-P8-S8
A9: 45719 | B9: QC | C9: DLA-NSI | D9: 03MAR. | E9: 00203/03/2025 | F9: DAF BANGE BANK | G9: HABIB , MOHAMADOU | H9: DG | J9: 89970 | K9: 55170 | L9: =J9-K9 | M9: KIU | N9: ETKT 0400300037047 | T9: =J9-P9-S9
A10: 45720 | B10: KQ | C10: DLA-KGL | D10: 10MAR. | E10: 00207/03/2025 | F10: MRS KOUMOUSSOM | G10: KOUMOUSSOM NDJOCK MARIE ROSE | H10: MR ROMEO | I10: 93400 | J10: 250000 | K10: 234620 | L10: =J10-K10 | M10: GOLITE | N10: ETKT 7069588273694 | O10: 2 | S10: 250000 | T10: =J10-P10-S10 | U10: 45720 | V10: CAISSE
A11: 45720 | B11: QC | C11: NSI-DLA-NSI | D11: 05MAR-09MAR | E11: 00208/03/2025 | F11: BANGE BANK | G11: ESONO EDJANG JOSE MANUEL | H11: DG | J11: 35000 | K11: 24800 | L11: =J11-K11 | M11: QC | N11: ETKT 0400200522600 | O11: EXCHANGE | S11: 35000 | T11: =J11-P11-S11 | U11: 45779 | V11: V/R
A12: 45721 | B12: QC | C12: DLA-BFX-DLA | D12: 07MAR-09MAR | E12: 00209/03/2025 | F12: MR NGUIMEYA | G12: NGUIMEYA NGUEFAH PEPIN CHARLES | H12: DG | I12: 21700 | J12: 70950 | K12: 50240 | L12: =J12-K12 | M12: KIU | N12: ETKT 0400300037048 | S12: 70950 | T12: =J12-P12-S12 | U12: 45741 | V12: CAISSE | W12: SOLDE
A13: 45722 | B13: ET | C13: DLA-CAN | D13: 06MAR. | E13: 00210/03/2025 | F13: MR IGWEMEZIE | G13: IGWEZIE ELVIS IKECHUKWU | H13: MR LUCIEN | I13: 745300 | J13: 1047120 | K13: 982914 | L13: =J13-K13 | M13: GOLITE | N13: ETKT 0719588273695 | O13: 2 | P13: 800000 | S13: 247000 | T13: =J13-P13-S13 | U13: 45726 | V13: CAISSE
A14: 45722 | B14: QC | C14: DLA-NSI | D14: 06MAR. | F14: MME LEUGA | G14: EMILIENNE LEUGA EPSE KEUYAKANG | H14: MME HEUNA | J14: 69950 | K14: 41870 | L14: =J14-K14 | M14: KIU | N14: ETKT 0400300037049 | S14: 65950 | T14: =J14-P14-S14 | U14: 45748 | V14: CAISSE | W14: SOLDE
A15: 45723 | B15: C8 | C15: DLA-SSG-DLA | D15: 12MAR-19MAR | E15: 00211/03/2025 | F15: BANGE BANK | G15: NGALLE MIANO MAY DAPHNE | H15: DG | J15: 352950 | K15: 288000 | L15: =J15-K15 | M15: C8 | N15: ETKT 49850000322941 | S15: 348822 | T15: =J15-P15-S15 | U15: 45779 | V15: V/R
A16: 45724 | B16: ET | C16: DLA-BGF-DLA | D16: 16MAR-20MAR | F16: AFG- ASSURANCE | G16: FOTADZONG TCHIO THEOPHILE | H16: DG | I16: 342800 | J16: 0 | K16: 0 | L16: =J16-K16 | M16: GOLITE | N16: ETKT 0719588273696 | O16: REFUND | T16: =J16-P16-S16
A17: 45725 | B17: KP | C17: DLA-BGF-DLA | D17: 16MAR-20MAR | E17: 00212/03/2025 | F17: AFG- ASSURANCE | G17: FOTADZONG TCHIO THEOPHILE | H17: DG | I17: 342800 | J17: 1075900 | K17: 721555 | L17: =J17-K17 | M17: GOLITE | N17: ETKT 0329588273697 | O17: 2 | S17: 1075900 | T17: =J17-P17-S17 | U17: 45789 | V17: BANQUE | W17: CHQ2342423
A18: 45726 | B18: QC | C18: DLA-NSI | D18: 11MAR. | E18: 00237/03/2025 | F18: MR TOGNIA | G18: TOGNIA BERTRAND | H18: DG | J18: 71870 | K18: 66870 | L18: =J18-K18 | M18: QC | N18: ETKT 0400300037051 | T18: =J18-P18-S18 | W18: 10MARS.
A19: 45727 | B19: AF | C19: ABJ-CDG-ABJ | D19: 14MAR-25MAR | E19: 00214/03/2025 | F19: MR ONANA | G19: LOHOUES YEMELY EMMANUELLA JESUS | H19: DG | J19: 7981800 | K19: 6861700 | L19: =J19-K19 | M19: AMADEUS | N19: ETKT 0713578260355 | P19: 3561945 | S19: 4419855 | T19: =J19-P19-S19 | U19: 14/03/2025 22/04/205 | V19: CAISSE
A20: 45727 | B20: AF | C20: CDG-IAH-CDG | D20: 15MAR-24MAR | E20: 00215/03/2025 | F20: MR ONANA | G20: LOHOUES YEMELY EMMANUELLA JESUS | H20: DG | J20: 5955900 | K20: 5655300 | L20: =J20-K20 | M20: AMADEUS | N20: ETKT 0713578260356 | P20: 580145 | S20: 5375755 | T20: =J20-P20-S20 | U20: 22/04/2025 25/04/2025 | V20: CAISSE
A21: 45727 | B21: C8 | C21: DLA-SSG. | D21: 12MAR. | E21: 00216/03/2025 | F21: BANGE BANK | G21: OBIANG NCHAMA JOSE MICHEL | H21: DG | J21: 252950 | K21: 196000 | L21: =J21-K21 | M21: C8 | N21: ETKT 49850000323756 | S21: 250253 | T21: =J21-P21-S21 | U21: 45779 | V21: V/R
A22: 45727 | B22: C8 | C22: DLA-SSG-DLA | D22: 12MAR-16MAR | E22: 00217/03/2025 | F22: BANGE BANK | G22: NGALLE MIANO MAY DAPHNE | H22: DG | J22: 60000 | K22: 35000 | L22: =J22-K22 | M22: C8 | N22: ETKT 49850000322941.324029 | O22: EXCHANGE | S22: 60000 | T22: =J22-P22-S22 | U22: 45779 | V22: V/R
A23: 45727 | B23: KP | C23: DLA-COO-DLA | D23: 17MAR-19MAR | E23: 00218/03/2025 | F23: BANGE BANK | G23: ESONO OYANA ANGELICA MONAYONG | H23: DG | I23: 208100 | J23: 720950 | K23: 645230 | L23: =J23-K23 | M23: GOLITE | N23: ETKT 0329588273698 | O23: 4 | S23: 715553 | T23: =J23-P23-S23 | U23: 45779 | V23: V/R
A24: 45727 | B24: HF | C24: DLA-ABJ. | D24: 13APR. | E24: 00219/03/2025 | F24: SMC | G24: HOT JUNIOR THIERRY | H24: DG | I24: 592200 | J24: 949900 | K24: 869120 | L24: =J24-K24 | M24: GOLITE | N24: ETKT 4839588273699 | O24: 1 | S24: 949900 | T24: =J24-P24-S24 | U24: 45728 | V24: CAISSE
A25: 45727 | B25: SN | C25: DLA-BCN.MAD-DLA | D25: 03APR-11APR | E25: 00213/03/2025 | F25: MR DJOUAKA | G25: DOUAKA ROGER ALAIN | H25: DG | I25: 992600 | J25: 1385920 | K25: 1302920 | L25: =J25-K25 | M25: NDC | N25: ETKT 0829049042136-137 | S25: 1385920 | T25: =J25-P25-S25 | U25: 45727 | V25: V/R | W25: CHQ 8815107
A26: 45727 | B26: SN | C26: DLA-BCN.MAD-DLA | D26: 03APR-11APR | E26: 00213/03/2025 | F26: MR DJOUAKA | G26: KIFACK BOUKENG EPSE DJOUAKA FLORENCE | H26: DG | I26: 992600 | J26: 1385920 | K26: 1302920 | L26: =J26-K26 | M26: NDC | N26: ETKT 0829049042138-139 | S26: 1385920 | T26: =J26-P26-S26 | U26: 45727 | V26: V/R | W26: CHQ 8815107
A27: 45728 | B27: C8 | C27: DLA-SSG | D27: 12MAR. | F27: BANGE BANK | G27: OBIANG NCHAMA JOSE MICHEL | H27: DG | J27: 252950 | K27: 196000 | L27: =J27-K27 | M27: C8 | N27: ETKT 49850000323756 | T27: =J27-P27-S27
A28: 45728 | B28: KP | C28: DLA-DSS-DLA | D28: 11MAY-17MAY | E28: 00220/03/2025 | F28: CANAL+ | G28: ZIIDANG HABIBA DANIELLE | H28: DG | I28: 167200 | J28: 678950 | K28: 618520 | L28: =J28-K28 | M28: GOLITE | N28: ETKT 0329588273700 | O28: 4 | S28: 678950 | T28: =J28-P28-S28 | U28: 45768 | V28: V/R
A29: 45728 | B29: KP | C29: DLA-DSS-DLA | D29: 11MAY-21MAY | E29: 00221/03/2025 | F29: CANAL+ | G29: NA IMMA AMMADOU HAMIDOU | H29: DG | I29: 147900 | J29: 670950 | K29: 599220 | L29: =J29-K29 | M29: GOLITE | N29: ETKT 0329588273701 | O29: 4 | S29: 670950 | T29: =J29-P29-S29 | U29: 45768 | V29: V/R
A30: 45728 | B30: SN | C30: DLA-BCN.MAD-DLA | D30: 03APR-10APR | E30: 00213/03/2025 | F30: MR DJOUAKA | G30: DOUAKA ROGER ALAIN | H30: DG | I30: 0 | J30: 146200 | K30: 131200 | L30: =J30-K30 | M30: NDC | N30: ETKT 0829049042140-141 | O30: EXCHANGE | S30: 146200 | T30: =J30-P30-S30 | U30: 45803 | V30: V/R
A31: 45728 | B31: SN | C31: DLA-BCN.MAD-DLA | D31: 03APR-10APR | E31: 00213/03/2025 | F31: MR DJOUAKA | G31: KIFACK BOUKENG EPSE DJOUAKA FLORENCE | H31: DG | I31: 0 | J31: 146200 | K31: 131200 | L31: =J31-K31 | M31: NDC | N31: ETKT 0829049042142-143 | O31: EXCHANGE | S31: 146200 | T31: =J31-P31-S31 | U31: 45803 | V31: V/R
A32: 45728 | B32: SN | C32: DLA-BRU-DLA | D32: 13APR-08MAY | E32: 00223/03/2025 | F32: SMC | G32: DIBOUSSI MARIE ANGELE | H32: DG | I32: 455000 | J32: 725500 | K32: 675320 | L32: =J32-K32 | M32: NDC | N32: ETKT 0829049042144 | S32: 725500 | T32: =J32-P32-S32 | U32: 45728 | V32: CAISSE
A33: 45729 | B33: AT | C33: CDG-DLA. | D33: 14MAR. | E33: 00224/03/2025 | F33: MR DJAPOM | G33: DJAPOM NANA JOB STEPHANE | H33: MR STEPHANE | I33: 152200 | J33: 309500 | K33: 309500 | L33: =J33-K33 | M33: GOLITE | N33: ETKT 1479588273702 | O33: 2 | T33: =J33-P33-S33 | W33: 21MARS
A34: 45730 | B34: ET | C34: DLA-CAN-DLA | D34: 24MAR-05APR | E34: 00225/03/2025 | F34: MRS BIKONG | G34: SIMEU BEATRICE | H34: DG | J34: 905000 | K34: 832520 | L34: =J34-K34 | M34: B2B | N34: ETKT 0712151317279 | P34: 765000 | T34: =J34-P34-S34 | U34: 45730 | V34: CAISSE
A35: 45730 | B35: ET | C35: DLA-CAN-DLA | D35: 24MAR-05APR | E35: 00227/03/2025 | F35: SAFARI LOGISTIQUE | G35: TCHATCHOUA SUZANNE LINDA | H35: DG | J35: 2098800 | K35: 1383300 | L35: =J35-K35 | M35: AMADEUS | N35: ETKT 0713578262958 | P35: 2000000 | S35: 98800 | T35: =J35-P35-S35 | U35: 45737 | V35: BANQUE | W35: CHQ0000116
A36: 45730 | B36: ET | C36: DLA-CAN-DLA | D36: 24MAR-05APR | E36: 00227/03/2025 | F36: SAFARI LOGISTIQUE | G36: TINA ONGOLO CLAIRE FLORA | H36: DG | J36: 905000 | K36: 832520 | L36: =J36-K36 | M36: B2B | N36: ETKT 0712151317280 | S36: 905000 | T36: =J36-P36-S36 | U36: 45790 | V36: BANQUE | W36: CHQ0000127
A37: 45730 | B37: ET | C37: DLA-CAN-DLA | D37: 24MAR-05APR | E37: 00227/03/2025 | F37: SAFARI LOGISTIQUE | G37: YAMGOUE DEBANA CHRISTELLE YOLANDE | H37: DG | J37: 905000 | K37: 832520 | L37: =J37-K37 | M37: B2B | N37: ETKT 0712151317281 | S37: 905000 | T37: =J37-P37-S37 | U37: 45790 | V37: BANQUE | W37: CHQ0000127
A38: 45730 | B38: SA | C38: JNB-CPT | D38: 24MAR. | E38: 00228/03/2025 | F38: HORUS | G38: ONANA CYRILLE BERTRAND | H38: DG | J38: 464900 | K38: 330800 | L38: =J38-K38 | M38: SATGURU | N38: ETKT 0833576107301 | S38: 464900 | T38: =J38-P38-S38 | U38: 45762 | V38: V/R
A39: 45730 | B39: SA | C39: JNB-CPT | D39: 24MAR. | E39: 00228/03/2025 | F39: HORUS | G39: NGANI MEIGNIDON DIFFO MIRELLE NICAISE | H39: DG | J39: 282600 | K39: 152700 | L39: =J39-K39 | M39: SATGURU | N39: ETKT 0833576107302 | S39: 282600 | T39: =J39-P39-S39 | U39: 45762 | V39: V/R
A40: 45731 | B40: C8 | C40: SSG-DLA | D40: 16MAR. | E40: 00229/03/2025 | F40: BANGE BANK | G40: OBIANG NCHAMA JOSE MICHEL | H40: DG | J40: 247000 | K40: 167000 | L40: =J40-K40 | M40: C8 | N40: ETKT 49850000325117 | S40: 243402 | T40: =J40-P40-S40 | U40: 45779 | V40: V/R
A41: 45731 | B41: AF | C41: DLA-CDG.BOD-LYS-DLA | D41: 05JUN-14JUN-19JUN | E41: 00230/03/2025 | F41: CANAL+ | G41: TA BI TAH HUGUES YANNICK | H41: DG | I41: 1983100 | J41: 2437420 | K41: 2319620 | L41: =J41-K41 | M41: GOLITE | N41: ETKT 0579588273703 | O41: 6 | S41: 2437420 | T41: =J41-P41-S41 | U41: 45768 | V41: V/R
A42: 45731 | B42: AF | C42: CDG-JNB- CDG | D42: 23MAR-27MAR | E42: 00231/03/2025 | F42: HORUS | G42: ONANA CYRILLE BERTRAND | H42: DG | I42: 5367100 | J42: 7009500 | K42: 6075700 | L42: =J42-K42 | M42: GOLITE | N42: ETKT 0579588273705 | O42: 2 | P42: 5193205 | S42: 1816295 | T42: =J42-P42-S42 | U42: 45842 | V42: V/R
A43: 45731 | B43: ET | C43: DLA-CAN-DLA | D43: 21MAR-27MAR | E43: 00231/03/2025 | F43: HORUS | G43: NGANI MEIGNIDON DIFFO MIRELLE NICAISE | H43: DG | J43: 2195900 | K43: 1912120 | L43: =J43-K43 | M43: B2B | N43: ETKT 0712151334071 | S43: 2195900 | T43: =J43-P43-S43 | U43: 45842 | V43: V/R
A44: 45732 | B44: QC | C44: DLA-NSI-DLA | D44: 16MAR-17MAR | E44: 00233/03/2025 | F44: CANAL+ | G44: NGANKAM NIEGUIE FABIO | H44: DG | J44: 131000 | K44: 106340 | L44: =J44-K44 | M44: KIU | N44: ETKT 0400300037052 | T44: =J44-P44-S44
A45: 45733 | B45: KP | C45: SSG-NSI | D45: 18MAR. | E45: 00235/03/2025 | F45: BANGE BANK | G45: OBIANG NCHAMA JOSE MICHEL | H45: DG | I45: 90500 | J45: 307950 | K45: 180200 | L45: =J45-K45 | M45: GOLITE | N45: ETKT 0329588273707 | O45: 1 | S45: 304352 | T45: =J45-P45-S45
A46: 45733 | B46: J7 | C46: DLA-LBV-NSI | D46: 17MAR-19MAR | E46: 00234/03/2025 | F46: BANGE BANK | G46: NTSAMA GUY BERTRAND | H46: DG | J46: 571400 | K46: 471400 | L46: =J46-K46 | M46: J7 | N46: ETKT 2772333759 | S46: 566003 | T46: =J46-P46-S46 | U46: 45779 | V46: V/R
A47: 45733 | B47: QC | C47: DLA-COO | D47: 24MAR. | E47: 00236/03/2025 | F47: MR MOH | G47: MOH NGANNOU RAPHAEL | H47: MR LUCIEN | J47: 176120 | K47: 171120 | L47: =J47-K47 | M47: KIU | N47: ETKT 0400300037053 | P47: 176000 | T47: =J47-P47-S47 | U47: 45735 | V47: CAISSE | Y47: 1347205 | AA47: 1 643 043 | AB47: 5000000
A48: 45733 | B48: QC | C48: DLA-NSI-DLA | D48: 18MAR-25APR | E48: 00258/03/2025 | F48: HARVEST | G48: KAMGAING TAASSI MARC ETIENNE | H48: DG | J48: 126900 | K48: 111340 | L48: =J48-K48 | M48: KIU | N48: ETKT 0400300037054 | S48: 126900 | T48: =J48-P48-S48 | U48: 45769 | V48: V/R
A49: 45733 | F49: CABINET DENTAIRE G2 | G49: GAMGEM GUIADEM CATHERINE | H49: DG | J49: 60000 | K49: 55500 | L49: =J49-K49 | O49: VISA COTONOU | S49: 60000 | T49: =J49-P49-S49 | U49: 45735 | V49: CAISSE
A50: 45733 | F50: CABINET DENTAIRE G2 | G50: GAMGEM GUIADEM CATHERINE | H50: DG | J50: 85000 | K50: 75000 | L50: =J50-K50 | O50: VISA DUBAI | S50: 85000 | T50: =J50-P50-S50 | U50: 45735 | V50: CAISSE
A51: 45734 | B51: AT | C51: CMN-DLA-CMN | D51: 20MAR-03MAI | F51: KALFRELEC | G51: NICORA/GUY CARLO | H51: DG | I51: 526800 | J51: 845920 | K51: 766520 | L51: =J51-K51 | M51: GOLITE | N51: ETKT 1479588273708 | O51: 2 | T51: =J51-P51-S51
A52: 45735 | B52: ET | C52: DLA-CAN-DLA | D52: 24MAR-05APR | E52: 00240/03/2025 | F52: SAFARI LOGISTIQUE | G52: TCHATCHOUA SUZANNE LINDA | H52: DG | J52: 553300 | K52: 513300 | L52: =J52-K52 | M52: AMADEUS | N52: ETKT 0713578264050 | O52: EXCHANGE | P52: 441200 | S52: 112100 | T52: =J52-P52-S52 | U52: 13/05/2025 26/06/2025 | V52: BANQUE | W52: CHQ0000127 CHQ0000141
A53: 45735 | B53: ET | C53: DLA-CAN-DLA | D53: 24MAR-05APR | E53: 00241/03/2025 | F53: MRS BIKONG | G53: SIMEU BEATRICE | H53: DG | J53: 75000 | K53: 60000 | L53: =J53-K53 | M53: B2B | N53: ETKT 0712151417587 | O53: EXCHANGE | P53: 70000 | T53: =J53-P53-S53 | U53: 45800 | V53: CAISSE
A54: 45735 | B54: ET | C54: DLA-CAN-DLA | D54: 24MAR-05APR | E54: 00240/03/2025 | F54: SAFARI LOGISTIQUE | G54: TINA ONGOLO CLAIRE FLORA | H54: DG | J54: 75000 | K54: 60000 | L54: =J54-K54 | M54: B2B | N54: ETKT 0712151418215 | O54: EXCHANGE | P54: 0 | S54: 75000 | T54: =J54-P54-S54 | U54: 45834 | V54: BANQUE | W54: CHQ0000141
A55: 45735 | B55: ET | C55: DLA-CAN-DLA | D55: 24MAR-05APR | E55: 00240/03/2025 | F55: SAFARI LOGISTIQUE | G55: YAMGOUE DEBANA CHRISTELLE YOLANDE | H55: DG | J55: 75000 | K55: 60000 | L55: =J55-K55 | M55: B2B | N55: ETKT 0712151418152 | O55: EXCHANGE | P55: 0 | S55: 75000 | T55: =J55-P55-S55 | U55: 45834 | V55: BANQUE | W55: CHQ0000141
A56: 45735 | B56: QC | C56: DLA-NGE-DLA | D56: 10APR-17APR | E56: 00239/03/2025 | F56: MR MAMO | G56: MAMO KADJE LUC | H56: MME NOMENY | J56: 146640 | K56: 124640 | L56: =J56-K56 | M56: KIU | N56: ETKT 0400300037055 | S56: 146640 | T56: =J56-P56-S56 | U56: 45735 | V56: CAISSE | W56: SOLDE
A57: 45735 | B57: SN | C57: DLA-CDG-DLA | D57: 04MAI-28JUL | E57: 00238/03/2025 | F57: PARENT IUC MR NEABO | G57: MOGUO KUATE EPSE NEABO MARLYSE | H57: DG | I57: 505600 | J57: 845950 | K57: 767420 | L57: =J57-K57 | M57: NDC | N57: ETKT 0829049042145 | S57: 845950 | T57: =J57-P57-S57 | U57: 45735 | V57: CAISSE | W57: SOLDE
A58: 45736 | B58: ET | C58: DXB-NSI | D58: 25MAR. | E58: 00244/03/2025 | F58: M NGAKO | G58: NGAKO KETCHANGA CEDRIC MATHIEU | H58: DG | J58: 1698000 | K58: 1475000 | L58: =J58-K58 | M58: BLUEBERRY | N58: ETKT 0712151435594 | P58: 588200 | Q58: 1000000 | S58: 109800 | T58: =J58-P58-Q58-S58 | U58: 13/09/2025 14/09/2025 15/09/2025 | V58: CAISSE
A59: 45736 | B59: QC | C59: BFX-DLA-BFX | D59: 21MAR-26MAR | E59: 00242/03/2025 | F59: TATA PASCALINE | G59: NINWOUO MAKOUTCHOUAN EPSE NKENFACK ZEBAZE SYLVIE PASCALINE | H59: DG | J59: 71940 | K59: 66940 | L59: =J59-K59 | M59: KIU | N59: ETKT 0400300037056 | S59: 71940 | T59: =J59-P59-S59 | U59: 45740 | V59: CAISSE | W59: SOLDE
A60: 45736 | B60: SN | C60: CDG-DLA-CDG | D60: 11JAN-18JAN | E60: 00243/03/2025 | F60: ISTAMA | G60: CHRISTOPHE MICHEL LUC BRETON | H60: DG | J60: 195000 | K60: 20100 | L60: =J60-K60 | M60: NDC | N60: ETKT 0829049042147 | O60: EXCHANGE | P60: 0 | S60: 195000 | T60: =J60-P60-S60 | U60: 45792 | V60: V/R
A61: 45736 | B61: TP | C61: BRU-RAI-BRU | D61: 21MAR-25MAR | E61: 00245/03/2025 | F61: SMC | G61: HOT JUNIOR THIERRY | H61: DG | I61: REFUND : AVT 155700-1457000=100000 | J61: 315000 | K61: 0 | L61: 0 | M61: SATGURU | N61: ETKT 0473557685696 | O61: REFUND | P61: 0 | S61: 315000 | T61: =J61-P61-S61 | U61: 45745 | V61: CAISSE
A62: 45736 | B62: SA | C62: NSI-CPT-NSI | D62: 23MAR-27MAR | E62: 00246/03/2025 | F62: MR ONANA | G62: BELIBY MFOUMOU LYSETTE ESTHER | H62: DG | J62: 2315620 | K62: 1867120 | L62: =J62-K62 | M62: SATGURU | N62: ETKT 0713578264566 ETKT 0833578263203 | P62: 0 | S62: 2315620 | T62: =J62-P62-S62 | U62: 45772 | V62: CAISSE
A63: 45737 | B63: AF | C63: DLA-CDG | D63: 22MAR. | E63: 00247/03/2025 | F63: MR ONANA | G63: TIANI VESSAH OLIVIA BIBIANA TCHANGAIN | H63: DG | J63: 485800 | K63: 947000 | L63: =J63-K63 | M63: BLUEBERRY | N63: ETKT 0572333237640 | P63: 0 | S63: 485800 | T63: =J63-P63-S63 | U63: 45772 | V63: CAISSE
A64: 45738 | B64: ET | C64: DLA-DXB-DLA | D64: 01APR-08APR | E64: 00249/03/2025 | F64: MRS ELANGA | G64: ELANGA SOPPI EPSE EBOA GISELE | H64: DG | J64: 123900 | K64: 99900 | L64: =J64-K64 | M64: GOLITE | N64: ETKT 0719588273711 | O64: EXCHANGE | S64: 123900 | T64: =J64-P64-S64 | U64: 45800 | V64: CAISSE
A65: 45738 | B65: ET | C65: DLA-DXB-DLA | D65: 01APR-08APR | E65: 00249/03/2025 | F65: MRS ELANGA | G65: BOLANGA MOUDO JACQUELINE | H65: DG | J65: 123900 | K65: 99900 | L65: =J65-K65 | M65: GOLITE | N65: ETKT 0719588273710 | O65: EXCHANGE | S65: 123900 | T65: =J65-P65-S65 | U65: 45800 | V65: CAISSE
A66: 45738 | B66: ET | C66: DLA-DXB-DLA | D66: 01APR-08APR | E66: 00249/03/2025 | F66: MRS ELANGA | G66: EBOA ELANGA YANN ARTHUR | H66: DG | J66: 111900 | K66: 87600 | L66: =J66-K66 | M66: GOLITE | N66: ETKT 0719588273712 | O66: EXCHANGE | S66: 111900 | T66: =J66-P66-S66 | U66: 45800 | V66: CAISSE
A67: 45738 | B67: ET | C67: DLA-DXB-DLA | D67: 01APR-08APR | E67: 00249/03/2025 | F67: MRS ELANGA | G67: EBOA MATHEO WILFRIED | H67: DG | J67: 111900 | K67: 87600 | L67: =J67-K67 | M67: GOLITE | N67: ETKT 0719588273713 | O67: EXCHANGE | S67: 111900 | T67: =J67-P67-S67 | U67: 45800 | V67: CAISSE
A68: 45738 | B68: ET | C68: DLA-DXB-DLA | D68: 01MAR-14APR | E68: 00250/03/2025 | F68: MR TATIEZEU | G68: TATIEZEU GUEDIA BRUNO | H68: DG | J68: 99800 | K68: 67400 | L68: =J68-K68 | M68: GOLITE | N68: ETKT 0719588273714 | O68: EXCHANGE | P68: 0 | S68: 99800 | T68: =J68-P68-S68 | U68: 45923 | V68: CAISSE
A69: 45738 | B69: ET | C69: DLA-DXB-DLA | D69: 01MAR-14APR | E69: 00250/03/2025 | F69: MR TATIEZEU | G69: TSAFACK EPSE TATIEZEU ANNE CHANTAL | H69: DG | J69: 99800 | K69: 67400 | L69: =J69-K69 | M69: GOLITE | N69: ETKT 0719588273715 | O69: EXCHANGE | P69: 0 | S69: 99800 | T69: =J69-P69-S69 | U69: 45923 | V69: CAISSE
A70: 45738 | B70: QC | C70: DLA-NSI-DLA | D70: 24MAR-24MAR | E70: 00248/03/2025 | F70: APCAR | G70: MEDJOMEVA A EPSE TSITSOL NAOMIE MIRABELLE | H70: DG | I70: BILLET ENCORE OUVERT VALIDE 3 MOIS | J70: 105940 | K70: 89340 | L70: =J70-K70 | M70: KIU | N70: ETKT 0400300037057 | P70: 0 | S70: 105940 | T70: =J70-P70-S70 | U70: 45827 | V70: BANQUE | W70: CHQ8815128
A71: 45738 | B71: QC | C71: DLA-GOU-DLA | D71: 07MAY-12MAY | E71: 00251/03/2025 | F71: ZEBAZE DE ZEPIRO | G71: KANA/VICTOR | H71: DG | I71: 70440 | J71: 155940 | K71: 143540 | L71: =J71-K71 | M71: KIU | N71: ETKT 0400300037058 | P71: 0 | S71: 935650 | T71: =J71+J72+J73+J74+J75+J76-P71-S71 | U71: 45740 | V71: V/R
A72: 45738 | B72: QC | C72: DLA-GOU-DLA | D72: 07MAY-12MAY | E72: 00251/03/2025 | F72: ZEBAZE DE ZEPIRO | G72: OUAMBA TSAGUE/NADIA | H72: DG | I72: 70440 | J72: 155940 | K72: 143540 | L72: =J72-K72 | M72: KIU | N72: ETKT 0400300037059
A73: 45738 | B73: QC | C73: DLA-GOU-DLA | D73: 07MAY-12MAY | E73: 00251/03/2025 | F73: ZEBAZE DE ZEPIRO | G73: KEMENA NGUEKEU/HERVE | H73: DG | I73: 70440 | J73: 155940 | K73: 143540 | L73: =J73-K73 | M73: KIU | N73: ETKT 0400300037060
A74: 45738 | B74: QC | C74: DLA-GOU-DLA | D74: 07MAY-12MAY | E74: 00251/03/2025 | F74: ZEBAZE DE ZEPIRO | G74: ZAMBOU/PIERRE | H74: DG | I74: 71640 | J74: 155940 | K74: 150640 | L74: =J74-K74 | M74: KIU | N74: ETKT 0400300037061
A75: 45738 | B75: QC | C75: DLA-GOU-DLA | D75: 07MAY-12MAY | E75: 00251/03/2025 | F75: ZEBAZE DE ZEPIRO | G75: ZEBAZE DONFACK/PAULIN MARTIAL | H75: DG | I75: 71640 | J75: 155940 | K75: 150640 | L75: =J75-K75 | M75: KIU | N75: ETKT 0400300037062
A76: 45738 | B76: QC | C76: DLA-GOU-DLA | D76: 07MAY-12MAY | E76: 00251/03/2025 | F76: ZEBAZE DE ZEPIRO | G76: NTSAFACK/CLEMENT DANIEL | H76: DG | I76: 71640 | J76: 155940 | K76: 150640 | L76: =J76-K76 | M76: KIU | N76: ETKT 0400300037063
A77: 45741 | B77: KP | C77: DLA-ABJ-NSI | D77: 11MAY-13MAY | E77: 00255/03/2025 | F77: HARVEST | G77: KAMGAING TAASSI MARC ETIENNE | H77: DG | I77: 616000 | J77: 1126820 | K77: 1076820 | L77: =J77-K77 | M77: GOLITE | N77: ETKT 0329588273717 | O77: 4 | P77: 0 | S77: 1126820 | T77: =J77-P77-S77 | U77: 45769 | V77: V/R
A78: 45741 | B78: AF | C78: DLA-CDG-DLA | D78: 02APR-12APR | E78: 00254/03/2025 | F78: MR ONANA | G78: BIYAG ANTOINE ARMAND | H78: DG | I78: 1040300 | J78: 1676900 | K78: 1386120 | L78: =J78-K78 | M78: GOLITE | N78: ETKT 0579588273716 | O78: 2 | P78: 0 | S78: 1676900 | T78: =J78-P78-S78 | U78: 45772 | V78: CAISSE
A79: 45741 | B79: SA | C79: CPT-JNB | D79: 27MAR. | E79: 00252/03/2025 | F79: HORUS | G79: ONANA CYRILLE BERTRAND | H79: DG | J79: 135000 | K79: 10000 | L79: =J79-K79 | M79: SATGURU | N79: ETKT 0833576108216 | O79: EXCHANGE | S79: 135000 | T79: =J79-P79-S79 | U79: 45842 | V79: V/R
A80: 45741 | B80: SA | C80: CPT-JNB | D80: 27MAR. | E80: 00253/03/2025 | F80: ONANA | G80: BELIBY MFOUMOU LYSETTE ESTHER | H80: DG | J80: 135000 | K80: 10000 | L80: =J80-K80 | M80: SATGURU | N80: ETKT 0833578265427 | O80: EXCHANGE | P80: 0 | S80: 135000 | T80: =J80-P80-S80 | U80: 45833 | V80: CAISSE
A81: 45742 | B81: SN | C81: DLA-CDG | D81: 28MAY. | E81: 00256/03/2025 | F81: CABINET DENTAIRE G2 | G81: GAMGEM GUIADEM CATHERINE | H81: DG | J81: 198000 | K81: 164000 | L81: =J81-K81 | M81: SN | N81: ETKT 08230389682286 | O81: EXCHANGE | P81: 0 | S81: 198000 | T81: =J81-P81-S81 | U81: 45776 | V81: CAISSE
A82: 45743 | B82: SN-TP | C82: BRU-OPO-LIS-BRU | D82: 15JUL-17JUL-20JUL | E82: 00257/03/2025 | F82: SMC | G82: HOT JUNIOR THIERRY | H82: DG | J82: 941000 | K82: 741000 | L82: =J82-K82 | M82: BLUEBERRY | N82: ETKT 0823578264993 | P82: 0 | S82: 941000 | T82: =J82-P82-S82 | U82: 45745 | V82: CAISSE
A83: 45743 | B83: TK | C83: DLA-CDG-DLA | D83: 05APR-27APR | E83: 00261/03/2025 | F83: MR DJOFANG | G83: DJOFANG DARLY AYMAR | H83: DG | I83: 70000 | J83: 498900 | K83: 441720 | L83: =J83-K83 | M83: GOLITE | N83: ETKT 2359588273718 | O83: 2 | P83: 0 | S83: 498900 | T83: =J83-P83-S83 | U83: 45744 | V83: CAISSE
A84: 45743 | B84: QC | C84: DLA-NSI-DLA | D84: 28MAR-28MAR | E84: 00263/03/2025 | F84: CANAL+ | G84: MAKOUGANG BRIGITTE | H84: DG | I84: 36140 | J84: 116750 | K84: 97140 | L84: =J84-K84 | M84: KIU | N84: ETKT 0400300037066 | P84: 0 | S84: 116750 | T84: =J84-P84-S84 | U84: 45789 | V84: V/R
A85: 45743 | B85: QC | C85: DLA-BFX | D85: 29MAR. | E85: 00264/03/2025 | F85: TATA PASCALINE | G85: NINWOUO MAKOUTCHOUAN EPSE NKENFACK ZEBAZE SYLVIE PASCALINE | H85: DG | J85: 23000 | K85: 13000 | L85: =J85-K85 | M85: QC | N85: ETKT 0400300037056 | S85: 23000 | T85: =J85-P85-S85 | U85: 45750 | V85: CAISSE | W85: SOLDE
A86: 45744 | B86: TK | C86: IST-NSI | D86: 30MAR. | E86: 00270/03/2025 | F86: SAAR | G86: OWONO MESSI GUSTAVE MARIE | H86: DG | J86: 589000 | K86: 505300 | L86: =J86-K86 | M86: BLUEBERRY | N86: ETKT 2359588261510 | O86: EXCHANGE | P86: 0 | S86: 589000 | T86: =J86-P86-S86 | U86: 45916 | V86: V/R
A87: 45744 | B87: SN-UA | C87: MEM-DLA | D87: 05APR. | E87: 00265/03/2025 | F87: CAPTE | G87: DJEUGAP EPSE NTSAGUIM FERNANDE ALIENCE | H87: DG | J87: 213400 | K87: 98400 | L87: =J87-K87 | M87: GOLITE | N87: ETKT 0829588273720 | O87: EXCHANGE | P87: 0 | T87: =J87-P87-S87
A88: 45744 | B88: HF | C88: DLA-ABJ-DLA | D88: 03APR-08APR | E88: 00268/03/2025 | F88: MRS ESSO | G88: NGO BAYANAK EP ESSO BERNADETTE MARINA | H88: DG | I88: 86100 | J88: 475620 | K88: 435620 | L88: =J88-K88 | M88: GOLITE | N88: ETKT 4839588273721 | O88: 2 | P88: 175000 | Q88: 300000 | T88: =J88-P88-Q88-S88 | U88: 45763 | V88: CAISSE | W88: AVANCE
A89: 45744 | B89: AF | C89: DLA-CDG-DLA | D89: 05APR-12APR | E89: 00269/03/2025 | F89: CANAL+ | G89: MOUSSA ABBA | H89: DG | I89: 2078900 | J89: 2698980 | K89: 2424720 | L89: =J89-K89 | M89: GOLITE | N89: ETKT 0579588273722 | O89: 2 | P89: 0 | S89: 2698980 | T89: =J89-P89-S89 | U89: 45779 | V89: V/R
A90: 45744 | B90: QC | C90: MRV-DLA-MRV | D90: 03APR-14APR | F90: CANAL+ | G90: MOUSSA ABBA | H90: DG | I90: 74640 | J90: 200950 | K90: 169540 | L90: 31410 | M90: KIU | N90: ETKT 0400300037064 | T90: =J90-P90-S90
A91: 45744 | B91: SN | C91: BRU-DLA-BRU | D91: 14AUG-24AUG | E91: 00266/03/2025 | F91: SMC | G91: ETOGO ASSE FREDERIQUE ESTELLE | H91: DG | I91: 1851800 | J91: 2339980 | K91: 2258420 | L91: =J91-K91 | M91: NDC | N91: ETKT 0829049042148 | P91: 0 | S91: 2339980 | T91: =J91-P91-S91 | U91: 45745 | V91: CAISSE
A92: 45744 | B92: SN | C92: BRU-ABJ-BRU | D92: 21APR-24APR | E92: 00267/03/2025 | F92: SMC | G92: BABISSAGANA EMMANUEL NOEL | H92: DG | I92: 755100 | J92: 1021800 | K92: 941100 | L92: =J92-K92 | M92: NDC | N92: ETKT 0829049042149 | P92: 0 | S92: 1021800 | T92: =J92-P92-S92 | U92: 45745 | V92: CAISSE
A93: 45745 | B93: WB | C93: BGF-DLA | D93: 01MAR. | E93: 00272/03/2025 | F93: CANAL+ | G93: DEBOMBO MARTIAL JUNIOR | H93: DG | J93: 304980 | K93: 257980 | L93: =J93-K93 | M93: BLUEBERRY | N93: ETKT 4599588261513 | O93: 1 | P93: 0 | S93: 304980 | T93: =J93-P93-S93 | U93: 45768 | V93: V/R
A94: 45745 | B94: KP | C94: NSI-BGF | D94: 04MAR. | E94: 00274/03/2025-00288/04/2025 | F94: CANAL+ | G94: DEBOMBO MARTIAL JUNIOR | H94: DG | I94: REFUND 472980-304980=168000 | J94: 95800 | K94: 43400 | L94: =J94-K94 | M94: BLUEBERRY | N94: ETKT 0329588261512 | O94: REFUND | P94: 0 | S94: 95800 | T94: =J94-P94-S94 | U94: 45768 | V94: V/R
A95: 45745 | B95: KP | C95: LFW-LBV | D95: 02APR. | E95: 00274/03/2025 | F95: CANAL+ | G95: ALBACHIR ABDEL AZIZ MAHAMAT | H95: DG | J95: 438980 | K95: 245292 | L95: =J95-K95 | M95: BLUEBERRY | N95: ETKT 0329588261514 | O95: 1 | P95: 0 | S95: 438980 | T95: =J95-P95-S95 | U95: 45768 | V95: V/R
A96: 45745 | B96: KP | C96: NSI-NDJ | D96: 04APR. | E96: 00274/03/2025 | F96: CANAL+ | G96: ALBACHIR ABDEL AZIZ MAHAMAT | H96: DG | J96: 420000 | K96: 234775 | L96: =J96-K96 | M96: BLUEBERRY | N96: ETKT 0329588261515 | O96: 1 | P96: 0 | S96: 420000 | T96: =J96-P96-S96 | U96: 45768 | V96: V/R
A97: 45745 | B97: J7 | C97: LBV-NSI | D97: 02APR. | E97: 00275/03/2025 | F97: CANAL+ | G97: ALBACHIR ABDEL AZIZ MAHAMAT | H97: DG | J97: 362980 | K97: 294400 | L97: =J97-K97 | M97: J7 | N97: ETKT 2770046551229 | P97: 0 | S97: 362980 | T97: =J97-P97-S97 | U97: 45768 | V97: V/R
A98: 45745 | B98: QC | C98: DLA-NSI | D98: 03MAR. | E98: 00273/03/2025 | F98: CANAL+ | G98: DEBOMBO MARTIAL JUNIOR | H98: DG | I98: REFUND INTEGRALLE (70980-41870 =29110 | J98: 0 | K98: 0 | L98: =J98-K98 | M98: KIU | N98: ETKT 0400300037067 | O98: REFUND | P98: 0 | T98: =J98-P98-S98
A99: 45745 | B99: ET | C99: IAD-DLA | D99: 30MAR. | E99: 00271/03/2025 | F99: NGC | G99: SIMO ELISE | H99: MR LUCIEN | I99: 284800 | J99: 567900 | K99: 507400 | L99: =J99-K99 | M99: B2B | N99: ETKT 0712151610310 | P99: 0 | S99: 567900 | T99: =J99-P99-S99 | U99: 45754 | V99: CAISSE
A100: 45745 | F100: CANAL+ | G100: 3 PERSONNES | H100: DG | J100: 1400000 | K100: 1300000 | L100: =J100-K100 | O100: CONSIEGERIE | P100: 0 | S100: 1400000 | T100: =J100-P100-S100 | U100: 45748 | V100: V/R
...

Sheet APRIL
A1: DATE | B1: CIES | C1: PARCOURS | D1: TRAVEL DATE | E1: N FACTURE | F1: ENTREPRISE | G1: NOMS/PRENOMS | H1: APPORTEUR | I1: TARIF HT | J1: TC | K1: TM | L1: FS | M1: LIEU ACHAT | N1: NUMERO DU BILLET | O1: NBRE SGTS | P1: AVANCE 01 | Q1: AVANCE 02 | R1: AVANCE 03 | S1: RGLT | T1: SOLDE | U1: DATE REGLT | V1: MODE RGLT | W1: DELAIS | X1: TMG | Y1: OV GOLITE | Z1: GOLITE | AA1: ECART | AB1: VU | AC1: DATE/HEUR
A2: 45748 | B2: QC | C2: DLA-NSI | D2: 01APR. | E2: 00287/04/2025 | F2: CANAL+ | G2: HUGUES YANNICK, TA BI TAH | H2: DG | I2: 21070 | J2: 76980 | K2: 66870 | L2: =J2-K2 | M2: KIU | N2: ETKT 0400300037068 | S2: 76980 | T2: =J2-P2-S2 | U2: 45779 | V2: V/R | X2: 0 | AC2: 228803
A3: 45748 | B3: QC | C3: DLA-NSI-DLA | D3: 03APR-04APR | E3: 00285/04/2025 | F3: CANAL+ | G3: DEBOMBO MARTIAL JUNIOR | H3: DG | J3: 138970 | K3: 83670 | L3: =J3-K3 | M3: QC | N3: ETKT 0400200535091 | O3: EXCHANGE | S3: 138970 | T3: =J3-P3-S3 | U3: 45768 | V3: V/R | X3: 0 | Z3: 1771550
A4: 45748 | B4: WB | C4: DLA-BGF | D4: 04APR. | E4: 00286/04/2025 | F4: CANAL+ | G4: DEBOMBO MARTIAL JUNIOR | H4: DG | I4: 120300 | J4: 320980 | K4: 254955 | L4: =J4-K4 | M4: GOLITE | N4: ETKT 4599588273727 | O4: 1 | S4: 320980 | T4: =J4-P4-S4 | U4: 45768 | V4: V/R | X4: =K4 | Y4: 6000000 | Z4: =Z3+Y4-X4 | AB4: 7771550 | AC4: 0
A5: 45749 | B5: AF | C5: DLA-CDG-DLA | D5: 05APR-12APR | E5: 00290/04/2025 | F5: CANAL+ | G5: KAMDEM KONMOGNE NASSER | H5: DG | I5: 2302100 | J5: 2698980 | K5: 2647920 | L5: =J5-K5 | M5: GOLITE | N5: ETKT 0579588273728 | O5: 2 | S5: 2698900 | T5: =J5-P5-S5 | U5: 45779 | V5: V/R | X5: =K5 | Z5: =Z4-X5 | AB5: 4607930
A6: 45749 | B6: SN | C6: BRU-OUA-BRU | D6: 17DEC-30DEC | E6: 00289/04/2025 | F6: SMC | G6: BARRY YACINE RAISSA | H6: DG | I6: 347700 | J6: 575700 | K6: 515700 | L6: =J6-K6 | M6: NDC | N6: ETKT 0829049042850 | P6: 575700 | T6: =J6-P6-S6 | X6: =K6 | Z6: =Z5-X6 | AB6: 4607930
A7: 45749 | B7: SN | C7: BRU-ABJ-BRU | D7: 23MAY-31MAY | E7: EN ATTENTE DE SURCLASSEMENT PAR SN BRUSSEL | F7: SMC | G7: HOT TIERRRY JUNIOR | H7: DG | J7: 179100 | K7: 129100 | L7: =J7-K7 | M7: SN | N7: ETKT 0822301014206 | O7: EXCHANGE | T7: =J7-P7-S7 | X7: 0 | Z7: =Z6-X7
A8: 45750 | B8: AF | C8: DLA-BQC-DLA | D8: 07APR-21APR | E8: 00277/04/2025 | F8: HOD INVESTMENT | G8: NGANI MEIGNIDON DIFFO, MIRELLE NICAISE ELIS | H8: DG | J8: 1798800 | K8: 1741120 | L8: =J8-K8 | M8: GOLITE | N8: ETKT 0579588273729-730 | O8: 6 | S8: 1798800 | T8: =J8-P8-S8 | U8: 45756 | V8: V/R | X8: =K8 | Z8: =Z7-X8
A9: 45750 | B9: KQ | C9: DLA-DBX | D9: 22APR. | E9: 00291/04/2025 | F9: MRS MAFFO | G9: MAFFO NDE TATSING, GERMAINE | H9: MR LUCIEN | J9: 282000 | K9: 262920 | L9: =J9-K9 | M9: GOLITE | N9: ETKT 7069588273731 | O9: 2 | S9: 282000 | T9: =J9-P9-S9 | U9: 45750 | V9: CAISSE | X9: =K9 | Z9: =Z8-X9 | AB9: 570050
A10: 45750 | B10: QC | C10: NSI-DLA | D10: 03APR. | E10: 00292/04/2025 | F10: BANGE BANK | G10: EKIRI MBANG MIGUEL JESUS | H10: DG | J10: 116700 | K10: 86670 | L10: =J10-K10 | M10: QC | N10: ETKT 0400200533681 | S10: 347402 | T10: =J10+J11+J12-P10-S10 | U10: 45779 | V10: V/R | X10: 0 | Z10: =Z9-X10
A11: 45750 | B11: QC | C11: NSI-DLA | D11: 03APR. | E11: 00292/04/2025 | F11: BANGE BANK | G11: GARRIGA OBIANG TEODORO ALBERTO | H11: DG | J11: 116700 | K11: 86670 | L11: =J11-K11 | M11: QC | N11: ETKT 0400200533682 | X11: 0 | Z11: =Z10-X11
A12: 45750 | B12: QC | C12: NSI-DLA | D12: 03APR. | E12: 00292/04/2025 | F12: BANGE BANK | G12: TNUG OBONO JACINTO NGUEMA | H12: DG | J12: 116700 | K12: 91670 | L12: =J12-K12 | M12: QC | N12: ETKT 0400200533683 | X12: 0 | Z12: =Z11-X12
A13: 45751 | B13: KP | C13: DLA-LFW-DLA | D13: 06JUL-11JUL | E13: 00294/04/2025 | F13: MRS GUIFO | G13: GUIFO AURELIE NICOLE | H13: DG | I13: 153900 | J13: 458920 | K13: 406120 | L13: =J13-K13 | M13: GOLITE | N13: ETKT 0329588273732 | O13: 2 | S13: 458920 | T13: =J13-P13-S13 | U13: 45777 | V13: CAISSE | W13: 45797 | X13: =K13 | Z13: =Z12-X13
A14: 45751 | B14: KQ | C14: DLA-CPT-DLA | D14: 06APR-10APR | E14: 00293/04/2025 | F14: MR DONGHO | G14: DONGHO DONGMO, THIERRY | H14: MR STEPHANE | J14: 1762720 | K14: 1627720 | L14: =J14-K14 | M14: AMADEUS | N14: ETKT 706 6376915934 | S14: 2075000 | T14: =J14+J15-S14 | U14: 45751 | V14: CAISSE | X14: =K14 | Z14: =Z13-X14
A15: 45751 | B15: SA | C15: JNB-CPT-JNB | D15: 07APR-10APR | E15: 00293/04/2025 | F15: MR DONGHO | G15: DONGHO DONGMO, THIERRY | H15: MR STEPHANE | J15: 312180 | K15: 296700 | L15: =J15-K15 | M15: SATGURU | N15: ETKT 0836376915807 | X15: 0 | Z15: =Z14-X15 | AA15: 254995 | AB15: 570050
A16: 45751 | B16: KP | C16: DLA-ABJ-NSI | D16: 10MAY-13MAY | E16: 00295/04/2025 | F16: HARVEST | G16: KAMGAING TAASSI MARC ETIENNE | H16: DG | J16: 213000 | K16: 204000 | L16: =J16-K16 | M16: GOLITE | N16: ETKT 0329588273733 | O16: EXCHANGE | S16: 213000 | T16: =J16-P16-S16 | U16: 45779 | V16: V/R | X16: 204000 | Z16: =Z15-X16 | AA16: =AB16-Z16 | AB16: 366050
A17: 45755 | B17: JL | C17: LHR-HND | D17: 16APR. | E17: 00279/04/2025 | F17: PIVOTAL AFRICA NETWORK | G17: HOT THIERRY JUNIOR | H17: DG | J17: 5785800 | K17: 5492800 | L17: =J17-K17 | M17: BLUEBERRY | N17: ETKT 1692820683897 | T17: =J17-P17-S17
A18: 45755 | B18: AF | C18: DEL-IAD-ABJ | D18: 23APR-27APR | E18: 00283/04/2025 | F18: PIVOTAL AFRICA NETWORK | G18: ACOUETEY KANGNI DIDIER | H18: DG | J18: 11040800 | K18: 10939200 | L18: =J18-K18 | M18: BLUEBERRY | N18: ETKT 0576376915564 | T18: =J18-P18-S18
A19: 45755 | B19: ET | C19: DLA-COO | D19: 08MAY. | E19: 00284/04/2025 | F19: PIVOTAL AFRICA NETWORK | G19: HOT THIERRY JUNIOR | H19: DG | I19: 690900-620920=69980 | J19: 159473 | K19: 49473 | L19: =J19-K19 | M19: BLUEBERRY | N19: ETKT 0716376915537 | O19: REFUND | T19: =J19-P19-S19
A20: 45755 | B20: HF | C20: COO-ABJ | D20: 10MAY. | E20: 00284/04/2025 | F20: PIVOTAL AFRICA NETWORK | G20: HOT THIERRY JUNIOR | H20: DG | I20: 938700-843700=95000 | J20: 169472 | K20: 50000 | L20: =J20-K20 | M20: BLUEBERRY | N20: ETKT 4836376915538 | O20: REFUND | T20: =J20-P20-S20
A21: 45755 | B21: AF | C21: ABJ-CDG | D21: 14APR. | E21: 00278/04/2025 | F21: PIVOTAL AFRICA NETWORK | G21: HOT THIERRY JUNIOR | H21: DG | J21: 2857500 | K21: 2734100 | L21: =J21-K21 | M21: BLUEBERRY | N21: ETKT 0576376915531 | T21: =J21-P21-S21
A22: 45755 | B22: AF | C22: HND-CDG-NKC | D22: 20APR. | E22: 00282/04/2025 | F22: PIVOTAL AFRICA NETWORK | G22: TAH SIDI | H22: DG | I22: 3551900-3461900=90000 | J22: 335800 | K22: 0 | L22: =J22-K22 | M22: BLUEBERRY | N22: ETKT 0576776915528 | O22: REFUND | T22: =J22-P22-S22
A23: 45755 | B23: JL | C23: LHR-HND | D23: 16APR. | E23: 00281/04/2025 | F23: PIVOTAL AFRICA NETWORK | G23: TAH SIDI | H23: DG | J23: 5785800 | K23: 5492800 | L23: =J23-K23 | M23: BLUEBERRY | N23: ETKT 1692820683885 | T23: =J23-P23-S23
A24: 45755 | B24: AF | C24: HND-CDG-ZYR | D24: 20APR. | E24: 00280/04/2025 | F24: PIVOTAL AFRICA NETWORK | G24: HOT THIERRY JUNIOR | H24: DG | J24: 3277500 | K24: 3187500 | L24: =J24-K24 | M24: BLUEBERRY | N24: ETKT 0576376915529 | T24: =J24-P24-S24 | Y24: 10000000 | Z24: 10366050 | AB24: 10366050
A25: 45755 | B25: ET | C25: DLA-CAN-DLA | D25: 10APR-01MAY | E25: 00299/04/2025 | F25: NGC | G25: ANTHONIA MESEH EPSE MBAKOP/XXX MRS | H25: MR LUCIEN | I25: 457600 | J25: 894900 | K25: 839420 | L25: =J25-K25 | M25: ET | N25: ETKT 0712151802925 | P25: 200000 | S25: 694900 | T25: =J25-P25-S25 | U25: 21/04/2025 23/04/2025 | V25: CAISSE | X25: 0 | AB25: 10366050
A26: 45755 | B26: AT | C26: NSI-YUL-NSI | D26: 08JUL-22AUG | E26: 00298/04/2025 | F26: MR HILAIRE | G26: VOUFFO TOUTSOP EP TAKOUEZIM, JOSEPHINE | H26: DG | I26: 351000 | J26: 823980 | K26: 786020 | L26: =J26-K26 | M26: GOLITE | N26: ETKT 1479588273736 | O26: 4 | S26: 823920 | T26: =J26-P26-S26 | U26: 45754 | V26: V/R | X26: =K26 | AB26: =AB25-X26
A27: 45755 | B27: TK | C27: DLA-HAJ | D27: 10APR. | E27: 00296/04/2025 | F27: MR LOUIS | G27: DJOMY TCHOUABIA/FLORIS JOSY MRS | H27: DG | I27: 277400 | J27: 555920 | K27: 494120 | L27: =J27-K27 | M27: GOLITE | N27: ETKT 2359588273735 | O27: 2 | P27: 551000 | T27: =J27-P27-S27 | U27: 45755 | V27: CAISSE | X27: =K27 | AB27: =#REF!-X27
A28: 45755 | B28: AF | C28: DLA-CDG-DLA | D28: 10APR-09MAY | E28: 00297/04/2025 | F28: MR TCHATUE | G28: SONE EKOLO, XAVIER YANNICK BENJAMIN | H28: DG | I28: 353200 | J28: 709800 | K28: 668420 | L28: =J28-K28 | M28: GOLITE | N28: ETKT 0579588273734 | O28: 2 | P28: 755000 | S28: 200000 | T28: =J28+J29-P28-S28 | U28: 45757 | V28: OM CAISSE | X28: =K28 | AB28: =AB27-X28
A29: 45756 | B29: AF | C29: DLA-CDG-DLA | D29: 16APR-09MAY | E29: 00303/04/2025 | F29: MR TCHATUE | G29: SONE EKOLO, XAVIER YANNICK BENJAMIN | H29: DG | I29: 0 | J29: 249800 | K29: 199100 | L29: =J29-K29 | M29: GOLITE | N29: ETKT 0579588273739 | O29: EXCHANGE | U29: 45758 | X29: =K29 | Z29: 5191540 | AB29: =AB27-X29 | AC29: 10042025T0840
A30: 45756 | B30: AF | C30: DLA-CDG-DLA | D30: 20APR-05JUL | E30: 00300/04/2025 | F30: MRS MOKAM | G30: MOKAM EPSE KAMGA, MARIE GISELE MRS | H30: MME HEUNA | I30: 519600 | J30: 862800 | K30: 827820 | L30: =J30-K30 | M30: GOLITE | N30: ETKT 0579588273737 | O30: 2 | S30: 862800 | T30: =J30-P30-S30 | U30: 45756 | V30: CAISSE | X30: =K30 | AB30: =AB27-X30
A31: 45756 | B31: AF | C31: NSI-CDG-NSI | D31: 13APR-18APR | E31: 00301/04/2025 | F31: SMC | G31: ETOUNDI BIYIDI, SIMON PIERRE | H31: DG | I31: 353200 | J31: 725820 | K31: 661420 | L31: =J31-K31 | M31: GOLITE | N31: ETKT 0579588273738 | O31: 2 | T31: =J31-P31-Q31-R31-S31 | X31: =K31 | AB31: =AB30-X31
A32: 45756 | B32: ET | C32: DLA-CAN-DLA | D32: 15APR-21APR | E32: 00302/04/2025 | F32: NGC | G32: OZIOKO/PASCHAL EMEKA | H32: MR LUCIEN | I32: 457600 | J32: 907900 | K32: 852620 | L32: =J32-K32 | M32: ET | N32: ETKT 0712151831577 | S32: 907900 | T32: =J32-P32-S32 | U32: 45770 | V32: CAISSE | X32: 0 | AB32: =AB31-X32
A33: 45756 | B33: ET | C33: DLA-NDJ-DLA | D33: 10APR-13APR | E33: 00304/04/2025 | F33: KAGOU | G33: KAGOU GEORGES LEOPOLD | H33: DG | J33: 809805 | K33: 768805 | L33: =J33-K33 | M33: AMADEUS | N33: ETKT 0716376917938 | S33: 809805 | T33: =J33-P33-Q33-R33-S33 | U33: 45763 | V33: CAISSE | X33: =K33 | AB33: =AB32-X33
A34: 45756 | B34: ET | C34: DLA-NDJ-DLA | D34: 10APR-13APR | E34: 00305/04/2025 | F34: KAGOU | G34: DJUIKOUO JOSEPHINE | H34: DG | J34: 809805 | K34: 768805 | L34: =J34-K34 | M34: AMADEUS | N34: ETKT 0716376917936 | S34: 809805 | T34: =J34-P34-Q34-R34-S34 | U34: 45763 | V34: CAISSE | X34: =K34 | AB34: =AB33-X34
A35: 45756 | B35: ET | C35: DLA-CAN-DLA | D35: 14APR-03MAY | E35: 00308/04/2025 | F35: MME CHIMENE | G35: MARTIAL TCHOUALA NDZE | H35: DG | J35: 885900 | K35: 857420 | L35: =J35-K35 | M35: B2B | N35: ETKT 0712151861118 | S35: 885900 | T35: =J35-P35-Q35-R35-S35 | U35: 45756 | V35: CAISSE | X35: 0 | AB35: =AB34-X35
A36: 45756 | B36: ET | C36: DLA-CAN-DLA | D36: 14APR-03MAY | E36: 00308/04/2025 | F36: MME CHIMENE | G36: CHIMENE NZAMESSHA NDZE EPSE YOMI | H36: DG | J36: 885900 | K36: 857420 | L36: =J36-K36 | M36: B2B | N36: ETKT 0712151861120 | S36: 885900 | T36: =J36-P36-Q36-R36-S36 | U36: 45756 | V36: CAISSE | X36: 0 | AB36: =AB35-X36
A37: 45756 | B37: ET | C37: DLA-CAN-DLA | D37: 14APR-03MAY | E37: 00308/2025 | F37: MME CHIMENE | G37: JEAN JACQUES TALONPA NZOULEWA | H37: DG | J37: 885900 | K37: 857420 | L37: =J37-K37 | M37: B2B | N37: ETKT 0712151861121 | S37: 885900 | T37: =J37-P37-Q37-R37-S37 | U37: 45792 | V37: CAISSE | X37: 0 | AB37: =AB36-X37
A38: 45757 | B38: AF | C38: CDG-JFK-CDG | D38: 21APR-26APR | E38: 00307/04/2025 | F38: HARVEST | G38: MARC KAMGAING | H38: DG | J38: 4556900 | K38: 4369100 | L38: =J38-K38 | M38: AF | N38: ETKT 0572334342393 | S38: 4556900 | T38: =J38-P38-S38 | U38: 45779 | V38: V/R | X38: 0 | AB38: =#REF!-X38
A39: 45757 | B39: AF | C39: CDG-JFK-CDG | D39: 21APR-26APR | E39: 00307/04/2025 | F39: HARVEST | G39: MAYLEE KAMGAING | H39: DG | J39: 1140600 | K39: 1086600 | L39: =J39-K39 | M39: AF | N39: ETKT 0572334342392 | S39: 1140600 | T39: =J39-P39-S39 | U39: 45779 | V39: V/R | X39: 0 | AB39: =AB38-X39
A40: 45757 | B40: AF | C40: CDG-JFK-CDG | D40: 21APR-26APR | E40: 00307/04/2025 | F40: HARVEST | G40: MAYANE KAMGAING | H40: DG | J40: 1140600 | K40: 1086600 | L40: =J40-K40 | M40: AF | N40: ETKT 0572334342391 | S40: 1140600 | T40: =J40-P40-S40 | U40: 45779 | V40: V/R | X40: 0 | AB40: =AB39-X40
A41: 45757 | B41: HF | C41: DLA-ABJ–DSS–DLA | D41: 13APR–18APR–20APR | E41: 00306/04/2025 | F41: NEO INDUSTRIE | G41: BOOG/SAMUEL DIEUDONNE | H41: DG | I41: 1379300 | J41: 2180980 | K41: 1788220 | L41: =J41-K41 | M41: GOLITE | N41: ETKT 4839588273740 | O41: 4 | S41: 2180980 | T41: =J41-P41-S41 | U41: 45768 | V41: V/R | X41: 1788220 | AB41: =AB40-X41
A42: 45757 | B42: HF | C42: DLA-ABJ–DSS–DLA | D42: 13APR–18APR–20APR | E42: 00306/04/2025 | F42: NEO INDUSTRIE | G42: BOUNKEU/CHANTAL | H42: DG | I42: 1379300 | J42: 2180980 | K42: 1788220 | L42: =J42-K42 | M42: GOLITE | N42: ETKT 4839588273741 | O42: 4 | S42: 2180980 | T42: =J42-P42-S42 | U42: 45768 | V42: V/R | X42: 1788220 | Z42: 1615100 | AB42: =AB41-X42
A43: 45757 | B43: AF | C43: CDG – DLA – CDG | D43: 14 APR – 25 MAY | E43: 00309/04/2025 | F43: MME FRANCOISE | G43: MAURICE GILBERT NANFAH TADOUGA | H43: DG | J43: 738720 | K43: 681520 | L43: =J43-K43 | M43: AF | N43: ETKT 0572334342412 | P43: 500000 | S43: 238720 | T43: =J43-P43-S43 | U43: 10/04/2025 14/04/2025 | V43: CAISSE | X43: 0 | Y43: 5000000 | Z43: 6615100 | AB43: =AB42-X43+Y43 | AC43: 11042025T0610
A44: 45758 | B44: ET | F44: CANAL+ | G44: TAMBA | H44: DG | J44: 0 | K44: 435620 | L44: 0 | M44: GOLITE | N44: ETKT 4839588273743 | O44: VOIDER | T44: =J44-P44-S44 | X44: 435620 | AB44: =AB43-X44+Y44
A45: 45758 | B45: SN | C45: DLA-NCE.CDG-DLA | D45: 03JUN-31AUG | E45: 00310/04/2025 | F45: AGV GODWIN TRAVEL | G45: .NDONGUE EPSE ESSO | H45: MME HEUNA | J45: 594420 | K45: 591920 | L45: =J45-K45 | M45: AMADEUS | N45: ETKT 082 6376919343-4 | S45: 594500 | T45: =J45-P45-S45 | U45: 45757 | V45: CAISSE | X45: =K45 | AB45: =AB44-X45+Y45 | AC45: 0
A46: 45758 | B46: KP | C46: DLA-LFW-DLA | D46: 26APR-03MAY | E46: 00311/04/2025 | F46: CANAL+ | G46: YOKOR EPSE GNABA, KOSSIWAVI | H46: DG | I46: 174000 | J46: 506920 | K46: 426820 | L46: =J46-K46 | M46: GOLITE | N46: ETKT 0329588273742 | O46: 2 | S46: 506920 | T46: =J46-P46-S46 | U46: 45789 | V46: V/R | X46: =K46 | Z46: 5160740 | AB46: =AB45-X46+Y46 | AC46: 11042025T1503
A47: 45758 | B47: HF | C47: DLA-DSS | D47: 14APR. | E47: 00312/04/2025 | F47: MR KAGOU | G47: TONDJA NDAFEUT/YANNICK SANDRINE | H47: DG | I47: 309600 | J47: 568620 | K47: 485620 | L47: =J47-K47 | M47: GOLITE | N47: ETKT 4839588273744 | O47: 1 | T47: =J47-P47-S47 | X47: =K47 | Z47: 4675120 | AB47: =AB46-X47+Y47 | AC47: 12042025T0620
A48: 45759 | B48: SN | C48: DLA-CDG-DLA | D48: 03JUL-27SEP | E48: 00313/04/2025 | F48: MME MOMO | G48: MOMO EPSE NOUNI TAMEZE JEANNE | H48: MME LAURE | I48: 280300 | J48: 587920 | K48: 542320 | L48: =J48-K48 | M48: NDC | N48: ETKT 0829049042851 | S48: 584920 | T48: =J48-P48-S48 | U48: 45761 | V48: CAISSE | X48: =K48 | Z48: 4132800 | AB48: =AB47-X48+Y48 | AC48: 12042025T2104
A49: 45761 | B49: EY | C49: NRT-RUH | D49: 19APR. | E49: 00314/04/2025 | F49: PIVOTAL AFRICA NETWORK | G49: TAH SIDI | H49: DG | K49: 4272661 | M49: BLUEBERRY | N49: ETKT 6076075460877 | O49: VOIDER | T49: =J49-P49-S49 | X49: 0 | AB49: =AB48-X49+Y49
A50: 45761 | B50: KP | C50: DLA-COO-DLA | D50: 15APR-17APR | E50: 00317/04/2025 | F50: BANGE BANK | G50: ESONO OYANA/ANGELICA MONAYONG MRS | H50: DG | I50: 254600 | J50: 760950 | K50: 681220 | L50: =J50-K50 | M50: GOLITE | N50: ETKT 0329588273745 | O50: 4 | S50: 757352 | T50: =J50-P50-S50 | U50: 45789 | V50: V/R | W50: 15276 | X50: =K50 | Z50: 4568420 | AA50: 435620 | AB50: =AB49-X50+Y50+AA50 | AC50: 14042025T0808
A51: 45761 | B51: SN | C51: NSI-YOW | D51: 04JUN. | E51: 00316/04/2025 | F51: MR FESSI | G51: FESSI FRANCIS ROMEO | H51: MME HEUNA | J51: 615820 | K51: 613320 | L51: =J51-K51 | M51: AMADEUS | N51: ETKT 0826376921089 | S51: 615820 | T51: =J51-P51-S51 | U51: 45761 | V51: CAISSE | X51: =K51 | AB51: =AB50-X51+Y51
A52: 45761 | B52: SN | C52: NSI-YOW | D52: 04JUN. | E52: 00316/04/2025 | F52: MR FESSI | G52: FESSI BISSA / AMANDA HILARY | H52: MME HEUNA | J52: 527720 | K52: 525220 | L52: =J52-K52 | M52: AMADEUS | N52: ETKT 0826376921090 | S52: 527720 | T52: =J52-P52-S52 | U52: 45761 | V52: CAISSE | X52: =K52 | Z52: 2748660 | AB52: =AB51-X52+Y52+AA52 | AC52: 14042025T1915
A53: 45761 | B53: ET | C53: DLA-SSG | D53: 15APR. | E53: 00318/04/2025 | F53: BANGE BANK | G53: MR BONAVENTURE/MVONDO ASSAM | H53: DG | I53: 990800 | J53: 1452980 | K53: 1351955 | L53: =J53-K53 | M53: GOLITE | N53: ETKT 0719588273746 | O53: 1 | S53: 1448482 | T53: =J53-P53-S53 | U53: 45779 | V53: V/R | X53: =K53 | AB53: =AB52-X53+Y53+AA53
A54: 45761 | B54: ET | C54: DLA-SSG | D54: 15APR. | E54: 00319/04/2025 | F54: BANGE BANK | G54: ESSISSIMA, PASCAL HERVE MR | H54: DG | I54: 165700 | J54: 383980 | K54: 303455 | L54: =J54-K54 | M54: GOLITE | N54: ETKT 0719588273747 | O54: 1 | S54: 382182 | T54: =J54-P54-S54 | U54: 45779 | V54: V/R | X54: =K54 | AB54: =AB53-X54+Y54+AA54 | AE54: 1228803
A55: 45761 | B55: QC | C55: NSI-DLA | D55: 14APR. | E55: 00320/04/2025 | F55: BANGE BANK | G55: MR BONAVENTURE/MVONDO ASSAM | H55: DG | I55: 26370 | J55: 119700 | K55: 99770 | L55: =J55-K55 | M55: KIU | N55: ETKT 0400300037070 | S55: 237602 | T55: =J55+J56-P55-S55 | U55: 45779 | V55: V/R | X55: 0 | Z55: 1093250 | AB55: =AB54-X55+Y55+AA55 | AD55: 99770 | AE55: =AE54-AD55
A56: 45761 | B56: QC | C56: NSI-DLA | D56: 14APR. | E56: 00320/04/2025 | F56: BANGE BANK | G56: OBIANG NCHAMA, JOSE MIGUEL MR | H56: DG | I56: 26370 | J56: 119700 | K56: 99770 | L56: =J56-K56 | M56: KIU | N56: ETKT 0400300037071 | O56: NOT USE | X56: 0 | AB56: =AB55-X56+Y56+AA56 | AD56: 99770 | AE56: =AE55-AD56 | AF56: 1029263
A57: 45761 | B57: AF | C57: HND-ABJ | D57: 19APR. | E57: 00315/04/2025 | F57: PIVOTAL AFRICA NETWORK | G57: HOT THIERRY JUNIOR | H57: DG | J57: 388100 | K57: 283100 | L57: =J57-K57 | M57: BLUEBERRY | N57: ETKT 0576376918170 | O57: EXCHANGE | T57: =J57-P57-S57 | X57: 0 | AB57: =AB56-X57+Y57+AA57 | AE57: =AE56-AD57
A58: 45762 | B58: WB | C58: DLA-BGF-DLA | D58: 22APR-25APR | F58: AFG | G58: FOTADZONG TCHIO/THEOPHILE MR | H58: DG | I58: 338100 | J58: 691720 | K58: 611955 | L58: =J58-K58 | M58: GOLITE | N58: ETKT 4599588273748 | O58: 2 | S58: 691720 | T58: =J58-P58-S58 | U58: 45789 | V58: BANQUE | W58: CHQ 2342423 | X58: =K58 | Y58: 30000000 | Z58: 30481295 | AB58: =AB57-X58+Y58+AA58 | AC58: 15042025T1122 | AE58: =AE57-AD58
A59: 45762 | B59: KP | C59: SSG-NSI | D59: 19APR. | E59: 00324/04/2025 | F59: BANGE BANK | G59: ESSISSIMA/PASCAL HERVE MR | H59: DG | I59: 114200 | J59: 280920 | K59: 201900 | L59: =J59-K59 | M59: GOLITE | N59: ETKT 0329588273749 | O59: 1 | S59: 279122 | T59: =J59-P59-S59 | U59: 45779 | V59: V/R | X59: =K59 | AB59: =AB58-X59+Y59+AA59 | AE59: =AE58-AD59
A60: 45762 | C60: ABJ-BRU | D60: 21APR. | F60: PIVOTAL AFRICA NETWORK | G60: HOT THIERRY JUNIOR | H60: DG | I60: 2077800-1957600=120200 | J60: 330800 | K60: 190800 | L60: =J60-K60 | M60: NDC | N60: ETKT 0829049042852 | O60: REFUND | T60: =J60-P60-S60 | W60: 1766822 | X60: =K60 | AA60: -1766820 | AB60: =AB59-X60+Y60+AA60 | AE60: =AE59-AD60
A61: 45762 | B61: SN | C61: CDG-DLA | D61: 18AUG. | F61: MME GUIFO | G61: GUIFO TAGNE/KAIS PHILIPPE | H61: DG | I61: 152200 | J61: 375900 | K61: 256200 | L61: =J61-K61 | M61: NDC | N61: ETKT 0829049042853 | P61: 241080 | S61: 134820 | T61: =J61-P61-S61 | U61: 30/04/2025 22/05/2025 | V61: CAISSE | W61: 45797 | X61: =K61 | AB61: =AB60-X61+Y61+AA61 | AE61: =AE60-AD61
A62: 45762 | B62: ET | C62: DLA-BRU | D62: 22JUL. | F62: MME GUIFO | G62: GUIFO TAGNE/KAIS PHILIPPE | H62: DG | J62: 429700 | K62: 351320 | L62: =J62-K62 | M62: BLUEBERRY | N62: ETKT 0719588261538 | S62: 429700 | T62: =J62-P62-S62 | U62: 45799 | V62: CAISSE | X62: 0 | AB62: =AB61-X62+Y62+AA62 | AE62: =AE61-AD62
A63: 45762 | B63: AT | C63: CMN-DLA | D63: 16APR. | E63: 00326/04/2025 | F63: MR TAPA | G63: TAPA GAEL SYLVESTRE | H63: MME HEUNA | I63: 264500 | J63: 373500 | K63: 351600 | L63: =J63-K63 | M63: GOLITE | N63: ETKT 1479588273750 | O63: 1 | S63: 373500 | T63: =J63-P63-S63 | U63: 45763 | V63: CAISSE | W63: SOLDE | X63: =K63 | AB63: =AB62-X63+Y63+AA63 | AE63: =AE62-AD63
A64: 45763 | B64: SN | C64: DLA-YQM | D64: 16JUL. | E64: 00321/04/2025 | F64: MRS DIAYO | G64: DIAYO MASSAH STEPHANE LAURE | H64: DG | I64: 783000 | J64: 1149800 | K64: 1029020 | L64: =J64-K64 | M64: NDC | N64: ETKT 0829049042854 | P64: 1000000 | S64: 3179400 | T64: =J64+J65+J66+J67-P64-S64 | U64: 45763 | V64: CAISSE | X64: =K64 | AB64: =AB63-X64+Y64+AA64 | AE64: =AE63-AD64
A65: 45763 | B65: SN | C65: DLA-YQM | D65: 16JUL. | E65: 00321/04/2025 | F65: MRS DIAYO | G65: MICHELLE JOSEPHINE GATSI KENZA | H65: DG | I65: 587800 | J65: 939900 | K65: 833020 | L65: =J65-K65 | M65: NDC | N65: ETKT 0829049042857 | X65: =K65 | AB65: =AB64-X65+Y65+AA65 | AE65: =AE64-AD65
A66: 45763 | B66: SN | C66: DLA-YQM | D66: 16JUL. | E66: 00321/04/2025 | F66: MRS DIAYO | G66: MARIE KARELLE GATSI | H66: DG | I66: 587800 | J66: 939900 | K66: 833020 | L66: =J66-K66 | M66: NDC | N66: ETKT 0829049042855 | X66: =K66 | AB66: =AB65-X66+Y66+AA66 | AE66: =AE65-AD66
A67: 45763 | B67: SN | C67: DLA-YQM | D67: 16JUL. | E67: 00321/04/2025 | F67: MRS DIAYO | G67: CLOE GATSI DIAYO | H67: DG | I67: 783000 | J67: 1149800 | K67: 1029020 | L67: =J67-K67 | M67: NDC | N67: ETKT 0829049042856 | X67: =K67 | AB67: =AB66-X67+Y67+AA67 | AE67: =AE66-AD67
A68: 45763 | B68: AF | C68: CDG-DLA-CDG | D68: 17APR-26APR | F68: MR ONANA | G68: TIANI VESSAH/OLIVIA BIBIANA TCHANGAIN | H68: DG | I68: 4415300 | J68: 5392820 | K68: 5252820 | L68: =J68-K68 | M68: AMADEUS | N68: ETKT 0576376922046 | P68: 10925 | S68: 5381895 | T68: =J68-P68-S68 | U68: 25/04/2025 23/05/2025 | V68: CAISSE | X68: =K68 | AB68: =AB67-X68+Y68+AA68 | AE68: =AE67-AD68
A69: 45763 | B69: KP | C69: SSG-NSI | D69: 17APR. | F69: BANGE BANK | G69: MVONDO ASSAM/BONAVENTURE | H69: DG | I69: 90500 | J69: 305920 | K69: 178200 | L69: =J69-K69 | M69: GOLITE | N69: ETKT 0329588273751 | O69: 1 | S69: 303223 | T69: =J69-P69-S69 | U69: 45779 | V69: V/R | X69: =K69 | AB69: =AB68-X69+Y69+AA69 | AE69: =AE68-AD69
A70: 45763 | B70: ET | C70: DLA-SSG | D70: 17APR. | F70: BANGE BANK | G70: NTSAMA/GUY BERTRAND | H70: DG | J70: 418900 | K70: 303455 | L70: =J70-K70 | M70: BLUEBERRY | N70: ETKT 0719588 261546 | S70: 832403 | T70: =J70+J71-P70-S70 | U70: 45779 | V70: V/R | X70: 0 | AB70: =AB69-X70+Y70+AA70 | AE70: =AE69-AD70
A71: 45763 | B71: ET | C71: DLA-SSG | D71: 17APR. | F71: BANGE BANK | G71: OBIANG NCHAMA/JOSE MIGUEL | H71: DG | J71: 418900 | K71: 303455 | L71: =J71-K71 | M71: BLUEBERRY | N71: ETKT 0719588 261547 | X71: 0 | AB71: =AB70-X71+Y71+AA71 | AE71: =AE70-AD71
A72: 45763 | B72: AF | C72: DLA-CDG-DLA | D72: 23APR-23MAY | F72: MR TCHATUE | G72: SONE EKOLO XAVIER BENJAMIN | H72: DG | J72: 319980 | K72: 169100 | L72: =J72-K72 | M72: GOLITE | N72: ETKT 0579588273752 | O72: EXCHANGE | P72: 321000 | T72: =J72-P72-S72 | U72: 45765 | V72: OM | X72: =K72 | Z72: 18389795 | AB72: =AB71-X72+Y72+AA72 | AE72: =AE71-AD72
A73: 45764 | B73: KP | C73: COO-DLA | D73: 19APR. | E73: 00331/04/2025 | F73: BANGE BANK | G73: ESONO OYANA/ANGELICA MONAYONG MRS | H73: DG | J73: 252920 | K73: 161800 | L73: =J73-K73 | M73: GOLITE | N73: ETKT 0329588273752 | O73: EXCHANGE | S73: 250222 | T73: =J73-P73-S73 | U73: 45779 | V73: V/R | X73: =K73 | AB73: =AB72-X73+Y73+AA73 | AE73: =AE72-AD73
A74: 45764 | B74: HF | C74: DSS-ABJ | D74: 17APR. | F74: MR KAGOU | G74: TONDJA NDAFEUT/YANNICK SANDRINE | H74: DG | I74: 246600 | J74: 462920 | K74: 380200 | L74: =J74-K74 | M74: GOLITE | N74: ETKT 4839588273754 | O74: 1 | T74: =J74-P74-S74 | X74: =K74 | Z74: 17847795 | AB74: =AB73-X74+Y74+AA74 | AC74: 17042025T1325 | AE74: =AE73-AD74
A75: 45765 | G75: NEOSSI/EMMANUEL | J75: 1043820 | K75: 1043820 | L75: =J75-K75 | M75: GOLITE | N75: ETKT 0579588273755 | O75: VOIDER | T75: =J75-P75-S75 | X75: =K75 | AB75: =AB74-X75+Y75+AA75 | AE75: =AE74-AD75
A76: 45765 | G76: MOUNCHILI/IDRISS | J76: 1043820 | K76: 1043820 | L76: =J76-K76 | M76: GOLITE | N76: ETKT 0579588273756 | O76: VOIDER | T76: =J76-P76-S76 | X76: =K76 | Z76: 12018373 | AA76: 2702500 | AB76: =AB75-X76+Y76+AA76 | AE76: =AE75-AD76
A77: 45765 | B77: AF | C77: DLA-MXP.STR-DLA | D77: 04MAY-13MAY | F77: NEO INDUSTRIE | G77: YOMENI TSAFACK, MADELEINE ALVINE | H77: DG | I77: 817800 | J77: 1325850 | K77: 1148820 | L77: =J77-K77 | M77: GOLITE | N77: ETKT 0579588273757-58 | O77: 2 | S77: 1321353 | T77: =J77-P77-S77 | U77: 45772 | V77: V/R | X77: =K77 | AB77: =AB76-X77+Y77+AA77 | AE77: =AE76-AD77
A78: 45765 | G78: NEOSSI/EMMANUEL | H78: DG | J78: 1104520 | K78: 1104520 | L78: =J78-K78 | M78: GOLITE | N78: ETKT 0579588273759 | O78: VOIDER | T78: =J78-P78-S78 | X78: =K78 | AB78: =AB77-X78+Y78+AA78 | AE78: =AE77-AD78
A79: 45765 | G79: MOUNCHILI/IDRISS | H79: DG | J79: 1104520 | K79: 1104520 | L79: =J79-K79 | M79: GOLITE | N79: ETKT 0579588273760 | O79: VOIDER | T79: =J79-P79-S79 | X79: =K79 | AB79: =AB78-X79+Y79+AA79 | AE79: =AE78-AD79
A80: 45765 | B80: SN | C80: DLA-CDG-DLA | D80: 29MAY-14JUN | G80: JEANNE CLAIRE SIMO KAMDEM (ADT | H80: DG | J80: 1937420 | K80: 1937420 | M80: NDC | N80: ETKT 0829049042864 | O80: VOIDER | T80: =J80-P80-S80 | X80: =K80 | Z80: 13167193 | AB80: =AB79-X80+Y80+AA80 | AE80: =AE79-AD80
A81: 45765 | B81: SN | C81: DLA-CDG-DLA | D81: 10JUL-22JUL | F81: MR CHRISTIAN | G81: SOLANGE CORINE KAMDEM EPSE KENMOGNIE | H81: DG | I81: 436900 | J81: 859980 | K81: 698920 | L81: =J81-K81 | M81: NDC | N81: ETKT 0829049042863 | P81: 1000000 | Q81: 1498180 | S81: 3000000 | T81: =J81+J82+J83+J84+J85+J86-P81-Q81-S81 | U81: 22/04/2025 29/04/2025 08/05/2025 | V81: CAISSE | X81: =K81 | AB81: =AB80-X81+Y81+AA81 | AE81: =AE80-AD81
A82: 45765 | B82: SN | C82: CDG-DLA-CDG | D82: 22JUL-28AUG | F82: MR CHRISTIAN | G82: OLWEN KAYDEN SIANI TCHAMANDE | H82: DG | I82: 476900 | J82: 839900 | K82: 738920 | L82: =J82-K82 | M82: NDC | N82: ETKT 0829049042862 | X82: =K82 | AB82: =AB81-X82+Y82+AA82 | AE82: =AE81-AD82
A83: 45765 | B83: SN | C83: CDG-DLA-CDG | D83: 22JUL-28AUG | F83: MR CHRISTIAN | G83: SIANI TCHAMANDE MARLONN KEVAN | H83: DG | I83: 515000 | J83: 898800 | K83: 777020 | L83: =J83-K83 | M83: NDC | N83: ETKT 0829049042858 | X83: =K83 | AB83: =AB82-X83+Y83+AA83 | AE83: =AE82-AD83
A84: 45765 | B84: SN | C84: CDG-DLA-CDG | D84: 22JUL-28AUG | F84: MR CHRISTIAN | G84: ELWAN MITCHELL SIANI TCHAMANDE | H84: DG | I84: 476900 | J84: 839900 | K84: 738920 | L84: =J84-K84 | M84: NDC | N84: ETKT 0829049042861 | X84: =K84 | AB84: =AB83-X84+Y84+AA84 | AE84: =AE83-AD84
A85: 45765 | B85: SN | C85: CDG-DLA-CDG | D85: 05AUG-28AUG | F85: MR CHRISTIAN | G85: ALIONKA ZAFIRA GUIAKAM KENMOGNIE | H85: DG | I85: 635700 | J85: 1029800 | K85: 897720 | L85: =J85-K85 | M85: NDC | N85: ETKT 0829049042859 | X85: =K85 | AB85: =AB84-X85+Y85+AA85 | AE85: =AE84-AD85
A86: 45765 | B86: SN | C86: CDG-DLA-CDG | D86: 05AUG-28AUG | F86: MR CHRISTIAN | G86: JANNELLA STACY DJIEGOUE SIANI TCHAMANDE | H86: DG | I86: 635700 | J86: 1029800 | K86: 897720 | L86: =J86-K86 | M86: NDC | N86: ETKT 0829049042860 | X86: =K86 | AB86: =AB85-X86+Y86+AA86 | AE86: =AE85-AD86
A87: 45765 | B87: AF | C87: ABJ-ZYR | D87: 22APR. | F87: PIVOTAL AFRICA NETWORK | G87: HOT THIERRY JUNIOR | H87: DG | I87: - | J87: 4388600 | K87: 4221600 | L87: =J87-K87 | M87: BLUEBERRY | N87: ETKT 0576376923585 | T87: =J87-P87-S87 | X87: 0 | AB87: =AB86-X87+Y87+AA87 | AE87: =AE86-AD87
A88: 45765 | B88: AF | C88: ABJ-IAD | D88: 22APR. | E88: 00345/04/2025 | F88: PIVOTAL AFRICA NETWORK | G88: TAH SIDI | H88: DG | J88: 253500 | K88: 0 | L88: =J88-K88 | M88: BLUEBERRY | N88: ETKT 0576376923596 | O88: REFUND | T88: =J88-P88-S88 | X88: =K88 | AB88: =AB87-X88+Y88+AA88 | AE88: =AE87-AD88
A89: 45766 | B89: KP | C89: 19APR-30APR | D89: DLA-ABJ-DLA | F89: SAAR | G89: KAGOU/GEORGES LEOPOLD MR | H89: DG | I89: 268300 | J89: 728900 | K89: 631120 | L89: =J89-K89 | M89: GOLITE | N89: ETKT 0329588273761 | O89: 4 | S89: 728900 | T89: =J89-P89-S89 | U89: 45791 | V89: BANQUE | W89: CHQ 8454458 | X89: =K89 | Z89: 7786853 | AB89: =AB88-X89+Y89+AA89 | AE89: =AE88-AD89
A90: 45766 | B90: C8 | C90: 22APR. | D90: SSG-DLA | E90: 00342/04/2025 | F90: BANGE BANK | G90: NTSAMA/GUY BERTRAND | H90: DG | I90: 137900 | J90: 232000 | K90: 182000 | L90: =J90-K90 | M90: C8 | N90: ETKT 49850000334048 | O90: USE | S90: 458605 | T90: =J90+J91-P90-S90 | U90: 45779 | V90: V/R | X90: 0 | AB90: =AB89-X90+Y90+AA90 | AE90: =AE89-AD90
A91: 45766 | B91: C8 | C91: 22APR. | D91: SSG-DLA | E91: 00342/04/2025 | F91: BANGE BANK | G91: OBIANG NCHAMA/JOSE MIGUEL | H91: DG | I91: 137900 | J91: 232000 | K91: 182000 | L91: =J91-K91 | M91: C8 | N91: ETKT 49850000334049 | O91: NO USE | X91: 0 | AB91: =AB90-X91+Y91+AA91 | AE91: =AE90-AD91
A92: 45766 | B92: J7 | C92: 22APR. | D92: SSG-DLA | E92: 00132/02/2025 | F92: BANGE BANK | G92: NTSAMA/GUY BERTRAND | H92: DG | J92: 215850 | K92: 115850 | L92: =J92-K92 | M92: J7 | N92: ETKT 27723735413 | O92: USE | T92: =J92-P92-S92 | X92: 0 | AB92: =AB91-X92+Y92+AA92 | AC92: 21042025T1146 | AE92: =AE91-AD92
A93: 45766 | B93: J7 | C93: 22APR. | D93: SSG-DLA | E93: 00132/02/2025 | F93: BANGE BANK | G93: OBIANG NCHAMA/JOSE MIGUEL | H93: DG | J93: 215850 | K93: 115850 | L93: =J93-K93 | M93: J7 | N93: ETKT 27723735413 | O93: NO USE | T93: =J93-P93-S93 | X93: 0 | AB93: =AB92-X93+Y93+AA93 | AE93: =AE92-AD93
A94: 45767 | B94: AF | C94: ABJ-BRU | D94: 22APR. | F94: PIVOTAL AFRICA NETWORK | G94: HOT THIERRY JUNIOR | H94: DG | J94: 65000 | K94: 0 | L94: =J94-K94 | M94: BLUEBERRY | N94: ETKT 0576376923611 | O94: EXCHANGE | T94: =J94-P94-S94 | X94: 0
A95: 45767 | B95: KP | C95: 21APR. | D95: DSS-DLA | F95: NEO INDUSTRIE | G95: BOUNKEU/CHANTAL | H95: DG | I95: 1051100 | J95: 1365980 | K95: 1265500 | L95: =J95-K95 | M95: GOLITE | N95: ETKT 0329588273762 | O95: 2 | T95: =J95-P95-S95 | X95: =K95 | Z95: 6521535 | AB95: =AB93-X95+Y95+AA95 | AE95: =AE93-AD95
A96: 45768 | B96: KQ | C96: 22APR-22MAY | D96: DLA-DXB-DLA | F96: MR MAFFO | G96: MAFFO NDE TATSIN | H96: MR LUCIEN | I96: 106900 | J96: 210100 | K96: 210100 | L96: =J96-K96 | M96: GOLITE | N96: ETKT 7069588273763 | O96: VOIDER | T96: =J96-P96-S96 | X96: =K96 | Z96: 6311435 | AB96: =AB95-X96+Y96+AA96 | AE96: =AE95-AD96
A97: 45768 | B97: SN | C97: 28MAY-14JUN | D97: DLA-CDG-DLA | E97: 00348/04/2025 | F97: CABINET DENTAIRE G2 | G97: JEANNE CLAIRE SIMO KAMDEM (ADT | H97: DG | I97: 1445300 | J97: 2027900 | K97: 1937420 | L97: =J97-K97 | M97: NDC | N97: ETKT 0829049042865 | S97: 2027900 | T97: =J97-P97-S97 | U97: 45770 | V97: CAISSE | X97: =K97 | Z97: 4374015 | AB97: =AB96-X97+Y97+AA97
A98: 45768 | B98: KP | C98: 22APR. | D98: SG-NSI | E98: 00347/04/2025 | F98: BANGE BANK | G98: OBIANG NCHAMA/JOSE MICHEL | H98: DG | I98: 137900 | J98: 356980 | K98: 225600 | L98: =J98-K98 | M98: GOLITE | N98: ETKT 0329588273764 | O98: 1 | S98: 708565 | T98: =J98+J99-P98-S98 | U98: 45779 | V98: V/R | X98: =K98 | Z98: 4148415 | AB98: =AB97-X98+Y98+AA98 | AE98: =AE96-AD98
A99: 45768 | B99: KP | C99: 22APR. | D99: SG-NSI | E99: 00347/04/2025 | F99: BANGE BANK | G99: NTSAMA/GUY BERTRAND | H99: DG | I99: 137900 | J99: 356980 | K99: 225600 | L99: =J99-K99 | M99: GOLITE | N99: ETKT 0329588273765 | O99: 1 | X99: =K99 | Z99: 3922815 | AB99: =AB98-X99+Y99+AA99 | AE99: =AE98-AD99
A100: 45768 | B100: KP | C100: 22APR. | D100: SG-NSI | E100: 00346/04/2025 | F100: BANGE BANK | G100: ESSISSIMA/PASCAL HERVE | H100: DG | J100: 172920 | K100: 98700 | L100: =J100-K100 | M100: GOLITE | N100: ETKT 0329588273766 | O100: EXCHANGE | S100: 170222 | T100: =J100-P100-S100 | U100: 45779 | V100: V/R | X100: =K100 | Z100: 3824115 | AB100: =AB99-X100+Y100+AA100 | AE100: =AE99-AD100
...

Sheet MAY
A1: DATE | B1: CIES | C1: TRAVEL DATE | D1: PARCOURS | E1: N FACTURE | F1: ENTREPRISE | G1: NOMS/PRENOMS | H1: APPORTEUR | I1: TARIF HT | J1: COM, HF (6% ) | K1: COM, MS (7% ) | L1: COM, KP (6% ) | M1: COM, ET (3/4%) | N1: TC | O1: TM | P1: FS | Q1: LIEU ACHAT | R1: NUMERO DU BILLET | S1: NBRE SGTS | T1: AVANCE | U1: AVANCE 02 | V1: AVANCE 03 | W1: RGLT | X1: SOLDE | Y1: DATE RGLT | Z1: MODE RGLT | AA1: OBSERVATION | AB1: TM | AC1: APPRO | AD1: 17905765 | AF1: 17905765 | AI1: 2522688 | AM1: 4143919
A2: 45778 | B2: KP | C2: 29MAY-09JUN | D2: DLA-ABJ-DLA | E2: 00392/05/2025 | F2: MRS MANEKEUNG | G2: MANEKEUNG EPSE YOUMBI CHARLOTTE | H2: MRS HEUNA | I2: 32000 | N2: 426800 | O2: 394420 | P2: =N2-O2 | Q2: GOLITE | R2: ETKT 0329588273785 | S2: 4 | W2: 426800 | X2: =N2-T2-W2 | Y2: 45778 | Z2: OM | AB2: =O2 | AD2: 18725205 | AE2: 1213860 | AF2: =AF1-AB2+AE2+AC2 | AI2: =AI1-AG2+AH2 | AM2: 4143919
A3: 45778 | B3: EK | C3: 02MAY-21JUN | D3: DXB-CDG-DXB | E3: 00393/05/2025 | F3: MR NGATCHOU | G3: FOKOM FOTSO/JULES BORIS | H3: DG | N3: 2870920 | O3: 2570120 | P3: =N3-O3 | Q3: BLUEBERRY | R3: ETKT 1763556329916 | S3: BB | T3: 2500000 | W3: 370000 | X3: =N3-T3-W3 | Y3: 05/05/2025 09/05/2025 | Z3: CAISSE | AA3: 09MAY. | AB3: 0 | AF3: =AF2-AB3+AE3+AC3 | AI3: =AI2-AG3+AH3 | AM3: 4143919
A4: 45779 | B4: HF | C4: 02MAY-03MAY | D4: ABJ-DLA-ABJ | E4: 00387/05/2025 | F4: MR ONANA | G4: NNOMO MEZUI/CHERILLE OLIVIA MRS | H4: DG | I4: 705900 | N4: 1295920 | O4: 1135420 | P4: =N4-O4 | Q4: GOLITE | R4: ETKT 4839588273786 | S4: 2 | W4: 1295920 | X4: =N4-T4-W4 | Y4: 45800 | Z4: CAISSE | AB4: =O4 | AD4: 17589785 | AF4: =AF3-AB4+AE4+AC4 | AI4: =AI3-AG4+AH4 | AM4: 4143919
A5: 02/05/22025 | B5: AF | C5: 02MAY-16MAY | D5: YUL-DLA-YU | E5: 00394/05/2025 | F5: MRS FRANCA | G5: FOTSO THERESE ODILE | H5: DG | I5: 605900 | N5: 1423700 | O5: 1160120 | P5: =N5-O5 | Q5: GOLITE | R5: ETKT 0579588273787 | S5: 4 | W5: 1423700 | X5: =N5-T5-W5 | Y5: 45778 | Z5: CAISSE | AB5: =O5 | AF5: =AF4-AB5+AE5+AC5 | AI5: =AI4-AG5+AH5 | AM5: 4143919
A6: 45779 | B6: QC | C6: 08MAY-11MAY | D6: NSI-DLA-NSI | E6: 00396/05/2025 | F6: MRS ESSO | G6: MARIAME RAISSA, MFOUTE PEPOUORE | H6: DG | N6: 104700 | O6: 89340 | P6: =N6-O6 | Q6: KIU | R6: ETKT 0400300037076 | W6: 104500 | X6: =N6-T6-W6 | Y6: 45817 | Z6: CAISSE | AA6: 45785 | AB6: 0 | AF6: =AF5-AB6+AE6+AC6 | AG6: 89340 | AI6: =AI5-AG6+AH6 | AM6: 4143919
A7: 45779 | B7: AF | C7: 04MAY-07MAY | D7: CDG-NKC-CDG | E7: 00395/05/2025 | F7: PIVOTAL | G7: LEAUTIER/ANN FRANCES MRS | H7: DG | N7: 5346800 | O7: 5248600 | P7: =N7-O7 | Q7: AMADEUS | R7: ETKT 057 6376931402 | X7: =N7-T7-W7 | AB7: =O7 | AF7: =AF6-AB7+AE7+AC7 | AI7: =AI6-AG7+AH7 | AM7: 4143919
A8: 45780 | B8: J7 | C8: 04MAY-09MAY | D8: DLA-LBV-DLA | E8: 00397/05/2025 | F8: HORUS | G8: NGANI MEIGNIDON DIFFO MIRELLE NICAISE ELISE | H8: DG | J8: 98700 | K8: 35000 | L8: 63700 | M8: J7 | N8: 98700 | O8: 35000 | P8: =N8-O8 | Q8: J7 | R8: ETKT 2770047170619 | S8: EXCHANGE | W8: 98700 | X8: =N8-T8-W8 | Y8: 45842 | Z8: V/R | AB8: 0 | AF8: =AF7-AB8+AE8+AC8 | AI8: =AI7-AG8+AH8 | AM8: 4143919
A9: 45751 | B9: KP | C9: 04MAY-05AUG | D9: DLA-BGF-DLA | E9: 00398/05/2025 | F9: CANAL+ | G9: BOUJEKE TCHEKOULONG/WILLIAM MR | H9: DG | I9: 32100 | N9: 498920 | O9: 343655 | P9: =N9-O9 | Q9: GOLITE | R9: ETKT 0329588273788 | S9: 2 | W9: 498920 | X9: =N9-T9-W9 | Y9: 45799 | Z9: V/R | AB9: =O9 | AD9: 10986710 | AE9: 149300 | AF9: =AF8-AB9+AE9+AC9 | AI9: =AI8-AG9+AH9 | AM9: 4143919
A10: 45782 | B10: AF | C10: 25MAY-28MAY | D10: CDG-DXB-CDG | E10: 00401/02/2025 | F10: HARVEST | G10: DIVOUX/JEAN MARC | H10: DG | I10: 983300 | N10: 1258900 | O10: 1223800 | P10: =N10-O10 | Q10: GOLITE | R10: ETKT 0579588273789 | S10: 2 | W10: 1258900 | X10: =N10-T10-W10 | Y10: 45779 | Z10: V/R | AB10: =O10 | AF10: =AF9-AB10+AE10+AC10 | AI10: =AI9-AG10+AH10 | AM10: 4143919
A11: 45782 | B11: AF | C11: 24MAY-28MAY | D11: JFK-DXB-JFK | E11: 00400/05/2025 | F11: HARVEST | G11: TENGA/FABRICE | H11: DG | I11: 1639000 | N11: 2389900 | O11: 2326200 | P11: =N11-O11 | Q11: GOLITE | R11: ETKT 0579588273791 | S11: 4 | W11: 2389900 | X11: =N11-T11-W11 | Y11: 45779 | Z11: V/R | AB11: =O11 | AF11: =AF10-AB11+AE11+AC11 | AI11: =AI10-AG11+AH11 | AM11: 4143919
A12: 45782 | B12: HF | C12: 13MAY-17MAY | D12: DLA-ABJ-DLA | E12: 00399/05/2025 | F12: CANAL+ | G12: TAMBA ZAPO/PAUL ZEPHYRIN | H12: DG | I12: 140600 | N12: 590800 | O12: 490120 | P12: =N12-O12 | Q12: GOLITE | R12: ETKT 4839588273790 | S12: 2 | X12: =N12-T12-W12 | AB12: =O12 | AD12: 6946590 | AF12: =AF11-AB12+AE12+AC12 | AI12: =AI11-AG12+AH12 | AM12: 4143919
A13: 45782 | E13: 00390/05/2025 | F13: SAFARI LOGISTICS | G13: TCHATCHOUA SUZANNE LINDA | N13: 20000 | O13: 0 | P13: =N13-O13 | R13: RESERVATION HOTEL | W13: 20000 | X13: =N13-T13-W13 | Y13: 45849 | Z13: BANQUE | AA13: CHQ 1399555 | AB13: =O13
A14: 45783 | B14: AF | C14: 10JUN-14JUN-19JUN-22JUN | D14: DLA-CDG-MRS-CDG-DLA | E14: 00404/05/2025 | F14: CANAL+ | G14: MBIATCHOU/LIONEL | H14: DG | I14: 594900 | N14: 1227980 | O14: 949620 | P14: =N14-O14 | Q14: GOLITE | R14: ETKT 0579588273792 | S14: 4 | W14: 1227980 | X14: =N14-T14-W14 | Y14: 45813 | Z14: V/R | AB14: =O14 | AF14: =AF12-AB14+AE14+AC14 | AI14: =AI12-AG14+AH14 | AM14: 4143919
A15: 45783 | B15: AF | C15: 17MAY-05JUN | D15: DLA-YUL-DLA | E15: 00403/05/2025 | F15: MR NGUETSE | G15: NGUETSE YMELE/MATHIAS | H15: DG | I15: 466800 | N15: 997520 | O15: 941620 | P15: =N15-O15 | Q15: GOLITE | R15: ETKT 0579588273793 | S15: 4 | W15: 997520 | X15: =N15-T15-W15 | Y15: 45783 | Z15: CAISSE | AB15: =O15 | AD15: 5055350 | AF15: =AF14-AB15+AE15+AC15 | AI15: =AI14-AG15+AH15 | AM15: 4143919
A16: 45783 | B16: J7 | C16: 07MAY. | D16: DLA-SSG | E16: 00402/05/2025 | F16: BANGE BANK | G16: OBIANG AYANG JOSE MANUEL BILE | H16: DG | N16: 230000 | O16: 170000 | P16: =N16-O16 | Q16: J7 | R16: ETKT 27723938326 | X16: =N16-T16-W16 | AB16: 0 | AF16: =AF15-AB16+AE16+AC16 | AI16: =AI15-AG16+AH16 | AM16: 4143919
A17: 45784 | B17: KP | C17: 23MAY-31MAY | D17: NSI-NDJ-NSI | E17: 00411/05/2025 | F17: CANAL+ | G17: MFOULA/JULIENNE | H17: DG | I17: 96300 | N17: 443920 | O17: 348005 | P17: =N17-O17 | Q17: GOLITE | R17: ETKT 0329588273794 | S17: 2 | W17: 443920 | X17: =N17-T17-W17 | Y17: 45821 | Z17: V/R | AB17: =O17 | AF17: =AF16-AB17+AE17+AC17 | AI17: =AI16-AG17+AH17 | AM17: 4143919
A18: 45784 | B18: KP | C18: 23MAY-06JUN | D18: NSI-NDJ-DLA | E18: 00410/05/2025 | F18: CANAL+ | G18: TCHAMKO EPSE MBU | H18: DG | I18: 88300 | N18: 449920 | O18: 341305 | P18: =N18-O18 | Q18: GOLITE | R18: ETKT 0329588273795 | S18: 2 | W18: 449920 | X18: =N18-T18-W18 | Y18: 45821 | Z18: V/R | AB18: =O18 | AF18: =AF17-AB18+AE18+AC18 | AI18: =AI17-AG18+AH18 | AM18: 4143919
A19: 45784 | B19: KP | C19: 10MAY-18MAY | D19: DLA-NDJ-DLA | E19: 00409/05/2025 | F19: CANAL+ | G19: MBALLA NKOA/STEV | H19: DG | I19: 159200 | N19: 529700 | O19: 428805 | P19: =N19-O19 | Q19: GOLITE | R19: ETKT 0329588273796 | S19: 2 | W19: 529700 | X19: =N19-T19-W19 | Y19: 45821 | Z19: V/R | AB19: =O19 | AF19: =AF18-AB19+AE19+AC19 | AI19: =AI18-AG19+AH19 | AM19: 4143919
A20: 45784 | B20: AF | C20: 04JUN-11JUN | D20: DLA-CDG-DLA | E20: 00408/05/2025 | F20: CANAL+ | G20: NTUMBA NDAYA EPS | H20: DG | I20: 387200 | J20: 387200 | K20: 387200 | L20: 387200 | M20: 387200 | N20: 940850 | O20: 702420 | P20: =N20-O20 | Q20: GOLITE | R20: ETKT 0579588273797 | S20: 2 | X20: =N20-T20-W20 | AB20: =O20 | AF20: =AF19-AB20+AE20+AC20 | AI20: =AI19-AG20+AH20 | AM20: 4143919
A21: 45784 | B21: AF | C21: 11MAY-18MAY | D21: ABJ-CDG-ABJ | E21: 00407/05/2025 | F21: MR ONANA | G21: .LOHOUES/YEDMELY EMMANUELLA JESUS MRS | H21: DG | N21: 8796800 | O21: 8566200 | P21: =N21-O21 | Q21: AMADEUS | R21: ETKT 0576376934867 | T21: 1146525 | W21: 7650275 | X21: =N21-T21-W21 | Y21: 23/05/2025 13/06/2025 | Z21: CAISSE | AB21: =O21 | AC21: 15000000 | AF21: =AF20-AB21+AE21+AC21 | AI21: =AI20-AG21+AH21 | AM21: 4143919
A22: 45784 | B22: QC | C22: 11MAY. | D22: DLA-NGE | E22: 00406/05/2025 | F22: MRS TSOPFACK | G22: MARIE MARTINE/TSOPFACK ZEFACK | H22: MR LUCIEN | N22: 66970 | O22: 64470 | P22: =N22-O22 | Q22: KIU | R22: ETKT 0400300037077 | W22: 66970 | X22: =N22-T22-W22 | Y22: 45785 | Z22: CAISSE | AB22: 0 | AF22: =AF21-AB22+AE22+AC22 | AG22: 64470 | AI22: =AI21-AG22+AH22 | AM22: 4143919
A23: 45784 | B23: QC | C23: 08MAY-08MAY | D23: DLA-NSI-DLA | E23: 00405/05/2025 | F23: MR KEMGAM | G23: LEONARD/KEMGAN NGUETCHOM | H23: MR LUCIEN | N23: 84000 | O23: 81540 | P23: =N23-O23 | Q23: KIU | R23: ETKT 0400300037078 | W23: 84000 | X23: =N23-T23-W23 | Y23: 45785 | Z23: CAISSE | AB23: 0 | AF23: =AF22-AB23+AE23+AC23 | AG23: 81540 | AI23: =AI22-AG23+AH23 | AM23: 4143919
A24: 45784 | B24: AF | C24: 13JUN-20JUN | D24: DLA-CDG-DLA | E24: 00420/05/2025 | F24: CANAL+ | G24: TAMBA ZAPO/PAUL ZEPHYRIN | H24: DG | N24: 1012900 | O24: 1012900 | P24: =N24-O24 | Q24: GALILEO | R24: ETKT 0579588273797 | S24: FICTIF | X24: =N24-T24-W24 | AB24: =O24 | AF24: =AF23-AB24+AE24+AC24 | AI24: =AI23-AG24+AH24 | AM24: 4143919
A25: 45785 | B25: SN | C25: 06JUN-14JUN | D25: DLA-MAD-DLA | E25: 00418/05/2025 | F25: MR DJOUAKA | G25: DJOUAKA/ALAIN ROGER MR | I25: 1129100 | N25: 1945920 | O25: 1517820 | P25: =N25-O25 | Q25: NDC | R25: ETKT 0829049042874 | T25: 1000000 | W25: 945920 | X25: =N25-T25-W25 | Y25: 07/05/2025 27/05/2025 | Z25: V/R | AB25: =O25 | AF25: =AF24-AB25+AE25+AC25 | AI25: =AI24-AG25+AH25 | AM25: 4143919
A26: 45785 | B26: SN | C26: 06JUN-14JUN | D26: DLA-MAD-DLA | E26: 00419/05/2025 | F26: MR DJOUAKA | G26: KIFACK BOUKENG EP DJOUAKA/FLORENCE | I26: 1129100 | N26: 1945920 | O26: 1517820 | P26: =N26-O26 | Q26: NDC | R26: ETKT 0829049042875 | T26: 1000000 | W26: 945920 | X26: =N26-T26-W26 | Y26: 07/05/2025 27/05/2025 | Z26: V/R | AB26: =O26 | AF26: =AF25-AB26+AE26+AC26 | AI26: =AI25-AG26+AH26 | AM26: 4143919
A27: 45785 | B27: SN | C27: 13MAY. | D27: ABJ-LHR | E27: 00415/05/2025 | F27: PIVOTAL | G27: APHING KOUASSI/LYNDA MRS | H27: DG | I27: 1281100 | N27: 1579800 | O27: 1449600 | P27: =N27-O27 | Q27: NDC | R27: ETKT 0829049042876 | X27: =N27-T27-W27 | AB27: =O27 | AF27: =AF26-AB27+AE27+AC27 | AI27: =AI26-AG27+AH27 | AM27: 4143919
A28: 45785 | B28: SN08MAY-12MAY | C28: 08MAY-12MAY | D28: FIH-BRU-FIH | E28: 00417/05/2025 | F28: MRS ELANGA | G28: NJONGUO TIALEFACK/JULIUS | H28: DG | I28: 2659300 | N28: 3040300 | O28: 2940300 | P28: =N28-O28 | Q28: NDC | R28: ETKT 0829049042877 | W28: 3040300 | X28: =N28-T28-W28 | Y28: 45800 | Z28: CAISSE | AB28: =O28 | AF28: =AF27-AB28+AE28+AC28 | AI28: =AI27-AG28+AH28 | AM28: 4143919
A29: 45785 | B29: AF | C29: 14MAY-24MAY | D29: ABJ-LHR-ABJ | E29: 00412/05/2025 | F29: PIVOTAL | G29: HOT JUNIOR THIERRY | H29: DG | I29: 4896900 | N29: 6433100 | O29: 5641300 | P29: =N29-O29 | Q29: AMADEUS/BLEUBERRY | R29: ETKT 0576376932795 | X29: =N29-T29-W29 | AB29: 0 | AF29: =AF28-AB29+AE29+AC29 | AI29: =AI28-AG29+AH29 | AM29: 4143919
A30: 45785 | B30: AF | C30: 31MAY. | D30: ABJ-ZHR | E30: 00413/05/2025 | F30: PIVOTAL | G30: HOT JUNIOR THIERRY | H30: DG | I30: 2463700 | N30: 2895800 | O30: 2794400 | P30: =N30-O30 | Q30: AMADEUS/BLEUBERRY | R30: ETKT 0576376932897 | X30: =N30-T30-W30 | AB30: 0 | AF30: =AF29-AB30+AE30+AC30 | AI30: =AI29-AG30+AH30 | AM30: 4143919
A31: 45785 | B31: AF | C31: 14MAY. | D31: ABJ-LHR | E31: 00414/05/2025 | F31: PIVOTAL | G31: TAH/SIDI | H31: DG | N31: 3246300 | O31: 3166300 | P31: =N31-O31 | Q31: AMADEUS/BLEUBERRY | R31: ETKT 0576376932886 | X31: =N31-T31-W31 | AB31: 0 | AF31: =AF30-AB31+AE31+AC31 | AI31: =AI30-AG31+AH31 | AM31: 4143919
A32: 45785 | B32: HF | C32: 27MAY-31MAY | D32: DLA-ABJ-DLA | E32: 00416/05/2025 | F32: PIVOTAL | G32: EKOUTI BENOIT THIERRY | H32: DG | N32: 564800 | O32: 504800 | P32: =N32-O32 | Q32: AMADEUS | R32: ETKT 4836376935105 | X32: =N32-T32-W32 | AB32: =O32 | AD32: 1738255 | AF32: =AF31-AB32+AE32+AC32 | AI32: =AI31-AG32+AH32 | AM32: 4143919
A33: 45786 | B33: AF | C33: 10MAY-14MAY | D33: CDG-ABJ-CDG | E33: 00421/05/2025 | F33: PIVOTAL | G33: LEAUTIER/ANN FRANCES MRS | H33: DG | N33: 22000 | O33: 0 | P33: =N33-O33 | Q33: AMADEUS | R33: ETKT 0576376935746 | S33: EXCHANGE | X33: =N33-T33-W33 | AB33: =O33 | AF33: =AF32-AB33+AE33+AC33 | AI33: =AI32-AG33+AH33 | AM33: 4143919
A34: 45786 | B34: MS | C34: 20MAY. | D34: DLA-CMN | E34: 00422/05/2025 | F34: MR TAPA | G34: TAPA GAEL SYLVESTRE | H34: MME HEUNA | N34: 359700 | O34: 350420 | P34: =N34-O34 | Q34: AMADEUS | R34: ETKT 0776376935741 | T34: 300000 | W34: 59700 | X34: =N34-T34-W34 | Y34: 09/05/2025 12/05/2025 | Z34: CAISSE | AB34: =O34 | AF34: =AF33-AB34+AE34+AC34 | AI34: =AI33-AG34+AH34 | AM34: 4143919
A35: 45786 | B35: KP | C35: 23MAY. | D35: DLA-BKO | E35: 00425/05/2025 | F35: MRS LAGMAGO | G35: LAGMAGO TOUOYEM, MARINA MRS | H35: MME GLADYS | I35: 232800 | N35: 480620 | O35: 465620 | P35: =N35-O35 | Q35: GOLITE | R35: ETKT 0329588273799 | S35: 1 | W35: 480620 | X35: =N35-T35-W35 | Y35: 45789 | Z35: CAISSE | AB35: =O35 | AF35: =AF34-AB35+AE35+AC35 | AI35: =AI34-AG35+AH35 | AM35: =AM34-AL35
A36: 45786 | B36: ET | C36: 13JUN. | D36: DLA-YEG | E36: 00426/05/2025 | F36: MRS SOME | G36: BILLA OLIVIER BIKWANYE | H36: DG | N36: 673220 | O36: 668220 | P36: =N36-O36 | Q36: B2B | R36: ETKT 0712152469038 | W36: 673220 | X36: =N36-T36-W36 | Y36: 45786 | Z36: CAISSE | AB36: 0 | AF36: =AF35-AB36+AE36+AC36 | AI36: =AI35-AG36+AH36 | AL36: 668220 | AM36: =AM35-AL36
A37: 45786 | B37: AF | C37: 19MAI | D37: CDG-DLA | E37: 00429/05/2025 | F37: NEO INDUSTRIE | G37: YOMENI TSAFACK/MADELEINE ALVINE | H37: DG | I37: EMD 1400 | N37: 91900 | O37: 23200 | P37: =N37-O37 | Q37: GOLITE | R37: ETKT 0579588273798 | S37: EXCHANGE | W37: 91900 | X37: =N37-T37-W37 | Y37: 45818 | Z37: BANQUE | AA37: CHQ 6417232 | AB37: =O37 | AF37: =AF36-AB37+AE37+AC37 | AI37: =AI36-AG37+AH37 | AM37: =AM36-AL37
A38: 45786 | B38: ET | C38: 19MAY-31MAY | D38: DLA-JNB-DLA | E38: 00424/05/2025 | F38: BEKO CAPITAL | G38: NKWAMOU FLORENCE BAKENGBON | H38: DG | N38: 497920 | O38: 471920 | P38: =N38-O38 | Q38: B2B | R38: ETKT 0712152472530 | W38: 497920 | X38: =N38-T38-W38 | Y38: 45807 | Z38: V/R | AB38: 0 | AF38: =AF37-AB38+AE38+AC38 | AI38: =AI37-AG38+AH38 | AL38: 471920 | AM38: =AM37-AL38
A39: 45787 | B39: KP | C39: 26MAY. | D39: DLA-NIM | E39: 00430/05/2025 | F39: CABTE | G39: ABDOULAYE ALIO/MAHAMAN LAWAN MR | H39: DG | I39: 194300 | N39: 469920 | O39: 416320 | P39: =N39-O39 | Q39: GOLITE | R39: ETKT 0329588273803 | S39: 2 | W39: 469920 | X39: =N39-T39-W39 | Y39: 45793 | Z39: BANQUE | AA39: CHQ 9858407 | AB39: =O39 | AF39: =AF38-AB39+AE39+AC39 | AI39: =AI38-AG39+AH39 | AM39: =AM38-AL39
A40: 45787 | B40: AF | C40: 22MAY-29MAY | D40: DLA-CDG-DLA | E40: 00431/05/2025 | F40: MR NGATCHOU | G40: NZETE/MARTIN LUTHER KING | H40: DG | I40: 1900100 | N40: 3019800 | O40: 2737620 | P40: =N40-O40 | Q40: GOLITE | R40: ETKT 0579588273800 | S40: 2 | T40: 2490000 | W40: 529800 | X40: =N40-T40-W40 | Y40: 08/05/2025 09/05/2025 | Z40: CAISSE | AB40: =O40 | AF40: =AF39-AB40+AE40+AC40 | AI40: =AI39-AG40+AH40 | AM40: =AM39-AL40
A41: 45787 | B41: AF | C41: 04JUN-14JUL | D41: DLA-NTE-DLA | E41: 00432/05/2025 | F41: MRS JIOTSA | G41: KENFACK GUEFO EP JIOTSA EDWIGE | H41: DG | I41: 383300 | N41: 767920 | O41: 717920 | P41: =N41-O41 | Q41: GOLITE | R41: ETKT 0579588273801 | S41: 5 | T41: 200000 | U41: 200000 | V41: 300000 | W41: 67920 | X41: =N41-T41-W41-U41-V41 | Y41: 09/05/2025 16/05/2025 03/06/2025 16/07/2025 | Z41: CAISSE | AB41: =O41 | AF41: =AF40-AB41+AE41+AC41 | AI41: =AI40-AG41+AH41 | AM41: =AM40-AL41
A42: 45787 | B42: SN | C42: 21DEC-04JAN | D42: CDG-DLA-CDG | E42: 00433/05/2025 | F42: PREMIUM | G42: ALEX PATRICK SERGE NJAPOUM | H42: DG | I42: 793800 | N42: 1140790 | O42: 1055820 | P42: =N42-O42 | Q42: NDC | R42: ETKT 0829049042878 | W42: 1140790 | X42: =N42-T42-W42 | Y42: 45770 | Z42: CAISSE | AB42: =O42 | AF42: =AF41-AB42+AE42+AC42 | AI42: =AI41-AG42+AH42 | AM42: =AM41-AL42
A43: 45788 | B43: KP | C43: 16MAY-21MAY | D43: DLA-DSS-DLA | E43: 00423/05/2025 | F43: DOC ANGE | G43: YMELE/JEAN PIERRE MR | H43: DG | N43: 1753620 | O43: 1656664 | P43: =N43-O43 | Q43: GOLITE/BLUEBERRY | R43: ETKT 0329588 261588 | T43: 1750000 | W43: 3620 | X43: =N43-T43-W43 | Y43: 45789 | Z43: CAISSE OM | AB43: 0 | AF43: =AF42-AB43+AE43+AC43 | AI43: =AI42-AG43+AH43 | AM43: =AM42-AL43
A44: 45788 | B44: HF | C44: 24MAY-15JUN | D44: DLA-ABJ-DLA | E44: 00434/05/2025 | F44: PREMIUM | G44: NGANI/THEANA JEANNE ELEANE | H44: DG | N44: 490980 | O44: 435620 | P44: =N44-O44 | Q44: GOLITE | R44: ETKT 4839588273804 | S44: 2 | W44: 490980 | X44: =N44-T44-W44 | Y44: 45804 | Z44: CAISSE | AB44: =O44 | AF44: =AF43-AB44+AE44+AC44 | AI44: =AI43-AG44+AH44 | AK44: 3 033 224 | AM44: =AM43-AL44
X45: =N45-T45-W45 | AB45: =O45 | AF45: =AF44-AB45+AE45+AC45 | AI45: =AI44-AG45+AH45 | AM45: =AM44-AL45
A46: 45789 | B46: AH | C46: 13MAY-19MAY | D46: ALG-DLA-ALG | E46: 00436/05/2025 | F46: KALFRELEC | G46: CHETTI YOUNES | H46: DG | J46: 477900 | K46: 189420 | L46: =J46-K46 | M46: GOLITE | N46: 477900 | O46: 327520 | P46: =N46-O46 | Q46: GOLITE | R46: ETKT 1249588273805 | S46: 2 | X46: =N46-T46-W46 | AB46: =O46 | AF46: =AF45-AB46+AE46+AC46 | AI46: =AI45-AG46+AH46 | AM46: =AM45-AL46
A47: 45790 | B47: SN | C47: 07JUN-29JUN | D47: DLA-BRU-DLA | E47: 00437/05/2025 | F47: CANAL+ | G47: PATRICK YVES NGUEGUIM (ADT) | H47: DG | I47: 613300 | J47: 1120800 | K47: 833620 | L47: =J47-K47 | M47: NDC | N47: 1120800 | O47: 833620 | P47: =N47-O47 | Q47: NDC | R47: ETKT 0829049042879 | W47: 1120800 | X47: =N47-T47-W47 | Y47: 45821 | Z47: V/R | AB47: =O47 | AF47: =AF46-AB47+AE47+AC47 | AI47: =AI46-AG47+AH47 | AM47: =AM46-AL47
A48: 45790 | B48: AF | C48: 17MAY. | D48: FRA-DLA | E48: 00438/05/2025 | F48: NEO INDUSTRIE | G48: YOMENI TSAFACK MADELEINE ALVINE | H48: DG | I48: 855200 | J48: 91900 | K48: 30400 | L48: =J48-K48 | M48: GOLITE | N48: 91900 | O48: 30400 | P48: =N48-O48 | Q48: GOLITE | R48: ETKT 0579588273806 | S48: EXCHANGE | W48: 91900 | X48: =N48-T48-W48 | Y48: 45818 | Z48: BANQUE | AA48: CHQ 6417232 | AB48: =O48 | AF48: =AF47-AB48+AE48+AC48 | AI48: =AI47-AG48+AH48 | AM48: =AM47-AL48
A49: 45790 | B49: AF | C49: 17MAY – 02JUN | D49: DLA-DFW-DLA | E49: 00428/05/2025 | F49: MR KAGOU | G49: MEDJO MEVA A EP TSITSOL NAOMIE MIRABELLE | H49: DG | I49: 1153800 | J49: 1715920 | K49: 1636020 | L49: =J49-K49 | M49: BLUEBERRY | N49: 1715920 | O49: 1636020 | P49: =N49-O49 | Q49: BLUEBERRY | R49: ETKT 0579588 261592 | S49: 4 | X49: =N49-T49-W49 | AB49: 0 | AF49: =AF48-AB49+AE49+AC49 | AI49: =AI48-AG49+AH49 | AM49: =AM48-AL49
A50: 45790 | B50: KP | C50: 17 MAY – 21 MAY | D50: BGF – DLA-BGF | E50: 00440/05/2025 | F50: MR KAPE | G50: KOUREICHY MAXIMUS M | H50: DG | I50: 465400 | J50: 871755 | K50: 771755 | L50: =J50-K50 | M50: BLUEBERRY | N50: 871755 | O50: 771755 | P50: =N50-O50 | Q50: BLUEBERRY | R50: ETKT 0329588 261591 | S50: 2 | X50: =N50-T50-W50 | AB50: 0 | AF50: =AF49-AB50+AE50+AC50 | AI50: =AI49-AG50+AH50 | AM50: =AM49-AL50
A51: 45790 | B51: AF | C51: 26 MAY-03JUN | D51: DLA-CDG-DLA | E51: 00439/05/2025 | F51: SAFARI LOGISTICS | G51: TCHATCHOUA SUZANNE LINDA | H51: DG | J51: 2362920 | L51: =J51-K51 | M51: AF | N51: 2362920 | O51: 2241420 | P51: =N51-O51 | Q51: AF | R51: ETKT 0572337848255 | T51: 1479960 | W51: 882960 | X51: =N51-T51-W51 | Y51: 45849 | Z51: BANQUE | AA51: CHQ 1399555 | AB51: =O51 | AF51: =AF50-AB51+AE51+AC51 | AI51: =AI50-AG51+AH51 | AM51: =AM50-AL51
A52: 45791 | B52: ET | C52: 16JUN-06JUL | D52: DLA-BRU-DLA | E52: 00435/05/2025 | F52: RWKING | G52: AZEMKOUO/ALAIN | H52: DG | I52: 205900 | J52: 595 | K52: 516820 | L52: =J52-K52 | M52: GOLITE | N52: 595820 | O52: 516820 | P52: =N52-O52 | Q52: GOLITE | R52: ETKT 0719588273807 | S52: 4 | X52: =N52-T52-W52 | AB52: =O52 | AF52: =AF51-AB52+AE52+AC52 | AI52: =AI51-AG52+AH52 | AM52: =AM51-AL52
A53: 45791 | G53: NJALL BIKOK JULES ALAIN | H53: DG | J53: 155000 | K53: 125000 | L53: =J53-K53 | N53: 155000 | O53: 125000 | P53: =N53-O53 | S53: VISA DUBAI | X53: =N53-T53-W53 | AB53: 0 | AF53: =AF52-AB53+AE53+AC53 | AI53: =AI52-AG53+AH53 | AM53: =AM52-AL53
A54: 45791 | G54: KAMGAING TAASSI MARC ETIENNE | H54: DG | J54: 155000 | K54: 125000 | L54: =J54-K54 | N54: 155000 | O54: 125000 | P54: =N54-O54 | S54: VISA DUBAI | X54: =N54-T54-W54 | AB54: 0 | AF54: =AF53-AB54+AE54+AC54 | AI54: =AI53-AG54+AH54 | AM54: =AM53-AL54
A55: 45791 | B55: KP | C55: 17MAY-21MAY | D55: DLA-NDJ-DLA | E55: 00442/05/2025 | F55: CANAL+ | G55: DJEUTCHEU NANA/CLAUDE MR | H55: DG | I55: 317400 | N55: 719800 | O55: 619005 | P55: =N55-O55 | Q55: GOLITE | R55: ETKT 0329588273813 | S55: 2 | W55: 719800 | X55: =N55-T55-W55 | Y55: 45821 | Z55: V/R | AB55: =O55 | AF55: =AF54-AB55+AE55+AC55 | AI55: =AI54-AG55+AH55 | AM55: =AM54-AL55
A56: 45791 | B56: HF | C56: 01JUN-07JUN | D56: NSI-ABJ-NSI | E56: 00443/05/2025 | F56: CANAL+ | G56: MFOULA/JULIENNE SYLVIE MRS | H56: DG | I56: 155300 | N56: 604900 | O56: 504820 | P56: =N56-O56 | Q56: GOLITE | R56: ETKT 4839588273812 | S56: 2 | W56: 604900 | X56: =N56-T56-W56 | Y56: 45821 | Z56: V/R | AB56: =O56 | AF56: =AF55-AB56+AE56+AC56 | AI56: =AI55-AG56+AH56 | AM56: =AM55-AL56
A57: 45791 | B57: AF | C57: 24MAY-27SEP | D57: DLA-STR-DLA | E57: 00444/05/2025 | F57: MRS CHRISTINE | G57: MBIAKOP PETKEU/TRACY LYNA | H57: DG | I57: 571000 | N57: 946920 | O57: 906720 | P57: =N57-O57 | Q57: GOLITE | R57: ETKT 0579588273811 | S57: 4 | W57: 946920 | X57: =N57-T57-W57 | Y57: 45793 | Z57: CAISSE | AB57: =O57 | AF57: =AF56-AB57+AE57+AC57 | AI57: =AI56-AG57+AH57 | AM57: =AM56-AL57
A58: 45791 | B58: QC | C58: 15MAY-15MAY | D58: DLA-NSI-DLA | E58: 00441/05/2025 | F58: FOKOUA ROMEO | G58: FOKOUA KUMO ROMEO ARITIDE | H58: DG | N58: 101920 | O58: 81540 | P58: =N58-O58 | Q58: KIU | R58: ETKT 0400300037079 | W58: 101920 | X58: =N58-T58-W58 | Y58: 45817 | Z58: CAISSE | AB58: 0 | AF58: =AF57-AB58+AE58+AC58 | AG58: 81540 | AH58: 0 | AI58: =AI57-AG58+AH58 | AM58: =AM57-AL58
A59: 45791 | B59: AT | C59: 26MAY. | D59: DLA-CDG | E59: 00445/05/2025 | F59: MRS JESTSA | G59: JEATSA GAPDO EPSE NGALEU/CARINE MRS | H59: MME HEUNA | I59: 74900 | N59: 328800 | O59: 278520 | P59: =N59-O59 | Q59: GOLITE | R59: ETKT 1479588273808 | S59: 2 | W59: 328800 | X59: =N59-T59-W59 | Y59: 45791 | Z59: CAISSE | AB59: =O59 | AF59: =AF58-AB59+AE59+AC59 | AI59: =AI58-AG59+AH59 | AM59: =AM58-AL59
A60: 45791 | B60: AT | C60: 26MAY. | D60: DLA-CDG | E60: 00445/05/2025 | F60: MRS JESTSA | G60: NGALEU JEATSA/KYLIAN CHRISTOPHE | H60: MME HEUNA | I60: 56200 | N60: 309760 | O60: 259820 | P60: =N60-O60 | Q60: GOLITE | R60: ETKT 1479588273809 | S60: 2 | W60: 309760 | X60: =N60-T60-W60 | Y60: 45791 | Z60: CAISSE | AB60: =O60 | AF60: =AF59-AB60+AE60+AC60 | AI60: =AI59-AG60+AH60 | AM60: =AM59-AL60
A61: 45791 | B61: ET | C61: 15MAY. | D61: DXB-NSI | E61: 00446/05/2025 | F61: NGATCHOU | G61: ENGOUBOU YABIT/MARIE THERESE MRS | H61: DG | I61: 2627300 | N61: 2867900 | O61: 2627300 | P61: =N61-O61 | Q61: GOLITE/BLUEBERRY | R61: ETKT 0719588261593 | S61: 2 | T61: 1800280 | W61: 1067620 | X61: =N61-T61-W61 | Y61: 45810 | Z61: CAISSE | AB61: 0 | AF61: =AF60-AB61+AE61+AC61 | AI61: =AI60-AG61+AH61 | AM61: =AM60-AL61
A62: 45791 | B62: AF | C62: 15MAY. | D62: DXB-CDG | E62: 00447/05/2025 | F62: NGATCHOU | G62: MBIA BATSI/SIMONE LAURE | H62: DG | I62: 457000 | N62: 789920 | O62: 559600 | P62: =N62-O62 | Q62: GOLITE | R62: ETKT 0579588273810 | S62: 1 | W62: 789920 | X62: =N62-T62-W62 | Y62: 45791 | Z62: CAISSE | AB62: =O62 | AF62: =AF61-AB62+AE62+AC62 | AI62: =AI61-AG62+AH62 | AM62: =AM61-AL62
A63: 45792 | B63: QC | C63: 15MAY. | D63: NSI-DLA | E63: 00448/05/2025 | F63: HARVEST | G63: MARC ETIENNE KAMGAING TAASSI | H63: DG | N63: 25000 | O63: 13000 | P63: =N63-O63 | Q63: QC | R63: ETKT 0400300037054 | W63: 25000 | X63: =N63-T63-W63 | Y63: 45855 | Z63: V/R | AB63: 0 | AF63: =AF62-AB63+AE63+AC63 | AI63: =AI62-AG63+AH63 | AM63: =AM62-AL63
A64: 45792 | B64: ET | C64: 28MAY-08MAY | D64: DLA-CDG-DLA | E64: 00449/05/2025 | F64: NOVA-PLAST SARL | G64: KENGMO TSOBZE ALEXIS | H64: DG | I64: 274500 | N64: 641900 | O64: 585920 | P64: =N64-O64 | Q64: GOLITE | R64: ETKT 0719588273814 | S64: 4 | W64: 641900 | X64: =N64-T64-W64 | Y64: 45799 | Z64: BANQUE | AA64: CHQ639852 | AB64: =O64 | AF64: =AF63-AB64+AE64+AC64 | AI64: =AI63-AG64+AH64 | AM64: =AM63-AL64
A65: 45792 | B65: QC | C65: 18MAY-20MAY | D65: DLA-BZV-DLA | E65: 00450/05/2025 | F65: MR CHARLES WONG | G65: MR C EFETI MOKA ENDELEY EP WATAT | H65: DG | N65: 469930 | O65: 439930 | P65: =N65-O65 | Q65: KIU | R65: ETKT 0400300037080 | W65: 469930 | X65: =N65-T65-W65 | Y65: 45818 | Z65: V/R | AB65: 0 | AF65: =AF64-AB65+AE65+AC65 | AG65: 439920 | AI65: =AI64-AG65+AH65 | AM65: =AM64-AL65
A66: 45793 | B66: ET | C66: 24MAY-28MAY | D66: DLA-ADD-DLA | E66: 00452/05/2025 | F66: SAAR | G66: KAGOU GEORGES LEOPOLD | H66: DG | N66: 1752920 | O66: 1667620 | P66: =N66-O66 | Q66: GOLITE | R66: ETKT 0719588273817 | S66: 2 | W66: 1752920 | X66: =N66-T66-W66 | Y66: 45827 | Z66: BANQUE | AA66: CHQ 8054959 | AB66: =O66 | AF66: =AF65-AB66+AE66+AC66 | AI66: =AI65-AG66+AH66 | AM66: =AM65-AL66
A67: 45793 | B67: AF | C67: 23MAY-10JUN | D67: DLA-YUL-DLA | E67: 00451/05/2025 | F67: MR NGUETSE | G67: NGUETSE YMELE MATHIAS | H67: DG | N67: 326900 | O67: 306400 | P67: =N67-O67 | Q67: GOLITE | R67: ETKT 0579588273816 | S67: EXCHANGE | W67: 326900 | X67: =N67-T67-W67 | Y67: 45799 | Z67: CAISSE | AB67: =O67 | AF67: =AF66-AB67+AE67+AC67 | AI67: =AI66-AG67+AH67 | AM67: =AM66-AL67
A68: 45794 | B68: QC | C68: 26MAY. | D68: MVR-DLA | E68: 00453/05/2025 | F68: MRS ZEBAZE | G68: ZEBAZE DONGO GUILAINE | H68: MR LUCIEN | N68: 142500 | O68: 139670 | P68: =N68-O68 | Q68: KIU | R68: ETKT 0400300037081 | W68: 142500 | X68: =N68-T68-W68 | Y68: 45799 | Z68: CAISSE | AB68: 0 | AF68: =AF67-AB68+AE68+AC68 | AG68: 139670 | AI68: =AI67-AG68+AH68 | AM68: =AM67-AL68
A69: 45794 | B69: HF | C69: 21MAY-27MAY | D69: DLA-ABJ-DLA | E69: 00454/05/2025 | F69: MR ADJAHOUNG FRANCOIS | G69: NGO YON ADJAHOUNG MERVIELLE | H69: DG | I69: 86100 | N69: 475900 | O69: 435620 | P69: =N69-O69 | Q69: GOLITE | R69: ETKT 4839588273819 | W69: 475900 | X69: =N69-T69-W69 | Y69: 45798 | Z69: CAISSE | AB69: =O69 | AF69: =AF68-AB69+AE69+AC69 | AI69: =AI68-AG69+AH69 | AM69: =AM68-AL69
A70: 45794 | B70: HF | C70: 21MAY-27MAY | D70: DLA-ABJ-DLA | E70: 00454/05/2025 | F70: MR ADJAHOUNG FRANCOIS | G70: MR ADJAHOUNG FRANCOIS | H70: DG | I70: 86100 | N70: 475900 | O70: 435620 | P70: =N70-O70 | Q70: GOLITE | R70: ETKT 4839588273818 | W70: 475900 | X70: =N70-T70-W70 | Y70: 45798 | Z70: CAISSE | AB70: =O70 | AF70: =AF69-AB70+AE70+AC70 | AI70: =AI69-AG70+AH70 | AM70: =AM69-AL70
A71: 45794 | B71: HF | C71: 21MAY-27MAY | D71: DLA-ABJ-DLA | E71: 00454/05/2025 | F71: MR ADJAHOUNG FRANCOIS | G71: NGO YON ADJAHOUNG MERVIELLE | H71: DG | I71: 0 | N71: 75000 | O71: 60000 | P71: =N71-O71 | Q71: GOLITE | R71: . | S71: VISA ABIDJAN | W71: 75000 | X71: =N71-T71-W71 | Y71: 45798 | Z71: CAISSE | AB71: 0 | AF71: =AF70-AB71+AE71+AC71 | AI71: =AI70-AG71+AH71 | AM71: =AM70-AL71
A72: 45794 | B72: HF | C72: 21MAY-27MAY | D72: DLA-ABJ-DLA | E72: 00454/05/2025 | F72: MR ADJAHOUNG FRANCOIS | G72: MR ADJAHOUNG FRANCOIS | H72: DG | I72: 0 | N72: 75000 | O72: 60000 | P72: =N72-O72 | Q72: GOLITE | R72: . | S72: VISA ABIDJAN | W72: 75000 | X72: =N72-T72-W72 | Y72: 45798 | Z72: CAISSE | AB72: 0 | AF72: =AF71-AB72+AE72+AC72 | AI72: =AI71-AG72+AH72 | AM72: =AM71-AL72
A73: 45795 | B73: J7 | C73: 19MAY. | D73: DLA-SSG | E73: 00457/05/2025 | F73: BANGE BANK | G73: NTSAMA GUY BERTRAND | H73: DG | N73: 283000 | O73: 223000 | P73: =N73-O73 | Q73: J7 | R73: ETKT 27724085358 | X73: =N73-T73-W73 | AB73: 0 | AF73: =AF72-AB73+AE73+AC73 | AI73: =AI72-AG73+AH73 | AM73: =AM72-AL73
A74: 45795 | B74: ET | C74: 19MAY. | D74: LFW-IAD | E74: 00456/05/2025 | F74: PIVOTAL | G74: ACOUETEY KANGNI DIDIER | H74: DG | I74: 2568500 | N74: 2849900 | O74: 2799600 | P74: =N74-O74 | Q74: B2B | R74: ETKT 071215266049 | X74: =N74-T74-W74 | AB74: 0 | AF74: =AF73-AB74+AE74+AC74 | AI74: =AI73-AG74+AH74 | AL74: 2799600 | AM74: =AM73-AL74
A75: 45795 | B75: AF | C75: 21MAY-23MAY-03JUN-05JUN | D75: IAD.LFW.ABJ-CDG-IAD | E75: 00455/05/2025 | F75: PIVOTAL | G75: ACOUETEY KANGNI DIDIER | H75: DG | N75: 6685900 | O75: 6583000 | P75: =N75-O75 | Q75: GOLITE | R75: ETKT 0579288273825 | S75: 4 | X75: =N75-T75-W75 | AB75: =O75 | AF75: =AF74-AB75+AE75+AC75 | AI75: =AI74-AG75+AH75 | AM75: =AM74-AL75
A76: 45796 | B76: AF | C76: 21MAY. | D76: DXB-NKC | E76: 00460/05/2025 | F76: PIVOTAL | G76: TAH SIDI | H76: DG | N76: 326800 | O76: 200 | P76: =N76-O76 | Q76: AMADEUS | R76: ETKT 0576376943536 | S76: REFUND | X76: =N76-T76-W76 | AB76: =O76 | AF76: =AF75-AB76+AE76+AC76 | AI76: =AI75-AG76+AH76 | AM76: =AM75-AL76
A77: 45796 | B77: AT | C77: 14AUG. | D77: DLA-CDG | E77: 00459/05/2025 | F77: ISTAMA | G77: THIAM IBRA | H77: DG | I77: 240100 | N77: 503920 | O77: 443620 | P77: =N77-O77 | Q77: GOLITE | R77: ETKT 1479588273824 | S77: 2 | T77: 402280 | W77: 101640 | X77: =N77-T77-W77 | Y77: 45792 | Z77: V/R | AB77: =O77 | AF77: =AF76-AB77+AE77+AC77 | AI77: =AI76-AG77+AH77 | AM77: =AM76-AL77
A78: 45796 | B78: EK | C78: 20MAY. | D78: DXB-BRU | E78: 00463/05/2025 | F78: PIVOTAL | G78: HOT JUNIOR THIERRY | H78: DG | N78: 2605980 | O78: 2496335 | P78: =N78-O78 | Q78: BLUEBERRY | R78: ETKT 17628850422540 | X78: =N78-T78-W78 | AB78: 0 | AF78: =AF77-AB78+AE78+AC78 | AI78: =AI77-AG78+AH78 | AM78: =AM77-AL78
A79: 45796 | B79: SV | C79: 20MAY. | D79: RUH-DXB | E79: 00464/05/2025 | F79: PIVOTAL | G79: TAH SIDI | H79: DG | N79: 315800 | O79: 99700 | P79: =N79-O79 | Q79: AMADEUS | R79: ETKT 0656075684331 | S79: REFUND | X79: =N79-T79-W79 | AB79: =O79 | AF79: =AF78-AB79+AE79+AC79 | AI79: =AI78-AG79+AH79 | AM79: =AM78-AL79
A80: 45796 | B80: AF | C80: 21MAY. | D80: ZYR-NKC | E80: 00460/05/2025 | F80: PIVOTAL | G80: HOT JUNIOR THIERRY | H80: DG | I80: 1812500 | N80: 2295920 | O80: 2200000 | P80: =N80-O80 | Q80: GOLITE | R80: ETKT 0579588273822 | S80: 2 | X80: =N80-T80-W80 | AB80: =O80 | AF80: =AF79-AB80+AE80+AC80 | AI80: =AI79-AG80+AH80 | AM80: =AM79-AL80
A81: 45796 | B81: ET | C81: 24MAY-28MAY | D81: DLA-ADD-DLA | E81: 00458/05/2025 | F81: SAAR | G81: KAGOU GEORGES LEOPOLD | H81: DG | N81: 169500 | O81: 65900 | P81: =N81-O81 | Q81: GOLITE | R81: ETKT 0719588273823 | S81: EXCHANGE | W81: 169500 | X81: =N81-T81-W81 | Y81: 45827 | Z81: BANQUE | AA81: CHQ 8054957 | AB81: =O81 | AF81: =AF80-AB81+AE81+AC81 | AI81: =AI80-AG81+AH81 | AM81: =AM80-AL81
A82: 45797 | B82: SN | C82: 25MAY-01JUN | D82: LHR-ABJ-LHR | E82: 00469/05/2025 | F82: PIVOTAL | G82: APHING KOUASSI LINDA | H82: DG | N82: 3748600 | O82: 3633800 | P82: =N82-O82 | Q82: AMADEUS | R82: ETKT 0826376943547 | X82: =N82-T82-W82 | AB82: =O82 | AF82: =AF81-AB82+AE82+AC82 | AI82: =AI81-AG82+AH82 | AM82: =AM81-AL82
A83: 45797 | B83: SN | C83: 08AUG-28AUG | D83: CDG-DLA-CDG | E83: 00468/05/2025 | F83: MR ROMARIC | G83: ELIANE ELLA KAMDEM KOUAM EP SIANI | H83: DG | I83: 635700 | N83: 949720 | O83: 897720 | P83: =N83-O83 | Q83: NDC | R83: ETKT 0829049042880 | W83: 949720 | X83: =N83-T83-W83 | Y83: 45817 | Z83: CAISSE | AB83: =O83 | AF83: =AF82-AB83+AE83+AC83 | AI83: =AI82-AG83+AH83 | AM83: =AM82-AL83
A84: 45797 | B84: SN | C84: 08AUG-28AUG | D84: CDG-DLA-CDG | E84: 00468/05/2025 | F84: MR ROMARIC | G84: ROMARIC TCHAPPI | H84: DG | I84: 635700 | N84: 949720 | O84: 897720 | P84: =N84-O84 | Q84: NDC | R84: ETKT 0829049042881 | W84: 949720 | X84: =N84-T84-W84 | Y84: 45817 | Z84: CAISSE | AB84: =O84 | AF84: =AF83-AB84+AE84+AC84 | AI84: =AI83-AG84+AH84 | AM84: =AM83-AL84
A85: 45797 | B85: AT | C85: 17JUL-15AUG | D85: DLA-YUL-DLA | E85: 00467/05/2025 | F85: MR MBOUGUE | G85: MBOUGUE NGUETSOP IVE DESIRE | H85: DG | I85: 306000 | N85: 821820 | O85: 735720 | P85: =N85-O85 | Q85: GOLITE | R85: ETKT 1479588273826 | W85: 821820 | X85: =N85-T85-W85 | Y85: 45798 | Z85: CAISSE | AB85: =O85 | AF85: =AF84-AB85+AE85+AC85 | AI85: =AI84-AG85+AH85 | AM85: =AM84-AL85
A86: 45797 | B86: AT | C86: 17JUL. | D86: DLA-YUL | E86: 00466/05/2025 | F86: MR MBOUGUE | G86: MBOUGUE DESIRE FILS | H86: DG | I86: 0 | N86: 263400 | O86: 183700 | P86: =N86-O86 | Q86: GOLITE | R86: ETKT 1479588273827 | S86: 2 | T86: 178180 | U86: 300000 | X86: =N86-T86-U86-W86 | Y86: 21/05/2025 28/05/2025 | Z86: CAISSE | AB86: =O86 | AF86: =AF85-AB86+AE86+AC86 | AI86: =AI85-AG86+AH86 | AM86: =AM85-AL86
A87: 45797 | B87: AF | C87: 21MAY-24MAY | D87: IAD-CDG-LFW | E87: 00466/05/2025 | F87: PIVOTAL | G87: ACOUETEY KANGNI DIDIER | H87: DG | N87: 660600 | O87: 590600 | P87: =N87-O87 | Q87: GOLITE | R87: ETKT 0579588273820 | S87: EXCHANGE | X87: =N87-T87-W87 | AB87: =O87 | AF87: =AF86-AB87+AE87+AC87 | AI87: =AI86-AG87+AH87 | AM87: =AM86-AL87
A88: 45798 | B88: J7 | C88: 22MAY-24MAY | D88: SSG-LBV-DLA | E88: 00475/05/2025 | F88: BANGE BANK | G88: NTSAMA GUY BERTRAND | H88: DG | N88: 529980 | O88: 438201 | P88: =N88-O88 | Q88: J7 | R88: ETKT 27724126443 | X88: =N88-T88-W88 | AB88: 0 | AF88: =AF87-AB88+AE88+AC88 | AI88: =AI87-AG88+AH88 | AM88: =AM87-AL88
A89: 45798 | B89: SN | C89: 10JUN-20JUN | D89: BRU-DLA.DSS-BRU | E89: 00474/05/2025 | F89: PIVOTAL | G89: HOT JUNIOR THIERRY | H89: DG | I89: 1749500 | N89: 2180920 | O89: 2072600 | P89: =N89-O89 | Q89: NDC | R89: ETKT 0829049042882 | X89: =N89-T89-W89 | AB89: =O89 | AF89: =AF88-AB89+AE89+AC89 | AI89: =AI88-AG89+AH89 | AM89: =AM88-AL89
A90: 45798 | B90: HF | C90: 17JUN. | D90: DLA-DSS | E90: 00473/05/2025 | F90: PIVOTAL | G90: HOT JUNIOR THIERRY | H90: DG | I90: 605800 | N90: 941800 | O90: 861720 | P90: =N90-O90 | Q90: GOLITE | R90: ETKT 4839588273833 | S90: 2 | X90: =N90-T90-W90 | AB90: =O90 | AF90: =AF89-AB90+AE90+AC90 | AI90: =AI89-AG90+AH90 | AM90: =AM89-AL90
A91: 45798 | B91: AF | C91: 26MAY-07JUN | D91: NSI-CDG-NSI | E91: 00472/05/2025 | F91: NGATCHOU | G91: KAMGANG INGRID FABIOLA | H91: DG | I91: 353200 | N91: 898520 | O91: 661420 | P91: =N91-O91 | Q91: GOLITE | R91: ETKT 0579588273834 | S91: 2 | T91: 793000 | W91: 105520 | X91: =N91-T91-W91 | Y91: 23/05/2025 02/06/2025 | Z91: CAISSE | AB91: =O91 | AF91: =AF90-AB91+AE91+AC91 | AI91: =AI90-AG91+AH91 | AM91: =AM90-AL91
A92: 45798 | B92: QC | C92: 22MAY-23MAY | D92: DLA-NSI-DLA | E92: 00487/05/2025 | F92: MR ONANA | G92: BIDJONI MARIE | H92: DG | N92: 131500 | O92: 111340 | P92: =N92-O92 | Q92: QC | R92: ETKT 0400200547968 | S92: ERREUR SUR LE TRAJET | W92: 131500 | X92: =N92-T92-W92 | Y92: 45821 | Z92: CAISSE | AB92: 0 | AF92: =AF91-AB92+AE92+AC92 | AI92: =AI91-AG92+AH92 | AM92: =AM91-AL92
A93: 45798 | B93: QC | C93: 23MAY-23MAY | D93: DLA-NSI-DLA | E93: 00471/05/2025 | F93: HORUS | G93: ENAMA EPSE ONANA MARIE LAURE | H93: DG | N93: 117500 | O93: 97140 | P93: =N93-O93 | Q93: KIU | R93: ETKT 0400300037082 | W93: 117500 | X93: =N93-T93-W93 | Y93: 45842 | Z93: V/R | AB93: 0 | AF93: =AF92-AB93+AE93+AC93 | AG93: 117500 | AI93: =AI92-AG93+AH93 | AM93: =AM92-AL93
A94: 45798 | B94: HF | C94: 23MAY-27MAY | D94: DLA-ABJ-DLA | E94: 00470/05/2025 | F94: MR ADJAHOUNG | G94: NGO YON EPSE ADJAHOUNG MERVEILLE | H94: DG | N94: 45000 | O94: 30000 | P94: =N94-O94 | Q94: GOLITE | R94: ETKT 483 9588273832 | S94: EXCHANGE | X94: =N94-T94-W94 | AB94: =O94 | AF94: =AF93-AB94+AE94+AC94 | AI94: =AI93-AG94+AH94 | AM94: =AM93-AL94
A95: 45799 | B95: HF | C95: 25MAY-29MAY | D95: NSI-ABJ-NSI | E95: 00478/05/2025 | F95: CANAL+ | G95: TILA TILA/STEPHANE MR | H95: DG | I95: 254900 | N95: 694900 | O95: 604420 | P95: =N95-O95 | Q95: GOLITE | R95: ETKT 4839588273839 | S95: 2 | W95: 694900 | X95: =N95-T95-W95 | Y95: 45828 | Z95: V/R | AB95: =O95 | AF95: =AF94-AB95+AE95+AC95 | AI95: =AI94-AG95+AH95 | AM95: =AM94-AL95
A96: 45799 | B96: HF | C96: 25MAY-29MAY | D96: DLA-ABJ-DLA | E96: 00481/05/2025 | F96: CANAL+ | G96: YOUBISSI TOWO EP ZEINSE F/JUSTINE DI | H96: DG | I96: 204800 | N96: 644800 | O96: 554320 | P96: =N96-O96 | Q96: GOLITE | R96: ETKT 4839588273838 | S96: 2 | W96: 644800 | X96: =N96-T96-W96 | Y96: 45828 | Z96: V/R | AB96: =O96 | AF96: =AF95-AB96+AE96+AC96 | AI96: =AI95-AG96+AH96 | AM96: =AM95-AL96
A97: 45799 | B97: KP | C97: 27MAY-31MAY | D97: NSI-ABJ-NSI | E97: 00482/05/2025 | F97: PIVOTAL | G97: FIDIECK A BIDIAS/MATHIAS EMILE | H97: DG | I97: 124800 | N97: 546820 | O97: 496820 | P97: =N97-O97 | Q97: GOLITE | R97: ETKT 0329588273837 | S97: 4 | X97: =N97-T97-W97 | AB97: =O97 | AF97: =AF96-AB97+AE97+AC97 | AI97: =AI96-AG97+AH97 | AM97: =AM96-AL97
A98: 45799 | B98: KP | C98: 31MAY-06JUN | D98: DLA-NDJ-DLA | E98: 00480/05/2025 | F98: CANAL+ | G98: AVOUZOA MINKOULOU/GRACE AGNES MRS | H98: DG | I98: 145800 | N98: 513900 | O98: 413405 | P98: =N98-O98 | Q98: GOLITE | R98: ETKT 0329588273836 | S98: 2 | W98: 513900 | X98: =N98-T98-W98 | Y98: 45828 | Z98: V/R | AB98: =O98 | AF98: =AF97-AB98+AE98+AC98 | AI98: =AI97-AG98+AH98 | AM98: =AM97-AL98
A99: 45799 | B99: KP | C99: 31MAY-04JUN | D99: DLA-NDJ-DLA | E99: 00479/05/2025 | F99: CANAL+ | G99: TAMBA ZAPO/PAUL ZEPHYRIN MR | H99: DG | I99: 145800 | N99: 513900 | O99: 413405 | P99: =N99-O99 | Q99: GOLITE | R99: ETKT 071 9588273840 | S99: 2 | W99: 513900 | X99: =N99-T99-W99 | Y99: 45828 | Z99: V/R | AB99: =O99 | AF99: =AF98-AB99+AE99+AC99 | AI99: =AI98-AG99+AH99 | AM99: =AM98-AL99
A100: 45799 | B100: ET | C100: 25MAY-28MAY | D100: DLA-JNB-DLA | E100: 00476/05/2025 | F100: BEKO | G100: NJAMFA/TIARA MARIE SHILLEH | H100: DG | I100: 234600 | N100: 562920 | O100: 512020 | P100: =N100-O100 | Q100: GOLITE | R100: ETKT 0719588273840 | S100: 4 | W100: 562920 | X100: =N100-T100-W100 | Y100: 45807 | Z100: V/R | AB100: =O100 | AF100: =AF99-AB100+AE100+AC100 | AI100: =AI99-AG100+AH100 | AM100: =AM99-AL100
...

Sheet JUIN
A1: DATE | B1: CIES | D1: PARCOURS | E1: N FACTURE | F1: ENTREPRISE | G1: NOMS/PRENOMS | H1: APPORTEUR | I1: TARIF HT | J1: TC | K1: TM | L1: FS | M1: LIEU ACHAT | N1: NUMERO DU BILLET | O1: NBRE SGTS | P1: AVANCE 01 | Q1: AVANCE 02 | R1: AVANCE 03 | S1: AVANCE 04 | T1: RGLT | U1: SOLDE | V1: DATE RGLT | W1: MODE REGLT | X1: DELAIS
A2: 45809 | B2: AF | C2: 26JUN-13AUG | D2: DLA-CDG-DLA | E2: 00522/06/2025 | F2: CANAL+ | G2: TAMBA ZAPO/PAUL ZEPHYRIN MR | H2: DG | I2: 1005000 | J2: 1868700 | K2: 1357820 | L2: =J2-K2 | M2: GOLITE | N2: ETKT 057 9588273861 | O2: 2 | T2: 1868700 | U2: =J2-P2-T2 | V2: 45845 | W2: v/r
A3: 45809 | B3: AF | C3: 12JUN-16JUN | D3: ABJ-DLA-ABJ | E3: 00521/06/2025 | F3: PIVOTAL | G3: APHING KOUASSI/LYNDA | H3: DG | J3: 1255800 | K3: 1135300 | L3: =J3-K3 | M3: AMADEUS | N3: ETKT 483 6376951395 | U3: =J3-P3-T3
A4: 45810 | B4: SN | C4: 03JUL-31JUL | D4: DLA-LHR-DLA | E4: 00523/06/2025 | F4: MR NJOUME | G4: JOCKY KINGUE EPSE NJOUME/EMMA ROSY | H4: DG | J4: 1067800 | K4: 978220 | L4: =J4-K4 | M4: NDC | N4: ETKT 0829049042885 | P4: 1000000 | T4: 67800 | U4: =J4-P4-T4 | V4: 03/06/2025 17/07/2025 | W4: CAISSE
A5: 45810 | B5: SN | C5: 03JUL-31JUL | D5: DLA-LHR-DLA | E5: 00523/06/2025 | F5: MR NJOUME | G5: NJOUME/GRACE VICTORIA MS | H5: DG | J5: 1067800 | K5: 978220 | L5: =J5-K5 | M5: NDC | N5: ETKT 0829049042886 | P5: 932200 | U5: =J5-P5-T5 | V5: 45855 | W5: CAISSE
A6: 45810 | B6: SN | C6: 08SEP-23SEP | D6: BRU-DLA-BRU | E6: 00524/06/2025 | F6: MRS TEZANOU | G6: THERESA LYVIA TEZANOU M (ADT) | H6: DG | J6: 562000 | K6: 557020 | L6: =J6-K6 | M6: NDC | N6: ETKT 0829049042888 | T6: 562000 | U6: =J6-P6-T6 | V6: 45838 | W6: CAISSE
A7: 45810 | B7: ET | C7: 03JUN, | D7: NSI-LBV | E7: 00511/06/2025 | F7: EMRALD SECURITIES SERVICES BOURSE | G7: .NDOM NDJOCK/ALEXIS MR | H7: DG | J7: 786900 | K7: 678055 | L7: =J7-K7 | M7: AMADEUS | N7: ETKT 0719588273862 | O7: 1 | T7: 786800 | U7: =J7-P7-T7 | V7: 45810 | W7: CAISSE
A8: 45810 | B8: AT | C8: 03JUN-18JUN | D8: DLA-TUN-DLA | E8: 00525/06/2025 | F8: KALFRELEC | G8: BELGACEM/ALI MR | H8: DG | J8: 947000 | K8: 796920 | L8: =J8-K8 | M8: AMADEUS | N8: ETKT 147 6376952232 | U8: =J8-P8-T8
A9: 45810 | B9: J7 | C9: 03JUN, | D9: SSG-DLA | E9: 00531/06/2025 | F9: BANGE BANK | G9: JUSTINO NGUERE NVE MODJO | H9: DG | J9: 120920 | K9: 61800 | L9: =J9-K9 | M9: J7 | N9: ETKT 27724277666 | O9: EXCHANGE | U9: =J9-P9-T9
A10: 45810 | B10: J7 | C10: 03JUN, | D10: SSG-DLA | E10: 00531/06/2025 | F10: BANGE BANK | G10: OBIANG NCHAMA JOSÉ MIGUEL | H10: DG | J10: 120920 | K10: 61800 | L10: =J10-K10 | M10: J7 | N10: ETKT 27724277666 | O10: EXCHANGE | U10: =J10-P10-T10
A11: 45810 | B11: J7 | C11: 03JUN, | D11: SSG-DLA | E11: 00531/06/2025 | F11: BANGE BANK | G11: GUY BERTRAND NTSAMA | H11: DG | J11: 120920 | K11: 61800 | L11: =J11-K11 | M11: J7 | N11: ETKT 27724277666 | O11: EXCHANGE | U11: =J11-P11-T11
A12: 45811 | B12: AF | C12: 05JUN-30JUN | D12: TLS-NSI-CDG | E12: 00533/06/2025 | F12: MR ONANA | G12: MVENE SENGUE/PAULINE LAETITIA MRS | H12: DG | I12: 4004700 | J12: 4989920 | K12: 4839920 | L12: =J12-K12 | M12: GOLITE | N12: ETKT 0579588273863 | O12: 3 | T12: 4989920 | U12: =J12-P12-T12 | V12: 45811 | W12: CAISSE
A13: 45811 | B13: KP | C13: 04JUN-14JUN | D13: ABJ-BGF-ABJ | E13: 00532/06/2025 | F13: MR NGATCHOU | G13: EVINA ABOULA/YANNICK SATURNIN MR | H13: DG | I13: 505300 | J13: 970600 | K13: 870600 | L13: =J13-K13 | M13: GOLITE | N13: ETKT 0329588273864 | O13: 4 | T13: 970600 | U13: =J13-P13-T13 | V13: 45813 | W13: CAISSE
A14: 45812 | B14: J7 | C14: 10JUN-11JUN | D14: DLA-LBV-DLA | E14: 00535/06/2025 | F14: ISTAMA | G14: NJANTA EBENEZER | H14: DG | J14: 395700 | K14: 382144 | L14: =J14-K14 | M14: J7 | N14: ETKT 27724307088 | T14: 395700 | U14: =J14-P14-T14 | V14: 45880 | W14: BANQUE | X14: CHQ 9896459
A15: 45812 | B15: SN | C15: 16JUN-13JUL | D15: DLA-BRU-DLA | E15: 00536/06/2025 | F15: MRS SUZANNE | G15: DJOUGUI EPOUSE NGUENEWOU/JULIENNE | H15: DG | J15: 1326920 | K15: 1226920 | L15: =J15-K15 | M15: NDC | N15: ETKT 0829049042889 | P15: 533000 | Q15: 198500 | R15: 147500 | S15: 239000 | U15: =J15-P15-R15-Q15-T15-S15 | V15: 09/06/2025 11/06/2025 23/06/2025 07/10/2025 | W15: CAISSE
A16: 45812 | B16: KP | C16: 07JUN, | D16: BGF-DLA | E16: 00534/06/2025 | F16: CANAL+ | G16: BOUJEKE TCHEKOULONG/WILLIAM | H16: DG | J16: 127920 | K16: 30000 | L16: =J16-K16 | M16: GOLITE | N16: ETKT 032 9588273865 | O16: EXCHANGE | T16: 127920 | U16: =J16-P16-T16 | V16: 45828 | W16: v/r
A17: 45813 | B17: ET | C17: 18JUN-23JUN-25JUN | D17: DLA-CPT-JNB-DLA | F17: MRS DJUIMO | G17: DJUIMO DEBANA/EMILIE SANDRINE EP TEFOIT | H17: MME HEUNA | J17: 1037720 | K17: 1037720 | L17: =J17-K17 | M17: GOLITE | N17: ETKT 0719588273867 | O17: VOIDER | U17: =J17-P17-T17
A18: 45813 | B18: HF | C18: 09JUN-11JUN | D18: DLA-ABJ-DLA | E18: 00537/06/2025 | F18: MR NGATCHOU | G18: TALLA DJEMMO/ROMUALD MR | H18: DG | I18: 527700 | J18: 1087900 | K18: 957220 | L18: =J18-K18 | M18: GOLITE | N18: ETKT 483 9588273869 | O18: 2 | T18: 1087900 | U18: =J18-P18-T18 | V18: 45828 | W18: CAISSE
A19: 45813 | B19: HF | C19: 09JUN-11JUN | D19: DLA-ABJ-DLA | E19: 00537/06/2025 | F19: MR NGATCHOU | G19: KAMGAING KAMDEM/GUY JANVIER MR | H19: DG | I19: 527700 | J19: 1087900 | K19: 957220 | L19: =J19-K19 | M19: GOLITE | N19: ETKT 483 9588273870 | O19: 2 | T19: 1087900 | U19: =J19-P19-T19 | V19: 45828 | W19: CAISSE
A20: 45813 | B20: AF | C20: 21JUN-07JUL | D20: DLA-ZRH,CDG-DLA | E20: 00529/06/2025 | F20: NEO INDUSTRIE | G20: BOOG/SAMUEL DIEUDONNE | H20: DG | J20: 4570920 | K20: 4393120 | L20: =J20-K20 | M20: GOLITE/BLUEBERRY | N20: ETKT 0573006415324 | O20: 3 | T20: 4570920 | U20: =J20-P20-T20 | V20: 45818 | W20: BANQUE | X20: CHQ6417231
A21: 45813 | B21: AF | C21: 21JUN-07JUL | D21: DLA-ZRH,CDG-DLA | E21: 00529/06/2025 | F21: NEO INDUSTRIE | G21: BOUNKEU/CHANTAL | H21: DG | J21: 4570920 | K21: 4393120 | L21: =J21-K21 | M21: GOLITE/BLUEBERRY | N21: ETKT 0573006415325 | O21: 3 | T21: 4570920 | U21: =J21-P21-T21 | V21: 45819 | W21: BANQUE | X21: CHQ6417232
A22: 45813 | B22: AF | C22: 21JUN-07JUL | D22: DLA-ZRH,CDG-DLA | E22: 00529/06/2026 | F22: NEO INDUSTRIE | G22: NOUTCHA TCHOMBA/SERGE BRUNO MICHEL | H22: DG | J22: 4570920 | K22: 4393120 | L22: =J22-K22 | M22: GOLITE/BLUEBERRY | N22: ETKT 0573006415326 | O22: 3 | P22: 858160 | T22: 3712760 | U22: =J22-P22-T22 | V22: 10/06/2025 11/08/2025 | W22: BANQUE | X22: CHQ6417232 V/R
A23: 45813 | B23: AF | C23: 21JUN-07JUL | D23: DLA-ZRH,CDG-DLA | E23: 00529/06/2026 | F23: NEO INDUSTRIE | G23: NEOSSI/EMMANUEL | H23: DG | I23: REFUND | J23: 237800 | K23: 0 | L23: =J23-K23 | M23: GOLITE/BLUEBERRY | N23: ETKT 0573006415327 | O23: 3 | P23: 0 | T23: 237800 | U23: =J23-P23-T23 | V23: 45880 | W23: BANQUE | X23: V/R
A24: 45813 | B24: HF | C24: 16JUN-18JUN | D24: DLA-ABJ-DSS | E24: 00539/06/2025 | F24: PIVOTAL | G24: HOT JUNIOR THIERRY | H24: DG | J24: 218500 | K24: 150200 | L24: =J24-K24 | M24: GOLITE | N24: ETKT 483 9588273873 | O24: EXCHANGE | U24: =J24-P24-T24
A25: 45813 | B25: SN | C25: 09JUN-20JUN | D25: BRU-DLA.DSS-BRU | E25: 00538/06/2025 | F25: PIVOTAL | G25: HOT JUNIOR THIERRY | H25: DG | I25: EMD 164000 | J25: 214800 | K25: 164000 | L25: =J25-K25 | M25: NDC | N25: ETKT 0829049042890 | O25: EXCHANGE | U25: =J25-P25-T25
A26: 45813 | B26: WB | C26: 14JUL-26AUG | D26: DLA-CDG-DLA | E26: 00540/06/2025 | F26: MRS NJIKEU | G26: .FEUNKEU BEUNKEU EPSE NJIKEU/YVETTE GEORGETTE MRS | H26: MME HEUNA | J26: 377600 | K26: 356420 | L26: =J26-K26 | M26: AMADEUS | N26: ETKT 459 6376948837 | T26: 377600 | U26: =J26-P26-T26 | V26: 45813 | W26: CAISSE
A27: 45813 | B27: WB | C27: 14JUL-26AUG | D27: DLA-CDG-DLA | E27: 00540/06/2025 | F27: MRS NJIKEU | G27: NJIKEU/CLAUDE MR | H27: MME HEUNA | J27: 377600 | K27: 356420 | L27: =J27-K27 | M27: AMADEUS | N27: ETKT 459 6376948836 | T27: 377600 | U27: =J27-P27-T27 | V27: 45813 | W27: CAISSE
A28: 45813 | B28: J7 | C28: 08JUN. | D28: DLA-SSG | E28: 00541/06/2025 | F28: BANGE BANK | G28: ATANGANA OYEBE/GABRIEL SERGE | H28: DG | J28: 247920 | K28: 191500 | L28: =J28-K28 | M28: J7 | N28: ETKT 22724323139 | U28: =J28-P28-T28
A29: 45813 | B29: ET | C29: 06JUN-22JUN | D29: DLA-SZX-DLA | E29: 00542/06/2025 | F29: AFS | G29: MAGOUDAYA/DAVID MR | H29: DG | J29: 985820 | K29: 908920 | L29: =J29-K29 | M29: B2B | N29: ETKT 0712153064004 | T29: 985820 | U29: =J29-P29-T29 | V29: 45834 | W29: v/r
A30: 45813 | B30: ET | C30: 06JUN-22JUN | D30: DLA-SZX-DLA | E30: 00542/06/2025 | F30: AFS | G30: MOTTO DIN DIKA EPSE NGAMBY/STEPHANIE FAL LONE MRS | H30: DG | J30: 985820 | K30: 908920 | L30: =J30-K30 | M30: B2B | N30: ETKT 0712153064002 | T30: 985820 | U30: =J30-P30-T30 | V30: 45834 | W30: v/r
A31: 45814 | B31: SN | C31: 02JUL-13AUG | D31: DLA-CDG-DLA | E31: 00544/06/2025 | F31: CANAL+ | G31: YOHANN PAUL TAMBA ZAPO (YTH) | H31: DG | I31: 1049600 | J31: 1889920 | K31: 1381420 | L31: =J31-K31 | M31: NDC | N31: ETKT 0829049042893 | T31: 1889920 | U31: =J31-P31-T31 | V31: 45845 | W31: v/r
A32: 45814 | B32: SN | C32: 02JUL-13AUG | D32: DLA-CDG-DLA | E32: 00544/06/2025 | F32: CANAL+ | G32: WINNER ELIAN TAMBA NDAYA (YTH) | H32: DG | I32: 1049600 | J32: 1889920 | K32: 1381420 | L32: =J32-K32 | M32: NDC | N32: ETKT 0829049042891 | T32: 1889920 | U32: =J32-P32-T32 | V32: 45845 | W32: V/R
A33: 45814 | B33: SN | C33: 02JUL-13AUG | D33: DLA-CDG-DLA | E33: 00544/06/2025 | F33: CANAL+ | G33: MRS MITA MIMI NTUMBA NDAYA EPSE TAMBA (ADT) | H33: DG | I33: 1049600 | J33: 1889920 | K33: 1381420 | L33: =J33-K33 | M33: NDC | N33: ETKT 0829049042892 | T33: 1889920 | U33: =J33-P33-T33 | V33: 45845 | W33: V/R
A34: 45814 | H34: DG | J34: 2650420 | K34: 2650420 | M34: GOLITE | O34: VOIDEER | U34: =J34-P34-T34
A35: 45814 | B35: TK | C35: 10JUN-13JUN | D35: DLA-DTW-DLA | E35: 00543/06/2025 | F35: SAAR | G35: KAGOU/GEORGES LEOPOLD MR | H35: DG | I35: 1910500 | J35: 2770920 | K35: 2650420 | L35: =J35-K35 | M35: GOLITE | N35: ETKT 235 9588273875 | O35: 4 | U35: =J35-P35-T35 | Y35: 65701 | Z35: IPE ISUANCE
A36: 45815 | B36: HF | C36: 08JUN. | D36: DLA-DSS | E36: 00545/06/2025 | F36: MR OUSMAN | G36: OUSMAN/KEVIN BABILA | H36: MME GLADYS | I36: 309600 | J36: 515920 | K36: 485320 | L36: =J36-K36 | M36: GOLITE | N36: ETKT 483 9588273876 | O36: 2 | P36: 277000 | T36: 238920 | U36: =J36-P36-T36 | V36: 45819 | W36: CAISSE | Z36: 2,398,220
A37: 45817 | B37: HF | C37: 11JUN-16JUN | D37: ABJ-DLA-ABJ | E37: 00546/06/2025 | F37: PIVOTAL | G37: APHING KOUASSI/LYNDA | H37: DG | J37: 25000 | K37: 0 | L37: =J37-K37 | M37: AMADEUS | N37: ETKT 483 6376951395 | O37: EXCHANGE | U37: =J37-P37-T37
A38: 45817 | B38: HF | C38: 10JUN-14JUN | D38: DLA-ABJ-DLA | E38: 00530/06/2025 | F38: NEO INDUSTRIE | G38: NGAHANG FONGANG/JAURES LEOVANNI | H38: DG | I38: 447700 | J38: 882920 | K38: 797220 | L38: =J38-K38 | M38: GOLITE | N38: ETKT 483 9588273878 | O38: 2 | T38: 882920 | U38: =J38-P38-T38 | V38: 45818 | W38: BANQUE | X38: CHQ 6417232
A39: 45817 | B39: HF | C39: 10JUN-14JUN | D39: DLA-ABJ-DLA | E39: 00530/06/2025 | F39: NEO INDUSTRIE | G39: BEUTKA NGNOUNEWOU/SERGES BERTRAND | H39: DG | I39: 447700 | J39: 882920 | K39: 797220 | L39: =J39-K39 | M39: GOLITE | N39: ETKT 483 9588273879 | O39: 2 | T39: 882920 | U39: =J39-P39-T39 | V39: 45818 | W39: BANQUE | X39: CHQ 6417232
A40: 45817 | B40: KP | C40: 12JUN. | D40: COO-DLA | E40: 00547/06/2025 | F40: M NGAKO | G40: FEPPA NANA/LYDIE GWENAELLE | H40: DG | I40: 386000 | J40: 722900 | K40: 622600 | L40: =J40-K40 | M40: GOLITE | N40: ETKT 032 9588273877 | O40: 2 | T40: 722900 | U40: =J40-P40-T40 | V40: 45828 | W40: CAISSE
A41: 45819 | B41: KP | C41: 12JUN-15JUN | D41: DLA-NDJ-DLA | E41: 00548/06/2025 | F41: CANAL + | G41: EHAK ENDEKSOBO/FRANCK LOIC MR | H41: DG | I41: 145800 | J41: 756805 | K41: 412005 | L41: =J41-K41 | M41: GOLITE | N41: ETKT 032 9588273877 | O41: 2 | T41: 756805 | U41: =J41-P41-T41 | V41: 45880 | W41: v/r
A42: 45819 | B42: AF | C42: 11JUN-16JUN | D42: DLA-CDG-DLA | E42: 00549/06/2025 | F42: MR NGUEMDZI | G42: NGUEMDZI TSOPKENG/GASTON LAURICE | H42: MME GLADYS | I42: 387200 | J42: 770920 | K42: 702420 | L42: =J42-K42 | M42: GOLITE | N42: ETKT 057 9588273881 | O42: 2 | P42: 500000 | T42: 270920 | U42: =J42-P42-T42 | V42: 07/07/2025 22/07/2025 | W42: CAISSE
A43: 45819 | B43: WB | C43: 25JUN-12AUG | D43: DLA-CDG-DLA | E43: 00550/06/2025 | F43: MRS MANDENG | G43: MANDENG/THERESE PATRICIA MRS | H43: MME HEUNA | J43: 457220 | K43: 427220 | L43: =J43-K43 | M43: AMADEUS | N43: ETKT 459 6376957309 | T43: 457220 | U43: =J43-P43-T43 | V43: 45947 | W43: CAISSE
A44: 45819 | B44: WB | C44: 25JUN-12AUG | D44: DLA-CDG-DLA | E44: 00550/06/2025 | F44: MRS MANDENG | G44: LOURDES DIVINA G/MANDENG B(CHD/30JUN15) | H44: MME HEUNA | J44: 457220 | K44: 427220 | L44: =J44-K44 | M44: AMADEUS | N44: ETKT 459 6376957308 | P44: 42780 | U44: =J44-P44-T44 | V44: 45947 | W44: CAISSE
A45: 45819 | B45: WB | C45: 25JUN-12AUG | D45: DLA-CDG-DLA | E45: 00550/06/2025 | F45: MRS MANDENG | G45: CHRIS KYLLIAN MICHEL/MANDENG(CHD/16JUL18) | H45: MME HEUNA | J45: 457220 | K45: 427220 | L45: =J45-K45 | M45: AMADEUS | N45: ETKT 459 6376957307 | U45: =J45-P45-T45
A46: 45819 | B46: AF | C46: 12JUN-06JUL | D46: DLA-CDG-DLA | E46: 00552/06/2025 | F46: MR TESSA | G46: TESSA/SIMON JEAN EMMANUEL MR | H46: DG | I46: 650200 | J46: 1028900 | K46: 958420 | L46: =J46-K46 | M46: GOLITE | N46: ETKT 057 9588273882 | O46: 2 | Q46: 76500 | R46: 580000 | U46: =J46-P46-Q46-R46-T46 | V46: 18/09/2025 24/09/2025 | W46: CAISSE
A47: 45819 | B47: L6 | C47: 18JUN, | D47: DSS-NKC | E47: 00551/06/2025 | F47: PIVOTAL | G47: HOT/JUNIOR THIERRY MR | H47: DG | J47: 268600 | K47: 221000 | L47: =J47-K47 | M47: AMADEUS/BLUEBERRY | N47: ETKT 495 2871429707 | U47: =J47-P47-T47
A48: 45819 | B48: AF | C48: 20JUN, | D48: NKC-ZYR | E48: 00553/06/2025 | F48: PIVOTAL | G48: HOT/JUNIOR THIERRY MR | H48: DG | J48: 68900 | K48: 0 | L48: =J48-K48 | M48: AMADEUS | N48: ETKT 057 6376957496 | O48: REFUND | P48: =K48 | V48: =V47+T48+U48-P48 -> 25569.042
A49: 45819 | B49: AF | C49: 12JUN-18JUN | D49: DLA-CDG-DLA | E49: 00554/06/2025 | F49: MR NGUEMDZI | G49: NGUEMDZI TSOPKENG/GASTON LAURICE | H49: MME GLADYS | I49: 0 | J49: 151200 | K49: 131200 | L49: =J49-K49 | M49: GOLITE | N49: ETKT 057 9588273883 | O49: EXCHANGE | T49: 151200 | U49: =J49-P49-T49 | V49: 45834 | W49: CAISSE
A50: 45820 | B50: AF | C50: 15JUN-22JUN | D50: DLA-CDG-DLA | E50: 00604/06/2025 | F50: HORUS | G50: MARIE LAURE ENAMA | H50: DG | J50: 3489000 | K50: 822500 | L50: =J50-K50 | M50: AF | N50: ETKT 057 230 091 690 0 | P50: 1672705 | T50: 1816295 | U50: =J50-P50-T50 | V50: 04/07/2025 18/07/2025 | W50: v/r
A51: 45820 | B51: AF | C51: 15AUG-20DEC | D51: CDG-IAD-CDG | E51: 00561/06/2025 | F51: SAFARI LOGISTICS | G51: FOUOZING/ZARA JANELLE MS | H51: DG | J51: 986700 | K51: 916700 | L51: =J51-K51 | M51: AMADEUS | N51: ETKT 057 6376958961 | T51: 986700 | U51: =J51-P51-T51 | V51: 45901 | W51: CAISSE
A52: 45820 | B52: ET | C52: 01JUL-14JUL | D52: DLA-EWR-DLA | E52: 00560/06/2025 | F52: AFS | G52: DJOUKENG/CLEMENT GAIMA MR | H52: DG | J52: 786800 | K52: 719720 | L52: =J52-K52 | M52: B2B | N52: ETKT 0712153199138 | T52: 786800 | U52: =J52-P52-T52 | V52: 45845 | W52: v/r
A53: 45820 | B53: MS | C53: 09JUL-19AUG | D53: EWR-DLA-EWR | E53: 00559/06/2025 | F53: AFS | G53: ZEBAZE/PIERRE ROGER MR | H53: DG | J53: 838920 | K53: 778220 | L53: =J53-K53 | M53: AMADEUS | N53: ETKT 077 2986846014 | T53: 838920 | U53: =J53-P53-T53 | V53: 45834 | W53: v/r
A54: 45820 | B54: QC | C54: 17JUN-18JUN | D54: DLA-NSI-DLA | E54: 00558/06/2025 | F54: CANAL+ | G54: NGO NONDJOCK/DAMARIS PATIENCE MRS | H54: DG | J54: 119500 | K54: 69740 | L54: =J54-K54 | M54: KIU | N54: ETKT 0400300037088 | U54: =J54-P54-T54 | W54: v/r
A55: 45820 | B55: AF | C55: 12JUN-19JUN-01JUL | D55: NSI-MRS-CDG-NSI | E55: 00557/06/2025 | F55: CANAL+ | G55: MOUSSI/FRANCK JUNIOR MR | H55: DG | I55: 556100 | J55: 1235920 | K55: 895220 | L55: =J55-K55 | M55: GOLITE | N55: ETKT 057 9588273885 | O55: 4 | T55: 1235920 | U55: =J55-P55-T55 | V55: 45845 | W55: v/r
A56: 45820 | B56: AF | C56: 13JUN-10SEP | D56: CDG-NSI-CDG | E56: 00556/06/2025 | F56: M NGATCHOU | G56: ABENG MBARGA/MARIANE OLIVIA MRS | H56: DG | I56: 792400 | J56: 1379800 | K56: 1103220 | L56: =J56-K56 | M56: GOLITR | N56: ETKT 057 9588273884 | O56: 2 | T56: 1380000 | U56: =J56-P56-T56 | V56: 45828 | W56: CAISSE
A57: 45820 | B57: SN | C57: 19JUN-30JUN | D57: DLA-CDG-DLA | E57: 00555/06/2025 | F57: MRS ESSO | G57: NGO BAYANAK EP KONGUE ESSO/BERNADETTE MARINA | H57: DG | I57: 1716600 | J57: 2452920 | K57: 2208720 | L57: =J57-K57 | M57: NDC | N57: ETKT 0829049042894 | P57: 900000 | U57: =J57-P57-T57 | V57: 45825 | W57: CAISSE
A58: 45821 | B58: AF | C58: 13JUN-20JUN | D58: DLA-CDG-DLA | E58: 00564/06/2025 | F58: MR NGUEMDZI | G58: NGUEMDZI TSOPKENG/GASTON LAURICE | H58: MME GLADYS | I58: 0 | J58: 315700 | K58: 295700 | L58: =J58-K58 | M58: GOLITE | N58: ETKT 057 9588273886 | O58: EXCHANGE | T58: 315700 | U58: =J58-P58-T58 | V58: 45824 | W58: CAISSE
A59: 45821 | B59: AF | C59: 15JUN-18JUN | D59: DLA-CDG-DLA | F59: MR ONANA | G59: SYLLA/WOROKHYA MRS | H59: DG | I59: 3666200 | J59: 5089320 | K59: 4503720 | L59: =J59-K59 | M59: GOLITE | N59: ETKT 057 9588273887 | O59: 2 | P59: 1300000 | T59: 3789320 | U59: =J59-P59-T59 | V59: 13/06/2025 25/06/2025 | W59: CAISSE
A60: 45821 | B60: SN | C60: 22AUG. | D60: DLA-CDG | E60: 00563/06/2025 | F60: ETUDIANT IUC | G60: DJOUAKA DJOUTSOP/BRIAN WESLEY | H60: DG | J60: 927920 | K60: 890320 | L60: =J60-K60 | M60: NDC | N60: ETKT 0829049042895 | T60: 927920 | U60: =J60-P60-T60 | V60: 45820 | W60: CAISSE
A61: 45821 | B61: SN | C61: 19JUN-07JUL | D61: DLA-CDG-DLA | E61: 00562/06/2025 | F61: HARVEST | G61: KAMGAING TAASSI/MARC ETIENNE MR | H61: DG | I61: 1835100 | J61: 2387920 | K61: 2327220 | L61: =J61-K61 | M61: NDC | N61: ETKT 0829049042896 | T61: 2387920 | U61: =J61-P61-T61 | V61: 45855 | W61: v/r
A62: 45822 | B62: ET | C62: 20JUN-29AUG | D62: NSI-YYZ-NSI | E62: 00565/06/2025 | F62: MRS DJUMMO | G62: ZE EPSE DJUMMO/MARTHE GERTRUDE MRS | H62: DG | I62: 3528900 | J62: 4425700 | K62: 4226720 | L62: =J62-K62 | M62: GOLITE | N62: ETKT 071 9588273888 | O62: 4 | T62: 4425700 | U62: =J62-P62-T62 | V62: 45840 | W62: CAISSE
A63: 45823 | B63: KP | C63: 20JUN. | D63: NDJ-DLA | E63: 00566/06/2025 | F63: CANAL + | G63: EHAK ENDEKSOBO/FRANCK LOIC MR | H63: DG | I63: 0 | J63: 199900 | K63: 30000 | L63: =J63-K63 | M63: GOLITE | N63: ETKT 032 9588273889 | O63: EXCHANGE | T63: 199900 | U63: =J63-P63-T63 | V63: 45880 | W63: v/r
A64: 45824 | B64: AF | C64: 17JUN-22JUN | D64: ABJ-CDG-ABJ | E64: 00567/06/2025 | F64: MME MBAMBATH | G64: NGO BASOP EPSE MBAMBATH/DANIELE VALERIE MRS | H64: DG | J64: 871700 | K64: 827800 | L64: =J64-K64 | M64: AMADEUS | N64: ETKT 0572986848496 | P64: 500000 | Q64: 275000 | T64: 96700 | U64: =J64-P64-Q64-T64 | V64: 16/06/2025 17/07/2025 23/09/2025 | W64: CAISSE
A65: 45825 | B65: SN | C65: 27JUL-30AUG | D65: DLA-CDG-DLA | E65: 00569/06/2025 | F65: CABINET DENTAIRE G2 | G65: MRS JEANNE CLAIRE SIMO KAMDEM (ADT) | H65: DG | J65: 2027900 | K65: 1937420 | L65: =J65-K65 | M65: NDC | N65: ETKT 0829049042897 | P65: 2021500 | T65: 6400 | U65: =J65-P65-T65 | V65: 45840 | W65: CAISSE
A66: 45825 | B66: KP | C66: 12JUL-17AUG | D66: DLA-LFW-DLA | E66: 00570/06/2025 | F66: CANAL+ | G66: GNABA/KOKOU MAWOUSSE MR | H66: DG | I66: 174000 | J66: 685920 | K66: 421220 | L66: =J66-K66 | N66: ETKT 032 9588273894 | O66: 2 | T66: 685920 | U66: =J66-P66-T66 | V66: 45845 | W66: v/r
A67: 45825 | B67: KP | C67: 12JUL-23AUG | D67: DLA-LFW-DLA | E67: 00570/06/2025 | F67: CANAL+ | G67: YOKOR EPSE GNABA/KOSSIWAVI | H67: DG | J67: 685920 | K67: 525720 | L67: =J67-K67 | N67: ETKT 032 9588273890 | O67: 2 | T67: 685920 | U67: =J67-P67-T67 | V67: 45845 | W67: v/r
A68: 45825 | B68: KP | C68: 12JUL-23AUG | D68: DLA-LFW-DLA | E68: 00570/06/2025 | F68: CANAL+ | G68: GNABA/KODJO GODWIN | H68: DG | J68: 685920 | K68: 525720 | L68: =J68-K68 | N68: ETKT 032 9588273891 | O68: 2 | T68: 685920 | U68: =J68-P68-T68 | V68: 45845 | W68: v/r
A69: 45825 | B69: KP | C69: 12JUL-23AUG | D69: DLA-LFW-DLA | E69: 00570/06/2025 | F69: CANAL+ | G69: GNABA/KOKOU BLESSING*P-C11 | H69: DG | J69: 588920 | K69: 443120 | L69: =J69-K69 | N69: ETKT 032 9588273892 | O69: 2 | T69: 588920 | U69: =J69-P69-T69 | V69: 45845 | W69: v/r
A70: 45825 | B70: KP | C70: 12JUL-23AUG | D70: DLA-LFW-DLA | E70: 00570/06/2025 | F70: CANAL+ | G70: GNABA/GRACE EMMANUELLE*P-C07 | H70: DG | J70: 588920 | K70: 443120 | L70: =J70-K70 | N70: ETKT 032 9588273893 | O70: 2 | T70: 588920 | U70: =J70-P70-T70 | V70: 45845 | W70: v/r
A71: 45825 | B71: EK | C71: 20JUN-10SEP | D71: ABJ-DXB-ABJ | E71: 00568/06/2025 | F71: MR ONANA | G71: LOHOUES YEMELY EMMANUELLE JESUS | H71: DG | J71: 10389900 | K71: 9900000 | L71: =J71-K71 | N71: ETKT 1763089630724 | P71: 6210680 | T71: 4179220 | U71: =J71-P71-T71 | V71: 25/06/2025 10/07/2025 | W71: CAISSE
A72: 45826 | B72: KP | C72: 22JUN-26JUN | D72: DLA-BGF-DLA | E72: 00572/06/2025 | F72: BANGE BANK | G72: OBIANG NCHAMA/JOSE MIGUEL MR | H72: DG | I72: 161800 | J72: 597920 | K72: 494755 | L72: =J72-K72 | M72: GOLITE | N72: ETKT 032 9588273895 | O72: 2 | U72: =J72-P72-T72
A73: 45826 | B73: KP | C73: 22JUN-26JUN | D73: DLA-BGF-DLA | E73: 00572/06/2025 | F73: BANGE BANK | G73: NTSAMA/GUY BERTRAND MR | H73: DG | I73: 161800 | J73: 597920 | K73: 494755 | L73: =J73-K73 | M73: GOLITE | N73: ETKT 032 9588273896 | O73: 2 | U73: =J73-P73-T73
A74: 45826 | B74: WB | C74: 22JUN-29JUN | D74: DLA-KGL-DLA | E74: 00571/06/2025 | F74: CANAL+ | G74: EMENE ALOSSA/ELISABETH CONCORDE | H74: DG | I74: 201500 | J74: 483820 | K74: 383020 | L74: =J74-K74 | M74: GOLITE | N74: ETKT 459 9588273897 | O74: 2 | U74: =J74-P74-T74
A75: 45826 | B75: WB | C75: 22JUN-29JUN | D75: DLA-KGL-DLA | E75: 00571/06/2025 | F75: CANAL+ | G75: BETBIA DJONOU/ROLANDE MRS | H75: DG | I75: 201500 | J75: 483820 | K75: 383020 | L75: =J75-K75 | M75: GOLITE | N75: ETKT 459 9588273898 | O75: 2 | U75: =J75-P75-T75
A76: 45827 | B76: KP | C76: 24JUN-27JUN | D76: DLA-CKY-DLA | E76: 00574/06/2025 | F76: BEKO | G76: BEUMO JAZE/BRICE PATRICK MR | H76: DG | I76: 1504900 | J76: 1957500 | K76: 1897520 | L76: =J76-K76 | M76: GOLITE | N76: ETKT 483 3006427050 | O76: 4 | T76: 1957500 | U76: =J76-P76-T76 | V76: 45833 | W76: v/r
A77: 45827 | B77: KP | C77: 24JUN-27JUN | D77: DLA-CKY-DLA | E77: 00574/06/2026 | F77: BEKO | G77: NJAMFA/TIARA MARIE SHILLEH MRS | H77: DG | I77: 510000 | J77: 867820 | K77: 822620 | L77: =J77-K77 | M77: GOLITE | N77: ETKT 483 3006427051 | O77: 4 | T77: 867820 | U77: =J77-P77-T77 | V77: 45833 | W77: v/r
A78: 45827 | B78: KP | C78: 24JUN-27JUN | D78: DLA-CKY-DLA | E78: 00574/06/2027 | F78: BEKO | G78: DJANGO KOUAM/RITHA ELISE MAGUY MRS | H78: DG | I78: 510000 | J78: 867820 | K78: 822620 | L78: =J78-K78 | M78: GOLITE | N78: ETKT 483 3006427052 | O78: 4 | T78: 867820 | U78: =J78-P78-T78 | V78: 45833 | W78: v/r
A79: 45827 | B79: KP | C79: 22JUN-24JUN | D79: DLA-BGF-DLA | E79: 00573/06/2025 | F79: BANGE BANK | G79: OBIANG NCHAMA/JOSE MIGUEL MR | H79: DG | J79: 112900 | K79: 30000 | L79: =J79-K79 | M79: GOLITE | N79: ETKT 483 3006427053 | O79: EXCHANGE | U79: =J79-P79-T79
A80: 45827 | B80: KP | C80: 22JUN-24JUN | D80: DLA-BGF-DLA | E80: 00573/06/2025 | F80: BANGE BANK | G80: NTSAMA/GUY BERTRAND MR | H80: DG | J80: 112900 | K80: 30000 | L80: =J80-K80 | M80: GOLITE | N80: ETKT 483 3006427054 | O80: EXCHANGE | U80: =J80-P80-T80
A81: 45827 | B81: ET | C81: 20JUN-13JULDLA-BKK-DLA | E81: 00575/06/2025 | F81: AFS | G81: HENRI WILLIAM/ATINE KEEMOUM MR | H81: DG | J81: 841900 | K81: 524820 | L81: =J81-K81 | M81: AMADEUS | N81: ETKT 071 2986850859 | T81: 841900 | U81: =J81-P81-T81 | V81: 45863 | W81: v/r
A82: 45827 | B82: CZ | C82: 21JUN-12JUL | D82: BKK-SZX-BKK | E82: 00575/06/2025 | F82: AFS | G82: HENRI WILLIAM/ATINE KEEMOUM MR | H82: DG | J82: 841900 | K82: 508350 | L82: =J82-K82 | M82: BLUEBERRY | N82: ETKT 784 6075894477 | T82: 841900 | U82: =J82-P82-T82 | V82: 45863 | W82: V/R
A83: 45827 | B83: ET | C83: 20JUN-13JULDLA-BKK-DLA | E83: 00575/06/2025 | F83: AFS | G83: SENGUIM FAI AYUNI/EPSE CHE FUH MRS | H83: DG | J83: 841900 | K83: 524820 | L83: =J83-K83 | M83: AMADEUS | N83: ETKT 071 2986850860 | T83: 841900 | U83: =J83-P83-T83 | V83: 45863 | W83: V/R
A84: 45827 | B84: CZ | C84: 21JUN-12JUL | D84: BKK-SZX-BKK | E84: 00575/06/2025 | F84: AFS | G84: SENGUIM FAI AYUNI/EPSE CHE FUH MRS | H84: DG | J84: 841900 | K84: 508350 | L84: =J84-K84 | M84: BLUEBERRY | N84: ETKT 784 6075894478 | T84: 841900 | U84: =J84-P84-T84 | V84: 45863 | W84: v/r
A85: 45828 | B85: HF | C85: 21JUN-28JUN | D85: ABJ-DLA-ABJ | E85: 00577/06/2025 | F85: MR NGAKO | G85: DJAMEN OLOMO/ROLAND MR | H85: DG | I85: 447700 | J85: 897900 | K85: 797220 | L85: =J85-K85 | M85: GOLITE | N85: ETKT 483 3006427055 | O85: 2 | T85: 897900 | U85: =J85-P85-T85 | V85: 45838 | W85: CAISSE
A86: 45828 | B86: AF | C86: 18JUL-13AUG | D86: DLA-CDG-DLA | E86: 00578/06/2025 | F86: CANAL+ | G86: MR TAMBA ZAPO/PAUL ZEPHYRIN | H86: DG | J86: 299920 | K86: 199300 | L86: =J86-K86 | M86: GOLITE | N86: ETKT 057 3006427056 | O86: EXCHANGE | U86: =J86-P86-T86
A87: 45828 | B87: AF | C87: 21JUN-05JUL | D87: DLA-ZRH,CDG-DLA | E87: 00576/06/2025 | F87: NEO INDUSTRIE | G87: BOUNKEU/CHANTAL | H87: DG | I87: 0 | J87: 199920 | K87: 0 | L87: =J87-K87 | M87: GOLITE/BLUEBERRY | N87: ETKT 0573006415325 | O87: EXCHANGE | T87: 199920 | U87: =J87-P87-T87 | V87: 45880 | W87: BANQUE | X87: V/R
A88: 45829 | B88: HF | C88: 22JUN. | D88: PNR-DLA. | E88: 00579/06/2025 | F88: MR ONANA | G88: MADECA/ELVINA NATALIA BRAS | H88: DG | I88: 1238300 | J88: 1531450 | K88: 1431450 | L88: =J88-K88 | M88: GOLITE | N88: ETKT 483 3006427057 | T88: 1531450 | U88: =J88-P88-T88 | V88: 45848 | W88: CAISSE
A89: 45829 | B89: HF | C89: 24JUN. | D89: DLA-PNR. | E89: 00579/06/2025 | F89: MR ONANA | G89: MADECA/ELVINA NATALIA BRAS | H89: DG | J89: 175000 | K89: 95000 | L89: 80000 | M89: GOLITE | N89: ETKT 483 3006427058 | O89: REFUND | T89: 175000 | U89: =J89-P89-T89 | V89: 45848 | W89: CAISSE
A90: 45829 | B90: AF | C90: 26JUN-22SEP | D90: YQB-DLA-YQB | E90: 00580/06/2025 | F90: MRS NGANI | G90: NGANI NOUDEM/FRANCINE MRS | H90: DG | I90: 531600 | J90: 1169220 | K90: 1093320 | L90: =J90-K90 | M90: GOLITE | N90: ETKT 057 3006427059 | T90: 1169220 | U90: =J90-P90-T90 | V90: 45838 | W90: CAISSE
A91: 45829 | B91: AF | C91: 26JUN-22SEP | D91: YQB-DLA-YQB | E91: 00580/06/2025 | F91: MRS NGANI | G91: FANCHEY/JULES NOUDEM*P-C11 DOB20MAY14 | H91: DG | I91: 400700 | J91: 998220 | K91: 962420 | L91: =J91-K91 | M91: GOLITE | N91: ETKT 057 3006427061 | P91: 535900 | T91: 462320 | U91: =J91-P91-T91 | V91: 30/06/2025 22/07/2025 | W91: CAISSE
A92: 45829 | B92: AF | C92: 26JUN-22SEP | D92: YQB-DLA-YQB | E92: 00580/06/2025 | F92: MRS NGANI | G92: FANCHEY/JOAKIM NOUDEM*P-C11 DOB20MAY14 | H92: DG | I92: 400700 | J92: 998220 | K92: 962420 | L92: =J92-K92 | M92: GOLITE | N92: ETKT 057 3006427063 | P92: 537680 | T92: 460540 | U92: =J92-P92-T92 | V92: 22/07/2025 12/09/2025 | W92: CAISSE
A93: 45830 | B93: AF | C93: 27JUN-23AUG | D93: DLA-CDG-DLA | E93: 00581/06/2025 | F93: MR ONANA | G93: BELIBY/MFOUMOU LYSETTE ESTHER MRS | H93: DG | I93: 2357000 | J93: 3607720 | K93: 3194520 | L93: =J93-K93 | M93: GOLITE | N93: ETKT 057 3006427065 | T93: 3607720 | U93: =J93-P93-T93 | V93: 45848 | W93: CAISSE
A94: 45831 | B94: QC | C94: 23JUN. | D94: NSI-DLA | F94: MR ESSENE | G94: MR ASSENE ENDOUGOU/JOSEPH MARTIAL | H94: MR ROMEO | J94: 71870 | K94: 66870 | L94: =J94-K94 | M94: KIU | N94: ETKT 0400300037090 | T94: 77090 | U94: =J94-P94-T94 | V94: 45831 | W94: OM
A95: 45831 | B95: ET | C95: 30JUN-01SEP | D95: DLA-CDG-DLA | E95: 00584/06/2025 | F95: MRS TESSA | G95: TESSA LONZI/YANIS EMMANUEL MR | H95: DG | J95: 769920 | K95: 681920 | L95: =J95-K95 | M95: B2B | N95: ETKT 0712153432516 | P95: 345250 | Q95: 400000 | T95: 24670 | U95: =J95-Q95-P95-T95 | V95: 23/06/2025 30/06/2025 09/07/2025 | W95: BANQUE | X95: CHQ 8465721
A96: 45831 | B96: AF | C96: 24JUN-28JUN | D96: CDG-DLA-CDG | E96: 00586/06/2025 | F96: M. NGATCHOU | G96: MEKONTCHOU TCHAFA/WILLIAM MR | H96: DG | I96: 1307400 | J96: 1840900 | K96: 1615620 | L96: =J96-K96 | M96: GOLITE | N96: ETKT 057 3006427066 | O96: 2 | T96: 1840900 | U96: =J96-P96-T96 | V96: 45835 | W96: CAISSE
A97: 45831 | B97: ET | C97: 26JUN-30JUN | D97: DLA-DXB-DLA | E97: 00585/06/2025 | F97: MRS FRANCA DE SOSSO | G97: TAKAM/DAVID DIDIER DE YOUMESSI MR | H97: DG | I97: 1300300 | J97: 1999520 | K97: 1869520 | L97: =J97-K97 | M97: GOLITE | N97: ETKT 071 3006427067 | O97: 4 | T97: 1999520 | U97: =J97-P97-T97 | V97: 45832 | W97: CAISSE
A98: 45831 | B98: KP | C98: 04JUL. | D98: DLA-DSS | E98: 00583/06/2025 | F98: MA DE MBOPPI | G98: TCHEWA/FRANTZ JORDAN*05MAY02 | H98: DG | I98: 89400 | J98: 351520 | K98: 321520 | L98: =J98-K98 | M98: GOLITE | N98: ETKT 032 3006427068 | O98: 1 | T98: 351520 | U98: =J98-P98-T98 | V98: 45841 | W98: CAISSE
A99: 45832 | B99: AF | C99: 25MAY-28MAY | D99: CDG-DXB-CDG | E99: 00582/06/2025 | F99: HARVEST | G99: PIERRE GUILLAUME JOSEPH LE PAPE | H99: DG | J99: 1213900 | K99: 1162900 | L99: =J99-K99 | M99: AF | N99: ETKT 057 2236278552 | T99: 1213900 | U99: =J99-P99-T99 | V99: 45855 | W99: V/R
A100: 45832 | B100: KP | C100: 08JUL-25AUG | D100: DLA-LFW-DLA | E100: 00590/06/2025 | F100: MME FRANCOISE | G100: NANFAH DJOKUNG/SERGE POCOM MR | H100: DG | J100: 42000 | K100: 42000 | L100: =J100-K100 | M100: GOLITE | N100: ETKT 032 3006427069 | O100: REFUND/2 | U100: =J100-P100-T100
...

Sheet JUILLET
A1: DATE | B1: CIES | C1: PARCOURS | D1: TRAJET | E1: N FACTURE | F1: ENTREPRISE | G1: NOMS/PRENOMS | H1: APPORTEUR | I1: TARIF HT | J1: TC | K1: TM | L1: FS | M1: LIEU ACHAT | N1: NUMERO DU BILLET | O1: NBRE SGTS | P1: AVANCE | Q1: AVANCE 02 | R1: RGLT | S1: SOLDE | T1: DATE RGLT | U1: MODE RGLT | V1: OBS
A2: 45839 | B2: AF | C2: 01JUN-07JUL | D2: DLA-CDG-DLA | E2: 00635/07/2025 | F2: HORUS | G2: ENAMA EPSE ONANA , MARIE LAURE | H2: DG | J2: 375000 | K2: 0 | L2: =J2-K2 | M2: AF | N2: ETKT 0572320681394 | O2: CONSIEGERIE | R2: 375000 | S2: =J2-P2-R2 | T2: 45856 | U2: V/R
A3: 45839 | B3: SN | C3: DLA-CDG | E3: 00631/07/2025 | F3: MR SONE | G3: MR XAVIER YANNICK SONE EKOLO (ADT) | H3: DG | J3: 121900 | K3: 98400 | L3: =J3-K3 | M3: NDC | N3: ETKT 0823511998654 | O3: EXCHANGE | S3: =J3-P3-R3
A4: 45840 | B4: ET | C4: 01AUG-09AUG | D4: DLA-DXB-DLA | E4: 00632/07/2025 | F4: HORUS | G4: AKOA MBALLA EDMOND MODESTE CHRSITIAN | H4: DG | J4: 130000 | K4: 70000 | L4: =J4-K4 | M4: SATGURU | N4: DEMANDE DE VISA | O4: VISA | R4: 130000 | S4: =J4-P4-R4 | T4: 45856 | U4: V/R
A5: 45840 | B5: SN | C5: 20JUL, | D5: CDG-DLA, | E5: 00633/07/2025 | F5: ISTAMA | G5: MR FILIPPO FABBRI (ADT) | H5: DG | I5: 0 | J5: 118200 | K5: 118200 | L5: =J5-K5 | M5: NDC | N5: BAGAGE SUPPLEMENTAIRE | R5: 118200 | S5: =J5-P5-R5 | T5: 45810 | U5: CAISSE
A6: 45840 | B6: SN | C6: 20JUL, | D6: CDG-DLA, | E6: 00633/07/2025 | F6: ISTAMA | G6: MR XAVIER DAVID DREYFUSS (ADT) | H6: DG | I6: 0 | J6: 118200 | K6: 118200 | L6: =J6-K6 | M6: NDC | N6: BAGAGE SUPPLEMENTAIRE | R6: 118200 | S6: =J6-P6-R6 | T6: 45810 | U6: CAISSE
A7: 45840 | B7: AT | C7: 07JUL-03AUG | D7: DLA-ORY-DLA | E7: 00634/07/2025 | F7: MR SAMA | G7: MBANG EPSE SAMA NJOUME/VIRGINIE SORELLE MRS | H7: MME HEUNA | J7: 620820 | K7: 512220 | L7: =J7-K7 | M7: AMADEUS | N7: ETKT 147 2986858802 | R7: 620820 | S7: =J7-P7-R7 | T7: 45840 | U7: CAISSE
A8: 45840 | B8: AT | C8: 07JUL-03AUG | D8: DLA-ORY-DLA | E8: 00634/07/2025 | F8: MR SAMA | G8: SAMA NJOUME/SANYA KRYSTAL MS | H8: MME HEUNA | J8: 620820 | K8: 512220 | L8: =J8-K8 | M8: AMADEUS | N8: ETKT 147 2986858803 | P8: 379180 | R8: 241640 | S8: =J8-P8-R8 | T8: 02/07/2025 26/09/2025 | U8: CAISSE BANQUE | V8: CHQ 0000007
A9: 45840 | B9: AT | C9: 07JUL-03AUG | D9: DLA-ORY-DLA | E9: 00634/07/2025 | F9: MR SAMA | G9: SAMA NJOUME/SASHA MALAIKA MS | H9: MME HEUNA | J9: 620820 | K9: 512220 | L9: =J9-K9 | M9: AMADEUS | N9: ETKT 147 2986858804 | R9: 620820 | S9: =J9-P9-R9 | T9: 45926 | U9: BANQUE | V9: CHQ 0000007
A10: 45841 | B10: TK | C10: 09JUL-24JUL | D10: DLA-DXB-DLA | E10: 00636/07/2025 | F10: ELECT ENGINEERING | G10: KAMGA STEPHANE | H10: DG | J10: 1583520 | K10: 1481320 | L10: =J10-K10 | M10: GOLITE | N10: ETKT 2353006427094 | O10: 4 | R10: 1583520 | S10: =J10-P10-R10 | T10: 45873 | U10: BANQUE | V10: CHQ 8040591
A11: 45841 | B11: EJ | C11: 04JUL, | D11: BZV-DLA | E11: 00638/07/2025 | F11: MR NGAKO | G11: MR. DJAMEN OLOMO ROLAND | H11: DG | J11: 392800 | K11: 270500 | L11: =J11-K11 | M11: SATGURU | N11: ETKT 0002415170103 | R11: 392800 | S11: =J11-P11-R11 | T11: 45925
A12: 45841 | B12: EJ | C12: 04JUL, | D12: BZV-DLA | E12: 00638/07/2025 | F12: MR NGAKO | G12: MRS. EBELA NYANGONO DANA PRIYANKA | H12: DG | J12: 392800 | K12: 270500 | L12: =J12-K12 | M12: SATGURU | N12: ETKT 0002415170104 | R12: 392800 | S12: =J12-P12-R12 | T12: 45925
A13: 45841 | B13: AT | C13: 07JUL-03AUG | D13: DLA-CDG-DLA | E13: 00639/07/2025 | F13: MR SAMA | G13: MBANG EPSE SAMA NJOUME/VIRGINIE SORELLE MRS | H13: MME HEUNA | J13: 73100 | K13: 80800 | L13: =J13-K13 | M13: AMADEUS | N13: ETKT 147 2986860397 | O13: EXCHANGE | R13: 73100 | S13: =J13-P13-R13 | T13: 45926 | U13: BANQUE | V13: CHQ 0000007
A14: 45841 | B14: AT | C14: 07JUL-03AUG | D14: DLA-CDG-DLA | E14: 00639/07/2025 | F14: MR SAMA | G14: SAMA NJOUME/SANYA KRYSTAL MS | H14: MME HEUNA | J14: 73100 | K14: 80800 | L14: =J14-K14 | M14: AMADEUS | N14: ETKT 147 2986860398 | O14: EXCHANGE | R14: 73100 | S14: =J14-P14-R14 | T14: 45926 | U14: BANQUE | V14: CHQ 0000007
A15: 45841 | B15: AT | C15: 07JUL-03AUG | D15: DLA-CDG-DLA | E15: 00639/07/2025 | F15: MR SAMA | G15: SAMA NJOUME/SASHA MALAIKA MS | H15: MME HEUNA | J15: 73100 | K15: 80800 | L15: =J15-K15 | M15: AMADEUS | N15: ETKT 147 2986860399 | O15: EXCHANGE | R15: 73100 | S15: =J15-P15-R15 | T15: 45926 | U15: BANQUE | V15: CHQ 0000007
A16: 45842 | B16: ET | C16: 09AUG-17AUG | D16: NSI-ZNZ-NSI | E16: 00642/07/2025 | F16: DOC ARMELLE | G16: METCHOP NGUEJEU/ARMELE MRS | H16: DG | I16: 349000 | J16: 649920 | K16: 563920 | L16: =J16-K16 | M16: GOLITE | N16: ETKT 071 3006427096 | O16: 4 | R16: 649920 | S16: =J16-P16-R16 | T16: 45846 | U16: CAISSE
A17: 45842 | B17: AF | C17: 11JUL, | D17: CDG-DLA, | E17: 00641/07/2025 | F17: HORUS | G17: ENAMA EPSE ONANA MARIE LAURE | H17: DG | J17: 278800 | K17: 196800 | L17: =J17-K17 | M17: GOLITE/BLUEBERRY | N17: ETKT 0573006415428 | O17: EXCHANGE | R17: 278800 | S17: =J17-P17-R17 | T17: 45856 | U17: V/R
A18: 45842 | B18: AT | C18: 10JUL-09SEP | D18: TUN-DLA-TUN | E18: 00643/07/2025 | F18: MRS LENGUE | G18: LENGUE ENGOME/CHLOE MAIWENN MS | H18: HEUNA MRS | J18: 635000 | K18: 593420 | L18: =J18-K18 | M18: AMADEUS | N18: ETKT 147298660614 | P18: 300000 | R18: 335000 | S18: =J18-P18-R18 | T18: 13/06/2025 04/07/2025 | U18: CAISSE
A19: 45843 | B19: SN,TP | C19: 16JUL-20JULBRU-LIS-BRU | E19: 00644/07/2025 | F19: PIVOTAL | G19: HOT/JUNIOR THIERRY MR | H19: DG | J19: 65600 | K19: 4400 | L19: =J19-K19 | M19: BLUEBERRY | N19: ETKT 0822986861210 | O19: EXCHANGE | S19: =J19-P19-R19
A20: 45844 | B20: SN | C20: 23JUL-17SEP | D20: CDG-DLA-CDG | E20: 00645/07/2025 | F20: CABINET DENTAIRE G2 | G20: GAMGNE GUIADEM/CATHERINE MARCELLE MRS | H20: DG | J20: 2221900 | K20: 2149820 | L20: =J20-K20 | M20: NDC | N20: ETKT 0823511998655 | R20: 2221900 | S20: =J20-P20-R20 | T20: 45861 | U20: CAISSE
A21: 45844 | B21: ET | C21: 25AUG-06SEP | D21: DLA-MAN-DLA | E21: 00646/07/2025 | F21: MR FOLEFACK | G21: FOLEFACK NANDA/GABIN MR | H21: DG | I21: 491500 | J21: 202000 | K21: 95500 | L21: =J21-K21 | M21: GOLITE | N21: ETKT 071 3006427100 | O21: REFUND | R21: 202000 | S21: =J21-P21-R21 | T21: 45915 | U21: BANQUE | V21: CHQ 0183454
A22: 45845 | B22: KP | C22: 10JUL. | D22: SSG-NSI | E22: 00649/07/2025 | F22: DAF BANGE BANK | G22: OBIANG ESIDANG/EMERENCIANA MANGUE | H22: DG | I22: 137900 | J22: 324900 | K22: 224100 | L22: =J22-K22 | M22: GOLITE | N22: ETKT 032 3006427108 | P22: 28160 | R22: 296740 | S22: =J22-P22-R22 | T22: 01/08/2025 12/08/2025 | U22: OM CAISSE
A23: 45845 | B23: AF | C23: 27JUN-07JUL | D23: DLA-CDG-DLA | E23: 00653/07/2025 | F23: HORUS | G23: ONANA CYRILLE BERTRAND | H23: DG | J23: 375000 | K23: 298460 | L23: =J23-K23 | M23: AF | O23: CONSIEGERIE RETOUR | R23: 375000 | S23: =SUM(J23-P23-R23) | T23: 45856 | U23: V/R
A24: 45845 | B24: ET | C24: 09JUL-21DEC | D24: DAM-DLA-DAM | E24: 00648/07/2025 | F24: KALFRELEC | G24: HASSAN KASSIES | H24: DG | J24: 1403920 | K24: 1282320 | L24: =J24-K24 | M24: AMADEUS/BLUEBERRY | N24: ETKT -0712986861279 | S24: =J24-P24-R24
A25: 45845 | B25: ET | C25: 18JUL-03AUG | D25: DLA-CDG-DLA | E25: 00637/07/2025 | F25: MR KUSAKININA | G25: KUSAKININA/ALAIN MAKOLA MR | H25: DG | I25: 439200 | J25: 815620 | K25: 765920 | L25: =J25-K25 | M25: GOLITE | N25: ETKT 071 3006427106 | O25: 4 | R25: 815620 | S25: =J25-P25-R25 | T25: 45845 | U25: CAISSE
A26: 45845 | B26: ET | C26: 18JUL-28AUG | D26: DLA-CDG-DLA | E26: 00637/07/2025 | F26: MR KUSAKININA | G26: MAKOLA/KUSAKININA | H26: DG | I26: 266600 | J26: 658520 | K26: 593320 | L26: =J26-K26 | M26: GOLITE | N26: ETKT 071 3006427103 | O26: 4 | R26: 658520 | S26: =J26-P26-R26 | T26: 45845 | U26: CAISSE
A27: 45845 | B27: ET | C27: 18JUL-28AUG | D27: DLA-CDG-DLA | E27: 00637/07/2025 | F27: MR KUSAKININA | G27: MAKOLA/NGUADI TANDIA | H27: DG | I27: 266600 | J27: 658520 | K27: 593320 | L27: =J27-K27 | M27: GOLITE | N27: ETKT 071 3006427101 | O27: 4 | R27: 658520 | S27: =J27-P27-R27 | T27: 45845 | U27: CAISSE
A28: 45845 | B28: ET | C28: 18JUL-28AUG | D28: DLA-CDG-DLA | E28: 00637/07/2025 | F28: MR KUSAKININA | G28: MIANDA/MALANGU MRS | H28: DG | I28: 266600 | J28: 658520 | K28: 593320 | L28: =J28-K28 | M28: GOLITE | N28: ETKT 071 3006427102 | O28: 4 | R28: 658520 | S28: =J28-P28-R28 | T28: 45845 | U28: CAISSE
A29: 45845 | B29: LX | C29: 10JUL-28JUL | D29: YUL-GVA-YUL | E29: 00647/07/2025 | F29: M NGATCHOU | G29: TCHANKOU,OLIVIER MR | H29: DG | J29: 1450000 | K29: 1200000 | L29: =J29-K29 | M29: BLUEBERRY | N29: ETKT 724 6075995713 | P29: 1109500 | Q29: 201240 | R29: 139260 | S29: =J29-Q29-P29-R29 | T29: 45873 | U29: CAISSE OM
A30: 45845 | B30: HF | C30: 10JUL-15JUL-18JUL | D30: DLA-ABJ-DSS-DLA | E30: 00650/07/2025 | F30: SAAR | G30: KAGOU/GEORGES LEOPOLD MR | H30: DG | I30: 1347900 | J30: 1915820 | K30: 1835820 | L30: =J30-K30 | M30: GOLITE | N30: ETKT 483 3006427107 | O30: 4 | R30: 1915820 | S30: =J30-P30-R30 | T30: 45862 | U30: BANQUE | V30: CHQ 8009001
A31: 45845 | B31: AF | C31: 09AUG-16AUG | D31: CDG-ZNZ-CDG | E31: 00651/07/2025 | G31: MOMO METCHOP/GYREL MR | H31: DG | I31: 938700 | J31: 1255700 | K31: 1201700 | L31: =J31-K31 | M31: GOLITE | N31: ETKT 057 3006427104 | O31: 2 | R31: 1255700 | S31: =J31-P31-R31 | T31: 45846 | U31: CAISSE
A32: 45846 | B32: C8 | C32: 09JUL. | D32: DLA-SSG | E32: 00656/07/2025 | F32: BANGE BANK | G32: NTSAMA GUY BERTRAND | H32: DG | J32: 235920 | K32: 185920 | L32: =J32-K32 | M32: C8 | N32: ETKT 4985000356852 | S32: =J32-P32-R32
A33: 45846 | B33: J7 | C33: 10JUL. | D33: SSG-LBV | E33: 00656/07/2025 | F33: BANGE BANK | G33: NTSAMA GUY BERTRAND | H33: DG | J33: 269920 | K33: 216920 | L33: =J33-K33 | M33: J7 | N33: ETKT 27724750173 | S33: =J33-P33-R33
A34: 45846 | B34: J7 | C34: 11JUL. | D34: LBV-NSI | E34: 00656/07/2025 | F34: BANGE BANK | G34: NTSAMA GUY BERTRAND | H34: DG | J34: 297920 | K34: 236600 | L34: =J34-K34 | M34: J7 | N34: ETKT 27724750173 | S34: =J34-P34-R34
A35: 45846 | B35: HF | C35: 14JUL-16JUL | D35: DLA-ABJ-DLA | E35: 00661/07/2025 | F35: HORUS | G35: ONANA CYRILLE BERTRAND | H35: DG | J35: 250000 | K35: 200000 | L35: =J35-K35 | O35: VISA | R35: 250000 | S35: =SUM(J35-P35-R35) | T35: 45856 | U35: V/R
A36: 45846 | B36: AH | C36: 11JUL, | D36: DLA-DXB, | E36: 00658/07/2025 | F36: MIRABELLE TRAVEL AGENCE | G36: LOUMLIYA/ERNEST MR | H36: DG | J36: 231920 | K36: 226920 | L36: =J36-K36 | M36: GOLITE | N36: ETKT 124 3006 427111 | O36: 2 | R36: 231920 | S36: =J36-P36-R36 | T36: 45849 | U36: CAISSE
A37: 45846 | B37: SN | C37: 08SEP-11SEP | D37: DLA-MAD-DLA | E37: 00655/07/2025 | F37: MR DJOUAKA | G37: DJOUAKA/ALAIN ROGER MR | H37: DG | J37: 1483720 | K37: 1222820 | L37: =J37-K37 | M37: NDC | N37: ETKT 0823511998656 | R37: 1483720 | S37: =J37-P37-R37 | T37: 45846 | U37: CAISSE
A38: 45846 | B38: SN | C38: 08SEP, | D38: DLA-MAD, | E38: 00655/07/2025 | F38: MR DJOUAKA | G38: KIFACK BOUKENG EP DJOUAKA/FLORENCE MRS | H38: DG | J38: 1178920 | K38: 956620 | L38: =J38-K38 | M38: NDC | N38: ETKT 0823511998657 | R38: 1178920 | S38: =J38-P38-R38 | T38: 45846 | U38: CAISSE
A39: 45846 | B39: AF | C39: 1SEP-04OCT | D39: MAD-CDG-NSI | E39: 00655/07/2025 | F39: MR DJOUAKA | G39: KIFACK BOUKENG EP DJOUAKA/FLORENCE MRS | H39: DG | J39: 1133920 | K39: 945000 | L39: =J39-K39 | M39: GOLITE | N39: ETKT 0573006427110 | O39: 2 | P39: 1088860 | R39: 45000 | S39: =J39-P39-R39 | T39: 08/07/2025 21/07/2025 | U39: V/R
A40: 45846 | B40: ET | C40: 27JUL, | D40: NSI-DUS | E40: 00657/07/2025 | F40: MR DJOUTSOP | G40: DJOUTSOP KOUAN BRIYEL | H40: MME GLADYS | J40: 450920 | K40: 430620 | L40: =J40-K40 | M40: GOLITE | N40: ETKT 0713006427109 | O40: 3 | R40: 450920 | S40: =J40-P40-R40 | T40: 45846 | U40: CAISSE
A41: 45846 | B41: AF | C41: 09JJUL-13JUL | D41: CDG-DLA-CDG | E41: 00660/07/2025 | F41: MR ONANA | G41: SYLLA/WOROKHYA MRS | H41: DG | J41: 3997020 | K41: 3797020 | L41: =J41-K41 | M41: AMADEUS/BLUEBERRY | N41: ETKT 0572986861350 | R41: 3997020 | S41: =J41-P41-R41 | T41: 45855 | U41: CAISSE
A42: 45846 | B42: AT | C42: 05AUG | D42: NSI-BDL | E42: 00659/07/2025 | F42: MRS KENNE | G42: NIMA, FRANCIS MR | H42: DG | J42: 765920 | K42: 705620 | L42: =J42-K42 | M42: GOLITE | N42: ETKT 1473006427112 | O42: 3 | R42: 765920 | S42: =J42-P42-R42 | T42: 45855 | U42: CAISSE
A43: 45846 | B43: HF | C43: 16JUL-16AUG | D43: DSS-DLA-DSS | E43: 00640/07/2025 | F43: PHARMACIE DE DOUALA | G43: DIOP IBRAHIMA MR | H43: DG | I43: 201500 | J43: 586900 | K43: 533220 | L43: =J43-K43 | M43: AMADEUS | N43: ETKT 4832986863624 | R43: 586900 | S43: =J43-P43-R43 | T43: 45846 | U43: V/R
A44: 45847 | B44: AF | C44: 11JUL-27JUL | D44: DLA-CDG-DLA | F44: MR ONANA | G44: KAMGA TUETE EPSE KAMGNIA/NADINE MRS | H44: DG | J44: 3389000 | K44: 3036220 | L44: 352780 | M44: AMADEUS | N44: ETKT 057 2986864146 | R44: 3389000 | S44: =J44-P44-R44 | T44: 45855 | U44: CAISSE
A45: 45848 | B45: HF | C45: 08AUG-23AUG | D45: DLA-DSS-DLA | F45: CANAL+ | G45: CAMARA/KHADIDIATOU MRS | H45: DG | J45: 771620 | K45: 691820 | L45: =J45-K45 | M45: AMADEUS | N45: ETKT 483 2986864274 | S45: =J45-P45-R45
